Workbook
Name a: #REF!
Name aa: #REF!
Name b: #REF!
Name br: #REF!
Name condition: [1]Data!$B:$C
Name Monthdata: [2]!Month_Table[Monthlist]
Name pop: #REF!
Name tc: #REF!
Name បញ្ជីអនុគណនី: [3]!Table2[[អនុគណនី]:[ឈ្មោះគណនី]]
Name ល.រ: '[4]Costing(ដំបូង)'!$B$283:$B$1048576
Name សរុប: '[4]Costing(ដំបូង)'!$K$283:$K$1048576
Name អនុគណនី: '[4]Costing(ដំបូង)'!$E$283:$E$1048576

Sheet Sheet1
A1: id | B1: name_en | C1: name_kh
A2: 1 | B2: name | C2: name

Sheet PB1Revenue
A1: id | B1: planning_id | C1: chapter_id | D1: account_id | E1: sub_account_id | F1: 1 | G1: 2 | H1: 3 | I1: 4 | J1: imple_income_budget | K1: rule_basic_income_plan | L1: rule_qty_income_plan | M1: rule_budget_credit | N1: imple_budget_semester_1 | O1: imple_budget_semester_2 | P1: annual_estimate | Q1: percentage_rule | R1: basic_income_plan | S1: qty_income_plan | T1: total_income_plan | U1: percentage_income_plan
A2: 1 | B2: 4 | C2: 18 | D2: 90 | E2: =MATCH(H2,'[5]Sub Account'!$E$2:$E$503,0) -> 318 | H2: 70011 | I2: ពន្ធលើប្រាក់ចំណូល (រូបវន្តបុគ្គល) | K2: 2 | L2: 4 | M2: 2 | N2: 2 | O2: 2 | P2: 1 | Q2: =IFERROR(P2/M2,"-") -> 0.5 | R2: 2 | S2: 2 | U2: =IFERROR(T2/M2,"-") -> 0 | V2: =IF(OR(M2>0,T2>0),"ok","-") -> ok
A3: 2 | B3: 4 | C3: 18 | D3: 90 | E3: =MATCH(H3,'[5]Sub Account'!$E$2:$E$503,0) -> 319 | H3: 70012 | I3: ពន្ធលើប្រាក់ចំណូល (នីតិបុគ្គល) | P3: =SUM(N3:O3) -> 0 | Q3: =IFERROR(P3/M3,"-") -> - | U3: =IFERROR(T3/M3,"-") -> - | V3: =IF(OR(M3>0,T3>0),"ok","-") -> -
A4: 3 | B4: 4 | C4: 18 | D4: 90 | E4: =MATCH(H4,'[5]Sub Account'!$E$2:$E$503,0) -> 320 | H4: 70013 | I4: ពន្ធលើប្រាក់បៀវត្ស | P4: =SUM(N4:O4) -> 0 | Q4: =IFERROR(P4/M4,"-") -> - | U4: =IFERROR(T4/M4,"-") -> - | V4: =IF(OR(M4>0,T4>0),"ok","-") -> -
A5: 4 | B5: 4 | C5: 18 | D5: 90 | E5: =MATCH(H5,'[5]Sub Account'!$E$2:$E$503,0) -> 321 | H5: 70014 | I5: ពន្ធលើឈ្នួលចលននិងអចលនទ្រព្យ (រូបវន្តបុគ្គល) | P5: =SUM(N5:O5) -> 0 | Q5: =IFERROR(P5/M5,"-") -> - | U5: =IFERROR(T5/M5,"-") -> - | V5: =IF(OR(M5>0,T5>0),"ok","-") -> -
A6: 5 | B6: 4 | C6: 18 | D6: 90 | E6: =MATCH(H6,'[5]Sub Account'!$E$2:$E$503,0) -> 322 | H6: 70015 | I6: ពន្ធលើឈ្នួលចលននិងអចលនទ្រព្យ (នីតិបុគ្គល) | P6: =SUM(N6:O6) -> 0 | Q6: =IFERROR(P6/M6,"-") -> - | U6: =IFERROR(T6/M6,"-") -> - | V6: =IF(OR(M6>0,T6>0),"ok","-") -> -
A7: 6 | B7: 4 | C7: 18 | D7: 90 | E7: =MATCH(H7,'[5]Sub Account'!$E$2:$E$503,0) -> 323 | H7: 70016 | I7: ពន្ធលើប្រាក់ចំណូលនីតិបុគ្គលជាបន្ទុករបស់រដ្ឋ | P7: =SUM(N7:O7) -> 0 | Q7: =IFERROR(P7/M7,"-") -> - | U7: =IFERROR(T7/M7,"-") -> - | V7: =IF(OR(M7>0,T7>0),"ok","-") -> -
G8: 7002 | I8: ពន្ធប្រយោល | J8: =SUM(J9:J15) -> 0 | K8: =SUM(K9:K15) -> 0 | L8: =SUM(L9:L15) -> 0 | M8: =SUM(M9:M15) -> 0 | N8: =SUM(N9:N15) -> 0 | O8: =SUM(O9:O15) -> 0 | P8: =SUM(P9:P15) -> 0 | Q8: =IFERROR(P8/M8,"-") -> - | R8: =SUM(R9:R15) -> 0 | S8: =SUM(S9:S15) -> 0 | T8: =SUM(T9:T15) -> 0 | U8: =IFERROR(T8/M8,"-") -> - | V8: =IF(OR(M8>0,T8>0),"ok","-") -> -
A9: 8 | B9: 4 | C9: 18 | D9: 91 | E9: =MATCH(H9,'[5]Sub Account'!$E$2:$E$503,0) -> 324 | H9: 70021 | I9: អាករលើផលរបរ | P9: =SUM(N9:O9) -> 0 | Q9: =IFERROR(P9/M9,"-") -> - | U9: =IFERROR(T9/M9,"-") -> - | V9: =IF(OR(M9>0,T9>0),"ok","-") -> -
A10: 9 | B10: 4 | C10: 18 | D10: 91 | E10: =MATCH(H10,'[5]Sub Account'!$E$2:$E$503,0) -> 325 | H10: 70022 | I10: អាករលើតម្លៃបន្ថែម | P10: =SUM(N10:O10) -> 0 | Q10: =IFERROR(P10/M10,"-") -> - | U10: =IFERROR(T10/M10,"-") -> - | V10: =IF(OR(M10>0,T10>0),"ok","-") -> -
A11: 10 | B11: 4 | C11: 18 | D11: 91 | E11: =MATCH(H11,'[5]Sub Account'!$E$2:$E$503,0) -> 326 | H11: 70023 | I11: អាករលើតម្លៃបន្ថែម​លើទំនិញជាបន្ទុករបស់​រដ្ឋ | P11: =SUM(N11:O11) -> 0 | Q11: =IFERROR(P11/M11,"-") -> - | U11: =IFERROR(T11/M11,"-") -> - | V11: =IF(OR(M11>0,T11>0),"ok","-") -> -
A12: 11 | B12: 4 | C12: 18 | D12: 91 | E12: =MATCH(H12,'[5]Sub Account'!$E$2:$E$503,0) -> 327 | H12: 70024 | I12: អាករលើតម្លៃបន្ថែម​លើសេវាជាបន្ទុករបស់​រដ្ឋ | P12: =SUM(N12:O12) -> 0 | Q12: =IFERROR(P12/M12,"-") -> - | U12: =IFERROR(T12/M12,"-") -> - | V12: =IF(OR(M12>0,T12>0),"ok","-") -> -
A13: 12 | B13: 4 | C13: 18 | D13: 91 | E13: =MATCH(H13,'[5]Sub Account'!$E$2:$E$503,0) -> 328 | H13: 70025 | I13: អាករលើតម្លៃបន្ថែម របបនាំចូល (សហគ្រាសប្រេងឥន្ធនៈ) | P13: =SUM(N13:O13) -> 0 | Q13: =IFERROR(P13/M13,"-") -> - | U13: =IFERROR(T13/M13,"-") -> - | V13: =IF(OR(M13>0,T13>0),"ok","-") -> -
A14: 13 | B14: 4 | C14: 18 | D14: 91 | E14: =MATCH(H14,'[5]Sub Account'!$E$2:$E$503,0) -> 329 | H14: 70026 | I14: អាករលើតម្លៃបន្ថែម របបនាំចូល (សហគ្រាសផ្សេងៗទៀត) | P14: =SUM(N14:O14) -> 0 | Q14: =IFERROR(P14/M14,"-") -> - | U14: =IFERROR(T14/M14,"-") -> - | V14: =IF(OR(M14>0,T14>0),"ok","-") -> -
A15: 14 | B15: 4 | C15: 18 | D15: 91 | E15: =MATCH(H15,'[5]Sub Account'!$E$2:$E$503,0) -> 330 | H15: 70027 | I15: អាករលើតម្លៃបន្ថែម របបនាំចូល (ជាបន្ទុករបស់រដ្ឋ) | P15: =SUM(N15:O15) -> 0 | Q15: =IFERROR(P15/M15,"-") -> - | U15: =IFERROR(T15/M15,"-") -> - | V15: =IF(OR(M15>0,T15>0),"ok","-") -> -
G16: 7003 | I16: អាករពិសេស | J16: =SUM(J17:J22) -> 0 | K16: =SUM(K17:K22) -> 0 | L16: =SUM(L17:L22) -> 0 | M16: =SUM(M17:M22) -> 0 | N16: =SUM(N17:N22) -> 0 | O16: =SUM(O17:O22) -> 0 | P16: =SUM(P17:P22) -> 0 | Q16: =IFERROR(P16/M16,"-") -> - | R16: =SUM(R17:R22) -> 0 | S16: =SUM(S17:S22) -> 0 | T16: =SUM(T17:T22) -> 0 | U16: =IFERROR(T16/M16,"-") -> - | V16: =IF(OR(M16>0,T16>0),"ok","-") -> -
A17: 16 | B17: 4 | C17: 18 | D17: 92 | E17: =MATCH(H17,'[5]Sub Account'!$E$2:$E$503,0) -> 331 | H17: 70031 | I17: អាករពិសេសលើទំនិញមួយចំនួន | P17: =SUM(N17:O17) -> 0 | Q17: =IFERROR(P17/M17,"-") -> - | U17: =IFERROR(T17/M17,"-") -> - | V17: =IF(OR(M17>0,T17>0),"ok","-") -> -
A18: 17 | B18: 4 | C18: 18 | D18: 92 | E18: =MATCH(H18,'[5]Sub Account'!$E$2:$E$503,0) -> 332 | H18: 70032 | I18: អាករពិសេសលើទំនិញមួយចំនួន របបនាំចូល (សហគ្រាសប្រេងឥន្ធនៈ) | P18: =SUM(N18:O18) -> 0 | Q18: =IFERROR(P18/M18,"-") -> - | U18: =IFERROR(T18/M18,"-") -> - | V18: =IF(OR(M18>0,T18>0),"ok","-") -> -
A19: 18 | B19: 4 | C19: 18 | D19: 92 | E19: =MATCH(H19,'[5]Sub Account'!$E$2:$E$503,0) -> 333 | H19: 70033 | I19: អាករពិសេសលើទំនិញមួយចំនួន របបនាំចូល (សហគ្រាសផ្សេងៗទៀត) | P19: =SUM(N19:O19) -> 0 | Q19: =IFERROR(P19/M19,"-") -> - | U19: =IFERROR(T19/M19,"-") -> - | V19: =IF(OR(M19>0,T19>0),"ok","-") -> -
A20: 19 | B20: 4 | C20: 18 | D20: 92 | E20: =MATCH(H20,'[5]Sub Account'!$E$2:$E$503,0) -> 334 | H20: 70034 | I20: អាករពិសេសលើសេវាមួយចំនួន | P20: =SUM(N20:O20) -> 0 | Q20: =IFERROR(P20/M20,"-") -> - | U20: =IFERROR(T20/M20,"-") -> - | V20: =IF(OR(M20>0,T20>0),"ok","-") -> -
A21: 20 | B21: 4 | C21: 18 | D21: 92 | E21: =MATCH(H21,'[5]Sub Account'!$E$2:$E$503,0) -> 335 | H21: 70035 | I21: អាករសម្រាប់បំភ្លឺសាធារណៈ | P21: =SUM(N21:O21) -> 0 | Q21: =IFERROR(P21/M21,"-") -> - | U21: =IFERROR(T21/M21,"-") -> - | V21: =IF(OR(M21>0,T21>0),"ok","-") -> -
A22: 21 | B22: 4 | C22: 18 | D22: 92 | E22: =MATCH(H22,'[5]Sub Account'!$E$2:$E$503,0) -> 336 | H22: 70038 | I22: ផ្សេងៗ | P22: =SUM(N22:O22) -> 0 | Q22: =IFERROR(P22/M22,"-") -> - | U22: =IFERROR(T22/M22,"-") -> - | V22: =IF(OR(M22>0,T22>0),"ok","-") -> -
G23: 7004 | I23: អាករលើសេវាដែលបានកំណត់ | J23: =SUM(J24:J25) -> 0 | K23: =SUM(K24:K25) -> 0 | L23: =SUM(L24:L25) -> 0 | M23: =SUM(M24:M25) -> 0 | N23: =SUM(N24:N25) -> 0 | O23: =SUM(O24:O25) -> 0 | P23: =SUM(P24:P25) -> 0 | Q23: =IFERROR(P23/M23,"-") -> - | R23: =SUM(R24:R25) -> 0 | S23: =SUM(S24:S25) -> 0 | T23: =SUM(T24:T25) -> 0 | U23: =IFERROR(T23/M23,"-") -> - | V23: =IF(OR(M23>0,T23>0),"ok","-") -> -
A24: 23 | B24: 4 | C24: 18 | D24: 93 | E24: =MATCH(H24,'[5]Sub Account'!$E$2:$E$503,0) -> 337 | H24: 70045 | I24: អាករលើការស្នាក់នៅ | P24: =SUM(N24:O24) -> 0 | Q24: =IFERROR(P24/M24,"-") -> - | U24: =IFERROR(T24/M24,"-") -> - | V24: =IF(OR(M24>0,T24>0),"ok","-") -> -
A25: 24 | B25: 4 | C25: 18 | D25: 93 | E25: =MATCH(H25,'[5]Sub Account'!$E$2:$E$503,0) -> 338 | H25: 70046 | I25: ពន្ធសត្តឃាត | P25: =SUM(N25:O25) -> 0 | Q25: =IFERROR(P25/M25,"-") -> - | U25: =IFERROR(T25/M25,"-") -> - | V25: =IF(OR(M25>0,T25>0),"ok","-") -> -
G26: 7005 | I26: អាករលើការប្រើប្រាស់ទ្រព្យសម្បត្តិ ឬ ការអនុវត្តសកម្មភាព | J26: =SUM(J27:J29) -> 0 | K26: =SUM(K27:K29) -> 0 | L26: =SUM(L27:L29) -> 0 | M26: =SUM(M27:M29) -> 0 | N26: =SUM(N27:N29) -> 0 | O26: =SUM(O27:O29) -> 0 | P26: =SUM(P27:P29) -> 0 | Q26: =IFERROR(P26/M26,"-") -> - | R26: =SUM(R27:R29) -> 0 | S26: =SUM(S27:S29) -> 0 | T26: =SUM(T27:T29) -> 0 | U26: =IFERROR(T26/M26,"-") -> - | V26: =IF(OR(M26>0,T26>0),"ok","-") -> -
A27: 26 | B27: 4 | C27: 18 | D27: 94 | E27: =MATCH(H27,'[5]Sub Account'!$E$2:$E$503,0) -> 339 | H27: 70053 | I27: ពន្ធប៉ាតង់ | P27: =SUM(N27:O27) -> 0 | Q27: =IFERROR(P27/M27,"-") -> - | U27: =IFERROR(T27/M27,"-") -> - | V27: =IF(OR(M27>0,T27>0),"ok","-") -> -
A28: 27 | B28: 4 | C28: 18 | D28: 94 | E28: =MATCH(H28,'[5]Sub Account'!$E$2:$E$503,0) -> 340 | H28: 70054 | I28: ពន្ធលើមធ្យោបាយដឹកជញ្ជូន និងយានជំនិះគ្រប់ប្រភេទ | P28: =SUM(N28:O28) -> 0 | Q28: =IFERROR(P28/M28,"-") -> - | U28: =IFERROR(T28/M28,"-") -> - | V28: =IF(OR(M28>0,T28>0),"ok","-") -> -
A29: 28 | B29: 4 | C29: 18 | D29: 94 | E29: =MATCH(H29,'[5]Sub Account'!$E$2:$E$503,0) -> 341 | H29: 70055 | I29: ពន្ធលើមធ្យោបាយដឹកជញ្ជូន និង​យានជំនិះគ្រប់ប្រភេទជាបន្ទុករបស់រដ្ឋ | P29: =SUM(N29:O29) -> 0 | Q29: =IFERROR(P29/M29,"-") -> - | U29: =IFERROR(T29/M29,"-") -> - | V29: =IF(OR(M29>0,T29>0),"ok","-") -> -
G30: 7006 | I30: ពន្ធប្រថាប់ត្រា | J30: =SUM(J31:J36) -> 0 | K30: =SUM(K31:K36) -> 0 | L30: =SUM(L31:L36) -> 0 | M30: =SUM(M31:M36) -> 0 | N30: =SUM(N31:N36) -> 0 | O30: =SUM(O31:O36) -> 0 | P30: =SUM(P31:P36) -> 0 | Q30: =IFERROR(P30/M30,"-") -> - | R30: =SUM(R31:R36) -> 0 | S30: =SUM(S31:S36) -> 0 | T30: =SUM(T31:T36) -> 0 | U30: =IFERROR(T30/M30,"-") -> - | V30: =IF(OR(M30>0,T30>0),"ok","-") -> -
A31: 30 | B31: 4 | C31: 18 | D31: 95 | E31: =MATCH(H31,'[5]Sub Account'!$E$2:$E$503,0) -> 342 | H31: 70061 | I31: ពន្ធប្រថាប់ត្រា លើតម្លៃអចលនទ្រព្យចំពោះការផ្ទេរកម្មសិទ្ធិ ឬ សិទ្ធិកាន់កាប់ | P31: =SUM(N31:O31) -> 0 | Q31: =IFERROR(P31/M31,"-") -> - | U31: =IFERROR(T31/M31,"-") -> - | V31: =IF(OR(M31>0,T31>0),"ok","-") -> -
A32: 31 | B32: 4 | C32: 18 | D32: 95 | E32: =MATCH(H32,'[5]Sub Account'!$E$2:$E$503,0) -> 343 | H32: 70062 | I32: ពន្ធប្រថាប់ត្រា លើតម្លៃមធ្យោបាយដឹកជញ្ជូន ឬ យានយន្តចំពោះការផ្ទេរកម្មសិទ្ធិ | P32: =SUM(N32:O32) -> 0 | Q32: =IFERROR(P32/M32,"-") -> - | U32: =IFERROR(T32/M32,"-") -> - | V32: =IF(OR(M32>0,T32>0),"ok","-") -> -
A33: 32 | B33: 4 | C33: 18 | D33: 95 | E33: =MATCH(H33,'[5]Sub Account'!$E$2:$E$503,0) -> 344 | H33: 70063 | I33: ពន្ធប្រថាប់ត្រា លើតម្លៃភាគហ៊ុនចំពោះការផ្ទេរភាគហ៊ុន | P33: =SUM(N33:O33) -> 0 | Q33: =IFERROR(P33/M33,"-") -> - | U33: =IFERROR(T33/M33,"-") -> - | V33: =IF(OR(M33>0,T33>0),"ok","-") -> -
A34: 33 | B34: 4 | C34: 18 | D34: 95 | E34: =MATCH(H34,'[5]Sub Account'!$E$2:$E$503,0) -> 345 | H34: 70064 | I34: ពន្ធប្រថាប់ត្រា លើតម្លៃកិច្ចសន្យាចំពោះការផ្គត់ផ្គង់ទំនិញ ឬ សេវា | P34: =SUM(N34:O34) -> 0 | Q34: =IFERROR(P34/M34,"-") -> - | U34: =IFERROR(T34/M34,"-") -> - | V34: =IF(OR(M34>0,T34>0),"ok","-") -> -
A35: 34 | B35: 4 | C35: 18 | D35: 95 | E35: =MATCH(H35,'[5]Sub Account'!$E$2:$E$503,0) -> 346 | H35: 70065 | I35: ពន្ធប្រថាប់ត្រា លើលិខិតមានលក្ខណៈគតិយុត្ដ | P35: =SUM(N35:O35) -> 0 | Q35: =IFERROR(P35/M35,"-") -> - | U35: =IFERROR(T35/M35,"-") -> - | V35: =IF(OR(M35>0,T35>0),"ok","-") -> -
A36: 35 | B36: 4 | C36: 18 | D36: 95 | E36: =MATCH(H36,'[5]Sub Account'!$E$2:$E$503,0) -> 347 | H36: 70066 | I36: ពន្ធប្រថាប់ត្រាលើការផ្ទេរកម្មសិទ្ធិ ឬ សិទ្ធិ​កាន់កាប់​អចលនទ្រព្យ​ក្នុង​រង្វង់ញាតិ និង​ការអនុគ្រោះពន្ធ ជាបន្ទុករបស់រដ្ឋ | P36: =SUM(N36:O36) -> 0 | Q36: =IFERROR(P36/M36,"-") -> - | U36: =IFERROR(T36/M36,"-") -> - | V36: =IF(OR(M36>0,T36>0),"ok","-") -> -
G37: 7007 | I37: ពន្ធលើអចលនទ្រព្យ | J37: =SUM(J38:J41) -> 0 | K37: =SUM(K38:K41) -> 0 | L37: =SUM(L38:L41) -> 0 | M37: =SUM(M38:M41) -> 0 | N37: =SUM(N38:N41) -> 0 | O37: =SUM(O38:O41) -> 0 | P37: =SUM(P38:P41) -> 0 | Q37: =IFERROR(P37/M37,"-") -> - | R37: =SUM(R38:R41) -> 0 | S37: =SUM(S38:S41) -> 0 | T37: =SUM(T38:T41) -> 0 | U37: =IFERROR(T37/M37,"-") -> - | V37: =IF(OR(M37>0,T37>0),"ok","-") -> -
A38: 37 | B38: 4 | C38: 18 | D38: 96 | E38: =MATCH(H38,'[5]Sub Account'!$E$2:$E$503,0) -> 348 | H38: 70071 | I38: ពន្ធលើអចលនទ្រព្យ (រូបវន្តបុគ្គល) | P38: =SUM(N38:O38) -> 0 | Q38: =IFERROR(P38/M38,"-") -> - | U38: =IFERROR(T38/M38,"-") -> - | V38: =IF(OR(M38>0,T38>0),"ok","-") -> -
A39: 38 | B39: 4 | C39: 18 | D39: 96 | E39: =MATCH(H39,'[5]Sub Account'!$E$2:$E$503,0) -> 349 | H39: 70072 | I39: ពន្ធលើអចលនទ្រព្យ (នីតិបុគ្គល) | P39: =SUM(N39:O39) -> 0 | Q39: =IFERROR(P39/M39,"-") -> - | U39: =IFERROR(T39/M39,"-") -> - | V39: =IF(OR(M39>0,T39>0),"ok","-") -> -
A40: 39 | B40: 4 | C40: 18 | D40: 96 | E40: =MATCH(H40,'[5]Sub Account'!$E$2:$E$503,0) -> 350 | H40: 70073 | I40: ពន្ធលើដីធ្លីមិនបានប្រើប្រាស់ | P40: =SUM(N40:O40) -> 0 | Q40: =IFERROR(P40/M40,"-") -> - | U40: =IFERROR(T40/M40,"-") -> - | V40: =IF(OR(M40>0,T40>0),"ok","-") -> -
A41: 40 | B41: 4 | C41: 18 | D41: 96 | E41: =MATCH(H41,'[5]Sub Account'!$E$2:$E$503,0) -> 351 | H41: 70074 | I41: ពន្ធលើអចលនទ្រព្យ ជាបន្ទុករបស់រដ្ឋ | P41: =SUM(N41:O41) -> 0 | Q41: =IFERROR(P41/M41,"-") -> - | U41: =IFERROR(T41/M41,"-") -> - | V41: =IF(OR(M41>0,T41>0),"ok","-") -> -
G42: 7008 | I42: ចំណូលសារពើពន្ធផ្សេងៗទៀត | J42: =SUM(J43:J44) -> 0 | K42: =SUM(K43:K44) -> 0 | L42: =SUM(L43:L44) -> 0 | M42: =SUM(M43:M44) -> 0 | N42: =SUM(N43:N44) -> 0 | O42: =SUM(O43:O44) -> 0 | P42: =SUM(P43:P44) -> 0 | Q42: =IFERROR(P42/M42,"-") -> - | R42: =SUM(R43:R44) -> 0 | S42: =SUM(S43:S44) -> 0 | T42: =SUM(T43:T44) -> 0 | U42: =IFERROR(T42/M42,"-") -> - | V42: =IF(OR(M42>0,T42>0),"ok","-") -> -
A43: 42 | B43: 4 | C43: 18 | D43: 97 | E43: =MATCH(H43,'[5]Sub Account'!$E$2:$E$503,0) -> 352 | H43: 70081 | I43: ពន្ធតែមប្រិ៍ | P43: =SUM(N43:O43) -> 0 | Q43: =IFERROR(P43/M43,"-") -> - | U43: =IFERROR(T43/M43,"-") -> - | V43: =IF(OR(M43>0,T43>0),"ok","-") -> -
A44: 43 | B44: 4 | C44: 18 | D44: 97 | E44: =MATCH(H44,'[5]Sub Account'!$E$2:$E$503,0) -> 353 | H44: 70082 | I44: ប្រាក់ទោសទណ្ឌសារពើពន្ធ | P44: =SUM(N44:O44) -> 0 | Q44: =IFERROR(P44/M44,"-") -> - | U44: =IFERROR(T44/M44,"-") -> - | V44: =IF(OR(M44>0,T44>0),"ok","-") -> -
F45: 71 | I45: ចំណូលពន្ធលើពាណិជ្ជកម្មក្រៅប្រទេស | J45: =J46+J55 -> 0 | K45: =K46+K55 -> 0 | L45: =L46+L55 -> 0 | M45: =M46+M55 -> 0 | N45: =N46+N55 -> 0 | O45: =O46+O55 -> 0 | P45: =P46+P55 -> 0 | Q45: =IFERROR(P45/M45,"-") -> - | R45: =R46+R55 -> 0 | S45: =S46+S55 -> 0 | T45: =T46+T55 -> 0 | U45: =IFERROR(T45/M45,"-") -> - | V45: =IF(OR(M45>0,T45>0),"ok","-") -> -
G46: 7100 | I46: ពន្ធនិងអាករលើការនាំចូល | J46: =SUM(J47:J54) -> 0 | K46: =SUM(K47:K54) -> 0 | L46: =SUM(L47:L54) -> 0 | M46: =SUM(M47:M54) -> 0 | N46: =SUM(N47:N54) -> 0 | O46: =SUM(O47:O54) -> 0 | P46: =SUM(P47:P54) -> 0 | Q46: =IFERROR(P46/M46,"-") -> - | R46: =SUM(R47:R54) -> 0 | S46: =SUM(S47:S54) -> 0 | T46: =SUM(T47:T54) -> 0 | U46: =IFERROR(T46/M46,"-") -> - | V46: =IF(OR(M46>0,T46>0),"ok","-") -> -
A47: 46 | B47: 4 | C47: 19 | D47: 98 | E47: =MATCH(H47,'[5]Sub Account'!$E$2:$E$503,0) -> 356 | H47: 71001 | I47: ពន្ធគយពីការនាំចូល | P47: =SUM(N47:O47) -> 0 | Q47: =IFERROR(P47/M47,"-") -> - | U47: =IFERROR(T47/M47,"-") -> - | V47: =IF(OR(M47>0,T47>0),"ok","-") -> -
A48: 47 | B48: 4 | C48: 19 | D48: 98 | E48: =MATCH(H48,'[5]Sub Account'!$E$2:$E$503,0) -> 357 | H48: 71002 | I48: កម្រៃពីការងារគយ | P48: =SUM(N48:O48) -> 0 | Q48: =IFERROR(P48/M48,"-") -> - | U48: =IFERROR(T48/M48,"-") -> - | V48: =IF(OR(M48>0,T48>0),"ok","-") -> -
A49: 48 | B49: 4 | C49: 19 | D49: 98 | E49: =MATCH(H49,'[5]Sub Account'!$E$2:$E$503,0) -> 358 | H49: 71003 | I49: ពន្ធគយលើផលិតផលតេលសិលា | P49: =SUM(N49:O49) -> 0 | Q49: =IFERROR(P49/M49,"-") -> - | U49: =IFERROR(T49/M49,"-") -> - | V49: =IF(OR(M49>0,T49>0),"ok","-") -> -
A50: 49 | B50: 4 | C50: 19 | D50: 98 | E50: =MATCH(H50,'[5]Sub Account'!$E$2:$E$503,0) -> 359 | H50: 71004 | I50: អាករបន្ថែមលើផលិតផលតេលសិលាសម្រាប់ថែទាំផ្លូវថ្នល់ | P50: =SUM(N50:O50) -> 0 | Q50: =IFERROR(P50/M50,"-") -> - | U50: =IFERROR(T50/M50,"-") -> - | V50: =IF(OR(M50>0,T50>0),"ok","-") -> -
A51: 50 | B51: 4 | C51: 19 | D51: 98 | E51: =MATCH(H51,'[5]Sub Account'!$E$2:$E$503,0) -> 360 | H51: 71005 | I51: ផលពីការលក់ទំនិញរឹបអូស និងទំនិញគ្មានការទាមទារ | P51: =SUM(N51:O51) -> 0 | Q51: =IFERROR(P51/M51,"-") -> - | U51: =IFERROR(T51/M51,"-") -> - | V51: =IF(OR(M51>0,T51>0),"ok","-") -> -
A52: 51 | B52: 4 | C52: 19 | D52: 98 | E52: =MATCH(H52,'[5]Sub Account'!$E$2:$E$503,0) -> 361 | H52: 71006 | I52: ពិន័យផ្សេងៗលើការនាំចូល | P52: =SUM(N52:O52) -> 0 | Q52: =IFERROR(P52/M52,"-") -> - | U52: =IFERROR(T52/M52,"-") -> - | V52: =IF(OR(M52>0,T52>0),"ok","-") -> -
A53: 52 | B53: 4 | C53: 19 | D53: 98 | E53: =MATCH(H53,'[5]Sub Account'!$E$2:$E$503,0) -> 362 | H53: 71007 | I53: ពន្ធនាំចូល (ជាបន្ទុករបស់រដ្ឋ) | P53: =SUM(N53:O53) -> 0 | Q53: =IFERROR(P53/M53,"-") -> - | U53: =IFERROR(T53/M53,"-") -> - | V53: =IF(OR(M53>0,T53>0),"ok","-") -> -
A54: 53 | B54: 4 | C54: 19 | D54: 98 | E54: =MATCH(H54,'[5]Sub Account'!$E$2:$E$503,0) -> 363 | H54: 71008 | I54: ពន្ធនិងអាករលើការនាំចូលផ្សេងៗ | P54: =SUM(N54:O54) -> 0 | Q54: =IFERROR(P54/M54,"-") -> - | U54: =IFERROR(T54/M54,"-") -> - | V54: =IF(OR(M54>0,T54>0),"ok","-") -> -
G55: 7101 | I55: ពន្ធនិងអាករលើការនាំចេញ | J55: =SUM(J56:J61) -> 0 | K55: =SUM(K56:K61) -> 0 | L55: =SUM(L56:L61) -> 0 | M55: =SUM(M56:M61) -> 0 | N55: =SUM(N56:N61) -> 0 | O55: =SUM(O56:O61) -> 0 | P55: =SUM(P56:P61) -> 0 | Q55: =IFERROR(P55/M55,"-") -> - | R55: =SUM(R56:R61) -> 0 | S55: =SUM(S56:S61) -> 0 | T55: =SUM(T56:T61) -> 0 | U55: =IFERROR(T55/M55,"-") -> - | V55: =IF(OR(M55>0,T55>0),"ok","-") -> -
A56: 55 | B56: 4 | C56: 19 | D56: 99 | E56: =MATCH(H56,'[5]Sub Account'!$E$2:$E$503,0) -> 364 | H56: 71011 | I56: អាករលើការនាំចេញឈើ | P56: =SUM(N56:O56) -> 0 | Q56: =IFERROR(P56/M56,"-") -> - | U56: =IFERROR(T56/M56,"-") -> - | V56: =IF(OR(M56>0,T56>0),"ok","-") -> -
A57: 56 | B57: 4 | C57: 19 | D57: 99 | E57: =MATCH(H57,'[5]Sub Account'!$E$2:$E$503,0) -> 365 | H57: 71012 | I57: អាករលើការនាំចេញកៅស៊ូ | P57: =SUM(N57:O57) -> 0 | Q57: =IFERROR(P57/M57,"-") -> - | U57: =IFERROR(T57/M57,"-") -> - | V57: =IF(OR(M57>0,T57>0),"ok","-") -> -
A58: 57 | B58: 4 | C58: 19 | D58: 99 | E58: =MATCH(H58,'[5]Sub Account'!$E$2:$E$503,0) -> 366 | H58: 71013 | I58: អាករលើការនាំចេញផលិតផលតេលសិលា | P58: =SUM(N58:O58) -> 0 | Q58: =IFERROR(P58/M58,"-") -> - | U58: =IFERROR(T58/M58,"-") -> - | V58: =IF(OR(M58>0,T58>0),"ok","-") -> -
A59: 58 | B59: 4 | C59: 19 | D59: 99 | E59: =MATCH(H59,'[5]Sub Account'!$E$2:$E$503,0) -> 367 | H59: 71014 | I59: អាករលើការនាំចេញទំនិញផ្សេងៗ | P59: =SUM(N59:O59) -> 0 | Q59: =IFERROR(P59/M59,"-") -> - | U59: =IFERROR(T59/M59,"-") -> - | V59: =IF(OR(M59>0,T59>0),"ok","-") -> -
A60: 59 | B60: 4 | C60: 19 | D60: 99 | E60: =MATCH(H60,'[5]Sub Account'!$E$2:$E$503,0) -> 368 | H60: 71016 | I60: ពិន័យផ្សេងៗពីការនាំចេញ | P60: =SUM(N60:O60) -> 0 | Q60: =IFERROR(P60/M60,"-") -> - | U60: =IFERROR(T60/M60,"-") -> - | V60: =IF(OR(M60>0,T60>0),"ok","-") -> -
A61: 60 | B61: 4 | C61: 19 | D61: 99 | E61: =MATCH(H61,'[5]Sub Account'!$E$2:$E$503,0) -> 369 | H61: 71018 | I61: ពន្ធនិងអាករលើការនាំចេញផ្សេងៗ | P61: =SUM(N61:O61) -> 0 | Q61: =IFERROR(P61/M61,"-") -> - | U61: =IFERROR(T61/M61,"-") -> - | V61: =IF(OR(M61>0,T61>0),"ok","-") -> -
F62: ប្រភេទទី២: ចំណូល​មិនមែន​សារពើពន្ធ | J62: =J63+J81+J143+J152+J202+J218 -> 0 | K62: =K63+K81+K143+K152+K202+K218 -> 0 | L62: =L63+L81+L143+L152+L202+L218 -> 0 | M62: =M63+M81+M143+M152+M202+M218 -> 0 | N62: =N63+N81+N143+N152+N202+N218 -> 0 | O62: =O63+O81+O143+O152+O202+O218 -> 0 | P62: =P63+P81+P143+P152+P202+P218 -> 0 | Q62: =IFERROR(P62/M62,"-") -> - | R62: =R63+R81+R143+R152+R202+R218 -> 0 | S62: =S63+S81+S143+S152+S202+S218 -> 0 | T62: =T63+T81+T143+T152+T202+T218 -> 0 | U62: =IFERROR(T62/M62,"-") -> - | V62: =IF(OR(M62>0,T62>0),"ok","-") -> -
F63: 72 | I63: ផលទុននៃទ្រព្យសម្បត្តិរដ្ឋ | J63: =J64+J76 -> 0 | K63: =K64+K76 -> 0 | L63: =L64+L76 -> 0 | M63: =M64+M76 -> 0 | N63: =N64+N76 -> 0 | O63: =O64+O76 -> 0 | P63: =P64+P76 -> 0 | Q63: =IFERROR(P63/M63,"-") -> - | R63: =R64+R76 -> 0 | S63: =S64+S76 -> 0 | T63: =T64+T76 -> 0 | U63: =IFERROR(T63/M63,"-") -> - | V63: =IF(OR(M63>0,T63>0),"ok","-") -> -
G64: 7200 | I64: ផលសម្បទាន | J64: =SUM(J65:J68,J72:J75) -> 0 | K64: =SUM(K65:K68,K72:K75) -> 0 | L64: =SUM(L65:L68,L72:L75) -> 0 | M64: =SUM(M65:M68,M72:M75) -> 0 | N64: =SUM(N65:N68,N72:N75) -> 0 | O64: =SUM(O65:O68,O72:O75) -> 0 | P64: =SUM(P65:P68,P72:P75) -> 0 | Q64: =IFERROR(P64/M64,"-") -> - | R64: =SUM(R65:R68,R72:R75) -> 0 | S64: =SUM(S65:S68,S72:S75) -> 0 | T64: =SUM(T65:T68,T72:T75) -> 0 | U64: =IFERROR(T64/M64,"-") -> - | V64: =IF(OR(M64>0,T64>0),"ok","-") -> -
A65: 64 | B65: 4 | C65: 20 | D65: 100 | E65: =MATCH(H65,'[5]Sub Account'!$E$2:$E$503,0) -> 370 | H65: 72001 | I65: ផលពីនេសាទ | P65: =SUM(N65:O65) -> 0 | Q65: =IFERROR(P65/M65,"-") -> - | U65: =IFERROR(T65/M65,"-") -> - | V65: =IF(OR(M65>0,T65>0),"ok","-") -> -
A66: 65 | B66: 4 | C66: 20 | D66: 100 | E66: =MATCH(H66,'[5]Sub Account'!$E$2:$E$503,0) -> 371 | H66: 72002 | I66: ផលពីព្រៃឈើ | P66: =SUM(N66:O66) -> 0 | Q66: =IFERROR(P66/M66,"-") -> - | U66: =IFERROR(T66/M66,"-") -> - | V66: =IF(OR(M66>0,T66>0),"ok","-") -> -
A67: 66 | B67: 4 | C67: 20 | D67: 100 | E67: =MATCH(H67,'[5]Sub Account'!$E$2:$E$503,0) -> 372 | H67: 72003 | I67: សម្បទានប្រេងកាត | P67: =SUM(N67:O67) -> 0 | Q67: =IFERROR(P67/M67,"-") -> - | U67: =IFERROR(T67/M67,"-") -> - | V67: =IF(OR(M67>0,T67>0),"ok","-") -> -
A68: 67 | B68: 4 | C68: 20 | D68: 100 | E68: =MATCH(H68,'[5]Sub Account'!$E$2:$E$503,0) -> 373 | H68: 72004 | I68: សម្បទានរ៉ែ | J68: =SUM(J69:J71) -> 0 | K68: =SUM(K69:K71) -> 0 | L68: =SUM(L69:L71) -> 0 | M68: =SUM(M69:M71) -> 0 | N68: =SUM(N69:N71) -> 0 | O68: =SUM(O69:O71) -> 0 | P68: =SUM(N68:O68) -> 0 | Q68: =IFERROR(P68/M68,"-") -> - | R68: =SUM(R69:R71) -> 0 | S68: =SUM(S69:S71) -> 0 | T68: =SUM(T69:T71) -> 0 | U68: =IFERROR(T68/M68,"-") -> - | V68: =IF(OR(M68>0,T68>0),"ok","-") -> -
I69: - អាជីវកម្មរ៉ែ | P69: =SUM(N69:O69) -> 0 | Q69: =IFERROR(P69/M69,"-") -> - | U69: =IFERROR(T69/M69,"-") -> - | V69: =IF(OR(M69>0,T69>0),"ok","-") -> -
I70: - សួយសារថ្លៃឈ្នួលប្រចាំឆ្នាំ | P70: =SUM(N70:O70) -> 0 | Q70: =IFERROR(P70/M70,"-") -> - | U70: =IFERROR(T70/M70,"-") -> - | V70: =IF(OR(M70>0,T70>0),"ok","-") -> -
I71: - សួយសារដី | P71: =SUM(N71:O71) -> 0 | Q71: =IFERROR(P71/M71,"-") -> - | U71: =IFERROR(T71/M71,"-") -> - | V71: =IF(OR(M71>0,T71>0),"ok","-") -> -
A72: 71 | B72: 4 | C72: 20 | D72: 100 | E72: =MATCH(H72,'[5]Sub Account'!$E$2:$E$503,0) -> 374 | H72: 72005 | I72: សម្បទានដីសេដ្ឋកិច្ច | P72: =SUM(N72:O72) -> 0 | Q72: =IFERROR(P72/M72,"-") -> - | U72: =IFERROR(T72/M72,"-") -> - | V72: =IF(OR(M72>0,T72>0),"ok","-") -> -
A73: 72 | B73: 4 | C73: 20 | D73: 100 | E73: =MATCH(H73,'[5]Sub Account'!$E$2:$E$503,0) -> 375 | H73: 72006 | I73: ចំណតយានជំនិះ | P73: =SUM(N73:O73) -> 0 | Q73: =IFERROR(P73/M73,"-") -> - | U73: =IFERROR(T73/M73,"-") -> - | V73: =IF(OR(M73>0,T73>0),"ok","-") -> -
A74: 73 | B74: 4 | C74: 20 | D74: 100 | E74: =MATCH(H74,'[5]Sub Account'!$E$2:$E$503,0) -> 376 | H74: 72007 | I74: ចំណតជលយាន | P74: =SUM(N74:O74) -> 0 | Q74: =IFERROR(P74/M74,"-") -> - | U74: =IFERROR(T74/M74,"-") -> - | V74: =IF(OR(M74>0,T74>0),"ok","-") -> -
A75: 74 | B75: 4 | C75: 20 | D75: 100 | E75: =MATCH(H75,'[5]Sub Account'!$E$2:$E$503,0) -> 377 | H75: 72008 | I75: ផលសម្បទានផ្សេងៗ | P75: =SUM(N75:O75) -> 0 | Q75: =IFERROR(P75/M75,"-") -> - | U75: =IFERROR(T75/M75,"-") -> - | V75: =IF(OR(M75>0,T75>0),"ok","-") -> -
G76: 7201 | I76: ផលទុនពីសហគ្រាសសាធារណៈ | J76: =SUM(J77:J80) -> 0 | K76: =SUM(K77:K80) -> 0 | L76: =SUM(L77:L80) -> 0 | M76: =SUM(M77:M80) -> 0 | N76: =SUM(N77:N80) -> 0 | O76: =SUM(O77:O80) -> 0 | P76: =SUM(P77:P80) -> 0 | Q76: =IFERROR(P76/M76,"-") -> - | R76: =SUM(R77:R80) -> 0 | S76: =SUM(S77:S80) -> 0 | T76: =SUM(T77:T80) -> 0 | U76: =IFERROR(T76/M76,"-") -> - | V76: =IF(OR(M76>0,T76>0),"ok","-") -> -
A77: 76 | B77: 4 | C77: 20 | D77: 101 | E77: =MATCH(H77,'[5]Sub Account'!$E$2:$E$503,0) -> 378 | H77: 72011 | I77: ការដកចំនួនលើសនៃទុនចល័ត | P77: =SUM(N77:O77) -> 0 | Q77: =IFERROR(P77/M77,"-") -> - | U77: =IFERROR(T77/M77,"-") -> - | V77: =IF(OR(M77>0,T77>0),"ok","-") -> -
A78: 77 | B78: 4 | C78: 20 | D78: 101 | E78: =MATCH(H78,'[5]Sub Account'!$E$2:$E$503,0) -> 379 | H78: 72012 | I78: ភាគលាភរបស់សហគ្រាសសាធារណៈ | P78: =SUM(N78:O78) -> 0 | Q78: =IFERROR(P78/M78,"-") -> - | U78: =IFERROR(T78/M78,"-") -> - | V78: =IF(OR(M78>0,T78>0),"ok","-") -> -
A79: 78 | B79: 4 | C79: 20 | D79: 101 | E79: =MATCH(H79,'[5]Sub Account'!$E$2:$E$503,0) -> 380 | H79: 72014 | I79: ប្រាក់ធានារ៉ាប់រងសង្គម | P79: =SUM(N79:O79) -> 0 | Q79: =IFERROR(P79/M79,"-") -> - | U79: =IFERROR(T79/M79,"-") -> - | V79: =IF(OR(M79>0,T79>0),"ok","-") -> -
A80: 79 | B80: 4 | C80: 20 | D80: 101 | E80: =MATCH(H80,'[5]Sub Account'!$E$2:$E$503,0) -> 381 | H80: 72018 | I80: ផលទុនផ្សេងៗពីសហគ្រាសសាធារណៈ | P80: =SUM(N80:O80) -> 0 | Q80: =IFERROR(P80/M80,"-") -> - | U80: =IFERROR(T80/M80,"-") -> - | V80: =IF(OR(M80>0,T80>0),"ok","-") -> -
F81: 73 | I81: ផលទុនពីការលក់ ជួលទ្រព្យសម្បត្តិ និងសេវា | J81: =J82+J91+J100+J106+J115+J122+J129+J135 -> 0 | K81: =K82+K91+K100+K106+K115+K122+K129+K135 -> 0 | L81: =L82+L91+L100+L106+L115+L122+L129+L135 -> 0 | M81: =M82+M91+M100+M106+M115+M122+M129+M135 -> 0 | N81: =N82+N91+N100+N106+N115+N122+N129+N135 -> 0 | O81: =O82+O91+O100+O106+O115+O122+O129+O135 -> 0 | P81: =P82+P91+P100+P106+P115+P122+P129+P135 -> 0 | Q81: =IFERROR(P81/M81,"-") -> - | R81: =R82+R91+R100+R106+R115+R122+R129+R135 -> 0 | S81: =S82+S91+S100+S106+S115+S122+S129+S135 -> 0 | T81: =T82+T91+T100+T106+T115+T122+T129+T135 -> 0 | U81: =IFERROR(T81/M81,"-") -> - | V81: =IF(OR(M81>0,T81>0),"ok","-") -> -
G82: 7300 | I82: ផលទុនតាមវិស័យ | J82: =SUM(J83:J90) -> 0 | K82: =SUM(K83:K90) -> 0 | L82: =SUM(L83:L90) -> 0 | M82: =SUM(M83:M90) -> 0 | N82: =SUM(N83:N90) -> 0 | O82: =SUM(O83:O90) -> 0 | P82: =SUM(P83:P90) -> 0 | Q82: =IFERROR(P82/M82,"-") -> - | R82: =SUM(R83:R90) -> 0 | S82: =SUM(S83:S90) -> 0 | T82: =SUM(T83:T90) -> 0 | U82: =IFERROR(T82/M82,"-") -> - | V82: =IF(OR(M82>0,T82>0),"ok","-") -> -
A83: 82 | B83: 4 | C83: 21 | D83: 102 | E83: =MATCH(H83,'[5]Sub Account'!$E$2:$E$503,0) -> 382 | H83: 73001 | I83: ផលទុនអាកាសចរស៊ីវិល | P83: =SUM(N83:O83) -> 0 | Q83: =IFERROR(P83/M83,"-") -> - | U83: =IFERROR(T83/M83,"-") -> - | V83: =IF(OR(M83>0,T83>0),"ok","-") -> -
A84: 83 | B84: 4 | C84: 21 | D84: 102 | E84: =MATCH(H84,'[5]Sub Account'!$E$2:$E$503,0) -> 383 | H84: 73002 | I84: ផលទុននៃសកម្មភាពភាពយន្ត | P84: =SUM(N84:O84) -> 0 | Q84: =IFERROR(P84/M84,"-") -> - | U84: =IFERROR(T84/M84,"-") -> - | V84: =IF(OR(M84>0,T84>0),"ok","-") -> -
A85: 84 | B85: 4 | C85: 21 | D85: 102 | E85: =MATCH(H85,'[5]Sub Account'!$E$2:$E$503,0) -> 384 | H85: 73003 | I85: ផលទុននៃសកម្មភាពទេសចរណ៍ | P85: =SUM(N85:O85) -> 0 | Q85: =IFERROR(P85/M85,"-") -> - | U85: =IFERROR(T85/M85,"-") -> - | V85: =IF(OR(M85>0,T85>0),"ok","-") -> -
A86: 85 | B86: 4 | C86: 21 | D86: 102 | E86: =MATCH(H86,'[5]Sub Account'!$E$2:$E$503,0) -> 385 | H86: 73004 | I86: ផលទុននៃសកម្មភាពវប្បធម៌ | P86: =SUM(N86:O86) -> 0 | Q86: =IFERROR(P86/M86,"-") -> - | U86: =IFERROR(T86/M86,"-") -> - | V86: =IF(OR(M86>0,T86>0),"ok","-") -> -
A87: 86 | B87: 4 | C87: 21 | D87: 102 | E87: =MATCH(H87,'[5]Sub Account'!$E$2:$E$503,0) -> 386 | H87: 73005 | I87: ផលទុនពីប្រៃសណីយ៍ និងទូរគមនាគមន៍ | P87: =SUM(N87:O87) -> 0 | Q87: =IFERROR(P87/M87,"-") -> - | U87: =IFERROR(T87/M87,"-") -> - | V87: =IF(OR(M87>0,T87>0),"ok","-") -> -
A88: 87 | B88: 4 | C88: 21 | D88: 102 | E88: =MATCH(H88,'[5]Sub Account'!$E$2:$E$503,0) -> 387 | H88: 73006 | I88: ផលទុនពីវិទ្យុ និងទូរទស្សន៍ | P88: =SUM(N88:O88) -> 0 | Q88: =IFERROR(P88/M88,"-") -> - | U88: =IFERROR(T88/M88,"-") -> - | V88: =IF(OR(M88>0,T88>0),"ok","-") -> -
A89: 88 | B89: 4 | C89: 21 | D89: 102 | E89: =MATCH(H89,'[5]Sub Account'!$E$2:$E$503,0) -> 388 | H89: 73007 | I89: ផលទុននៃសេវាផ្គត់ផ្គង់អគ្គិសនី និងទឹក | P89: =SUM(N89:O89) -> 0 | Q89: =IFERROR(P89/M89,"-") -> - | U89: =IFERROR(T89/M89,"-") -> - | V89: =IF(OR(M89>0,T89>0),"ok","-") -> -
A90: 89 | B90: 4 | C90: 21 | D90: 102 | E90: =MATCH(H90,'[5]Sub Account'!$E$2:$E$503,0) -> 389 | H90: 73008 | I90: ផលទុនផ្សេងៗទៀត | P90: =SUM(N90:O90) -> 0 | Q90: =IFERROR(P90/M90,"-") -> - | U90: =IFERROR(T90/M90,"-") -> - | V90: =IF(OR(M90>0,T90>0),"ok","-") -> -
G91: 7301 | I91: ការលក់ទ្រព្យសម្បត្តិនៃរដ្ឋបាលសាធារណៈ | J91: =SUM(J92:J99) -> 0 | K91: =SUM(K92:K99) -> 0 | L91: =SUM(L92:L99) -> 0 | M91: =SUM(M92:M99) -> 0 | N91: =SUM(N92:N99) -> 0 | O91: =SUM(O92:O99) -> 0 | P91: =SUM(P92:P99) -> 0 | Q91: =IFERROR(P91/M91,"-") -> - | R91: =SUM(R92:R99) -> 0 | S91: =SUM(S92:S99) -> 0 | T91: =SUM(T92:T99) -> 0 | U91: =IFERROR(T91/M91,"-") -> - | V91: =IF(OR(M91>0,T91>0),"ok","-") -> -
A92: 91 | B92: 4 | C92: 21 | D92: 103 | E92: =MATCH(H92,'[5]Sub Account'!$E$2:$E$503,0) -> 390 | H92: 73011 | I92: ការលក់សម្ភារបរិក្ខារ សម្ភារខូចខាត សម្ភារសិក្សា | P92: =SUM(N92:O92) -> 0 | Q92: =IFERROR(P92/M92,"-") -> - | U92: =IFERROR(T92/M92,"-") -> - | V92: =IF(OR(M92>0,T92>0),"ok","-") -> -
A93: 92 | B93: 4 | C93: 21 | D93: 103 | E93: =MATCH(H93,'[5]Sub Account'!$E$2:$E$503,0) -> 391 | H93: 73012 | I93: លក់ឯកសារ លតាប័ត្រ និងលិខិតបោះពុម្ពផ្សេងៗ | P93: =SUM(N93:O93) -> 0 | Q93: =IFERROR(P93/M93,"-") -> - | U93: =IFERROR(T93/M93,"-") -> - | V93: =IF(OR(M93>0,T93>0),"ok","-") -> -
A94: 93 | B94: 4 | C94: 21 | D94: 103 | E94: =MATCH(H94,'[5]Sub Account'!$E$2:$E$503,0) -> 392 | H94: 73013 | I94: ផលបានពីការលក់ទ្រព្យសម្បត្តិកំទេចកំទី សត្វពាហនៈ | P94: =SUM(N94:O94) -> 0 | Q94: =IFERROR(P94/M94,"-") -> - | U94: =IFERROR(T94/M94,"-") -> - | V94: =IF(OR(M94>0,T94>0),"ok","-") -> -
A95: 94 | B95: 4 | C95: 21 | D95: 103 | E95: =MATCH(H95,'[5]Sub Account'!$E$2:$E$503,0) -> 393 | H95: 73014 | I95: ការលក់ផលិតផលកសិកម្ម | P95: =SUM(N95:O95) -> 0 | Q95: =IFERROR(P95/M95,"-") -> - | U95: =IFERROR(T95/M95,"-") -> - | V95: =IF(OR(M95>0,T95>0),"ok","-") -> -
A96: 95 | B96: 4 | C96: 21 | D96: 103 | E96: =MATCH(H96,'[5]Sub Account'!$E$2:$E$503,0) -> 394 | H96: 73015 | I96: ការលក់មធ្យោបាយដឹកជញ្ជូន និងគ្រឿងចក្រចាស់ៗ ឬ ខូច | P96: =SUM(N96:O96) -> 0 | Q96: =IFERROR(P96/M96,"-") -> - | U96: =IFERROR(T96/M96,"-") -> - | V96: =IF(OR(M96>0,T96>0),"ok","-") -> -
A97: 96 | B97: 4 | C97: 21 | D97: 103 | E97: =MATCH(H97,'[5]Sub Account'!$E$2:$E$503,0) -> 395 | H97: 73016 | I97: ការលក់ឧបករណ៍អេឡិចត្រូនិចចាស់ៗ ឬ ខូច | P97: =SUM(N97:O97) -> 0 | Q97: =IFERROR(P97/M97,"-") -> - | U97: =IFERROR(T97/M97,"-") -> - | V97: =IF(OR(M97>0,T97>0),"ok","-") -> -
A98: 97 | B98: 4 | C98: 21 | D98: 103 | E98: =MATCH(H98,'[5]Sub Account'!$E$2:$E$503,0) -> 396 | H98: 73017 | I98: ការលក់ឧបករណ៍អគ្គិសនីចាស់ៗ ឬ ខូច | P98: =SUM(N98:O98) -> 0 | Q98: =IFERROR(P98/M98,"-") -> - | U98: =IFERROR(T98/M98,"-") -> - | V98: =IF(OR(M98>0,T98>0),"ok","-") -> -
A99: 98 | B99: 4 | C99: 21 | D99: 103 | E99: =MATCH(H99,'[5]Sub Account'!$E$2:$E$503,0) -> 397 | H99: 73018 | I99: ការលក់ទ្រព្យសម្បត្តិនៃរដ្ឋបាលសាធារណៈ ផ្សេងៗទៀត | P99: =SUM(N99:O99) -> 0 | Q99: =IFERROR(P99/M99,"-") -> - | U99: =IFERROR(T99/M99,"-") -> - | V99: =IF(OR(M99>0,T99>0),"ok","-") -> -
G100: 7302 | I100: ផលពីការគ្រប់គ្រងរដ្ឋបាល (1) | J100: =SUM(J101:J105) -> 0 | K100: =SUM(K101:K105) -> 0 | L100: =SUM(L101:L105) -> 0 | M100: =SUM(M101:M105) -> 0 | N100: =SUM(N101:N105) -> 0 | O100: =SUM(O101:O105) -> 0 | P100: =SUM(P101:P105) -> 0 | Q100: =IFERROR(P100/M100,"-") -> - | R100: =SUM(R101:R105) -> 0 | S100: =SUM(S101:S105) -> 0 | T100: =SUM(T101:T105) -> 0 | U100: =IFERROR(T100/M100,"-") -> - | V100: =IF(OR(M100>0,T100>0),"ok","-") -> -
...

Sheet BSP4B
C5: តារាង ៤ ខ : ពណ៌នាអំពីការគ្រោងចំណាយមូលធនសម្រាប់អនុកម្មវិធី
J6: តារាង ៤"ខ"
D7: កូដអនុកម្មវិធី | E7: =Costing!$G$11 -> 10101 | J7: ឯកតា៖ លានរៀល
A10: Check | B10: កូដអង្គភាព | C10: ឈ្មោះគម្រោង តាមកម្មវិធី | D10: លេខ អនុកម្មវិធី | E10: បរិយាយគម្រោង | F10: ពន្យល់អំពីនិន្នាការមូលនិធិ លើសពីឆ្នាំថវិកា | G10: ច្បាប់ហិរញ្ញវត្ថុឆ្នាំ២០២២ | I10: គ្រោងឆ្នាំ២០២៣
G11: ថវិការដ្ឋ | H11: ថវិកាដៃគូអភិវឌ្ឍន៍ | I11: ថវិការដ្ឋ | J11: ថវិកាដៃគូអភិវឌ្ឍន៍
C12: សរុបរួមចំណាយមូលធន | G12: =G13 -> 0 | H12: =H13 -> 0 | I12: =I13 -> 0 | J12: =J13 -> 0 | K12: =IF(SUM(G12:J12)>0,"ok","-") -> -
C13: =Costing!$H$11 -> អនុកម្មវិធីទី១.១ | D13: =Costing!$G$11 -> 10101 | G13: =SUM(G14:G19) -> 0 | H13: =SUM(H14:H19) -> 0 | I13: =SUM(I14:I19) -> 0 | J13: =SUM(J14:J19) -> 0 | K13: =IF(SUM(G13:J13)>0,"ok","-") -> -
C14: ឈ្មោះគម្រោង : ... | D14: =$D$13 -> 10101 | K14: =IF(SUM(G14:J14)>0,"ok","-") -> -
C15: ឈ្មោះគម្រោង : ... | D15: =$D$13 -> 10101 | K15: =IF(SUM(G15:J15)>0,"ok","-") -> -
C16: ឈ្មោះគម្រោង : ... | D16: =$D$13 -> 10101 | K16: =IF(SUM(G16:J16)>0,"ok","-") -> -
C17: ឈ្មោះគម្រោង : ... | D17: =$D$13 -> 10101 | K17: =IF(SUM(G17:J17)>0,"ok","-") -> -
C18: ឈ្មោះគម្រោង : ... | D18: =$D$13 -> 10101 | K18: =IF(SUM(G18:J18)>0,"ok","-") -> -
C19: ឈ្មោះគម្រោង : ... | D19: =$D$13 -> 10101 | K19: =IF(SUM(G19:J19)>0,"ok","-") -> -

Sheet PB1-Rev
A5: គម្រោងថវិកាឆ្នាំ២០២៣
A6: គម្រោងចំណូលថវិកាតាមចំណាត់ថ្នាក់សេដ្ឋកិច្ច
A7: =Costing!$K$11 -> អគ្គនាយកដ្ឋានគោលនយោបាយ
P8: តារាងទី១ (តារាង ១"ក" ក្នុងសារាចររៀបចំគម្រោងថវិកាប្រចាំឆ្នាំ)
P9: ឯកតា៖ លានរៀល
A12: ជំពូក | B12: គណនី | C12: អនុគណនី | D12: ចំណាត់ថ្នាក់ចំណាយ (តាមតារាងមាតិកាថវិកា ) | E12: ចំណូលឆ្នាំ២០២១ (អនុវត្ត) | F12: ច្បាប់ហិរញ្ញវត្ថុឆ្នាំ២០២២ | I12: ប៉ាន់ស្មាន​អនុវត្ត​ឆ្នាំ​២០២២ | M12: គម្រោង​ឆ្នាំ​២០២៣
F13: មូលដ្ឋាន គិតចំណូល | G13: បរិមាណ | H13: សរុប​ ឥណទានថវិកា | I13: អនុវត្ដ ឆមាសទី១ | J13: ប៉ាន់ស្មាន ឆមាសទី២ | K13: ប៉ាន់​ស្មាន​ប្រចាំ​ឆ្នាំ | M13: មូលដ្ឋាន គិតចំណូល | N13: បរិមាណ | O13: សរុប​ការ​គ្រោ​ង​ចំណូល
K14: សរុប | L14: %ច្ប.២២ | O14: សរុប​ | P14: %ច្ប.២២ | Q14: ok
A15: សរុប​រួមចំណូល​ (ក+ខ) | E15: =E17+E261 -> 0 | F15: =F17+F261 -> 0 | G15: =G17+G261 -> 0 | H15: =H17+H261 -> 0 | I15: =I17+I261 -> 0 | J15: =J17+J261 -> 0 | K15: =K17+K261 -> 0 | L15: =IFERROR(K15/H15,"-") -> - | M15: =M17+M261 -> 0 | N15: =N17+N261 -> 0 | O15: =O17+O261 -> 0 | P15: =IFERROR(O15/H15,"-") -> - | Q15: =IF(OR(H15>0,O15>0),"ok","-") -> -
A16: ក្នុងនោះចំណូល​ក្នុងប្រទេស | E16: =E17+E264 -> 0 | F16: =F17+F264 -> 0 | G16: =G17+G264 -> 0 | H16: =H17+H264 -> 0 | I16: =I17+I264 -> 0 | J16: =J17+J264 -> 0 | K16: =K17+K264 -> 0 | L16: =IFERROR(K16/H16,"-") -> - | M16: =M17+M264 -> 0 | N16: =N17+N264 -> 0 | O16: =O17+O264 -> 0 | P16: =IFERROR(O16/H16,"-") -> - | Q16: =IF(OR(H16>0,O16>0),"ok","-") -> -
A17: ក. សរុបចំណូល​ចរន្ត (ក្រុមទី១+ក្រុមទី២) | E17: =E18+E259 -> 0 | F17: =F18+F259 -> 0 | G17: =G18+G259 -> 0 | H17: =H18+H259 -> 0 | I17: =I18+I259 -> 0 | J17: =J18+J259 -> 0 | K17: =K18+K259 -> 0 | L17: =IFERROR(K17/H17,"-") -> - | M17: =M18+M259 -> 0 | N17: =N18+N259 -> 0 | O17: =O18+O259 -> 0 | P17: =IFERROR(O17/H17,"-") -> - | Q17: =IF(OR(H17>0,O17>0),"ok","-") -> -
A18: ក្រុមទី១: ចំណូល​ពិត (ប្រភេទទី១+ប្រភេទទី២) | E18: =E19+E82 -> 0 | F18: =F19+F82 -> 0 | G18: =G19+G82 -> 0 | H18: =H19+H82 -> 0 | I18: =I19+I82 -> 0 | J18: =J19+J82 -> 0 | K18: =K19+K82 -> 0 | L18: =IFERROR(K18/H18,"-") -> - | M18: =M19+M82 -> 0 | N18: =N19+N82 -> 0 | O18: =O19+O82 -> 0 | P18: =IFERROR(O18/H18,"-") -> - | Q18: =IF(OR(H18>0,O18>0),"ok","-") -> -
A19: ប្រភេទទី១: ចំណូល​សារពើពន្ធ | E19: =E20+E65 -> 0 | F19: =F20+F65 -> 0 | G19: =G20+G65 -> 0 | H19: =H20+H65 -> 0 | I19: =I20+I65 -> 0 | J19: =J20+J65 -> 0 | K19: =K20+K65 -> 0 | L19: =IFERROR(K19/H19,"-") -> - | M19: =M20+M65 -> 0 | N19: =N20+N65 -> 0 | O19: =O20+O65 -> 0 | P19: =IFERROR(O19/H19,"-") -> - | Q19: =IF(OR(H19>0,O19>0),"ok","-") -> -
A20: 70 | D20: ចំណូលសារពើពន្ធក្នុងស្រុក | E20: =E21+E28+E36+E43+E46+E50+E57+E62 -> 0 | F20: =F21+F28+F36+F43+F46+F50+F57+F62 -> 0 | G20: =G21+G28+G36+G43+G46+G50+G57+G62 -> 0 | H20: =H21+H28+H36+H43+H46+H50+H57+H62 -> 0 | I20: =I21+I28+I36+I43+I46+I50+I57+I62 -> 0 | J20: =J21+J28+J36+J43+J46+J50+J57+J62 -> 0 | K20: =K21+K28+K36+K43+K46+K50+K57+K62 -> 0 | L20: =IFERROR(K20/H20,"-") -> - | M20: =M21+M28+M36+M43+M46+M50+M57+M62 -> 0 | N20: =N21+N28+N36+N43+N46+N50+N57+N62 -> 0 | O20: =O21+O28+O36+O43+O46+O50+O57+O62 -> 0 | P20: =IFERROR(O20/H20,"-") -> - | Q20: =IF(OR(H20>0,O20>0),"ok","-") -> -
B21: 7001 | D21: ពន្ធផ្ទាល់ (ពន្ធលើផលទុន ប្រាក់ចំណូល) | E21: =SUM(E22:E27) -> 0 | F21: =SUM(F22:F27) -> 0 | G21: =SUM(G22:G27) -> 0 | H21: =SUM(H22:H27) -> 0 | I21: =SUM(I22:I27) -> 0 | J21: =SUM(J22:J27) -> 0 | K21: =SUM(K22:K27) -> 0 | L21: =IFERROR(K21/H21,"-") -> - | M21: =SUM(M22:M27) -> 0 | N21: =SUM(N22:N27) -> 0 | O21: =SUM(O22:O27) -> 0 | P21: =IFERROR(O21/H21,"-") -> - | Q21: =IF(OR(H21>0,O21>0),"ok","-") -> -
C22: 70011 | D22: ពន្ធលើប្រាក់ចំណូល (រូបវន្តបុគ្គល) | K22: =SUM(I22:J22) -> 0 | L22: =IFERROR(K22/H22,"-") -> - | P22: =IFERROR(O22/H22,"-") -> - | Q22: =IF(OR(H22>0,O22>0),"ok","-") -> -
C23: 70012 | D23: ពន្ធលើប្រាក់ចំណូល (នីតិបុគ្គល) | K23: =SUM(I23:J23) -> 0 | L23: =IFERROR(K23/H23,"-") -> - | P23: =IFERROR(O23/H23,"-") -> - | Q23: =IF(OR(H23>0,O23>0),"ok","-") -> -
C24: 70013 | D24: ពន្ធលើប្រាក់បៀវត្ស | K24: =SUM(I24:J24) -> 0 | L24: =IFERROR(K24/H24,"-") -> - | P24: =IFERROR(O24/H24,"-") -> - | Q24: =IF(OR(H24>0,O24>0),"ok","-") -> -
C25: 70014 | D25: ពន្ធលើឈ្នួលចលននិងអចលនទ្រព្យ (រូបវន្តបុគ្គល) | K25: =SUM(I25:J25) -> 0 | L25: =IFERROR(K25/H25,"-") -> - | P25: =IFERROR(O25/H25,"-") -> - | Q25: =IF(OR(H25>0,O25>0),"ok","-") -> -
C26: 70015 | D26: ពន្ធលើឈ្នួលចលននិងអចលនទ្រព្យ (នីតិបុគ្គល) | K26: =SUM(I26:J26) -> 0 | L26: =IFERROR(K26/H26,"-") -> - | P26: =IFERROR(O26/H26,"-") -> - | Q26: =IF(OR(H26>0,O26>0),"ok","-") -> -
C27: 70016 | D27: ពន្ធលើប្រាក់ចំណូលនីតិបុគ្គលជាបន្ទុករបស់រដ្ឋ | K27: =SUM(I27:J27) -> 0 | L27: =IFERROR(K27/H27,"-") -> - | P27: =IFERROR(O27/H27,"-") -> - | Q27: =IF(OR(H27>0,O27>0),"ok","-") -> -
B28: 7002 | D28: ពន្ធប្រយោល | E28: =SUM(E29:E35) -> 0 | F28: =SUM(F29:F35) -> 0 | G28: =SUM(G29:G35) -> 0 | H28: =SUM(H29:H35) -> 0 | I28: =SUM(I29:I35) -> 0 | J28: =SUM(J29:J35) -> 0 | K28: =SUM(K29:K35) -> 0 | L28: =IFERROR(K28/H28,"-") -> - | M28: =SUM(M29:M35) -> 0 | N28: =SUM(N29:N35) -> 0 | O28: =SUM(O29:O35) -> 0 | P28: =IFERROR(O28/H28,"-") -> - | Q28: =IF(OR(H28>0,O28>0),"ok","-") -> -
C29: 70021 | D29: អាករលើផលរបរ | K29: =SUM(I29:J29) -> 0 | L29: =IFERROR(K29/H29,"-") -> - | P29: =IFERROR(O29/H29,"-") -> - | Q29: =IF(OR(H29>0,O29>0),"ok","-") -> -
C30: 70022 | D30: អាករលើតម្លៃបន្ថែម | K30: =SUM(I30:J30) -> 0 | L30: =IFERROR(K30/H30,"-") -> - | P30: =IFERROR(O30/H30,"-") -> - | Q30: =IF(OR(H30>0,O30>0),"ok","-") -> -
C31: 70023 | D31: អាករលើតម្លៃបន្ថែម​លើទំនិញជាបន្ទុករបស់​រដ្ឋ | K31: =SUM(I31:J31) -> 0 | L31: =IFERROR(K31/H31,"-") -> - | P31: =IFERROR(O31/H31,"-") -> - | Q31: =IF(OR(H31>0,O31>0),"ok","-") -> -
C32: 70024 | D32: អាករលើតម្លៃបន្ថែម​លើសេវាជាបន្ទុករបស់​រដ្ឋ | K32: =SUM(I32:J32) -> 0 | L32: =IFERROR(K32/H32,"-") -> - | P32: =IFERROR(O32/H32,"-") -> - | Q32: =IF(OR(H32>0,O32>0),"ok","-") -> -
C33: 70025 | D33: អាករលើតម្លៃបន្ថែម របបនាំចូល (សហគ្រាសប្រេងឥន្ធនៈ) | K33: =SUM(I33:J33) -> 0 | L33: =IFERROR(K33/H33,"-") -> - | P33: =IFERROR(O33/H33,"-") -> - | Q33: =IF(OR(H33>0,O33>0),"ok","-") -> -
C34: 70026 | D34: អាករលើតម្លៃបន្ថែម របបនាំចូល (សហគ្រាសផ្សេងៗទៀត) | K34: =SUM(I34:J34) -> 0 | L34: =IFERROR(K34/H34,"-") -> - | P34: =IFERROR(O34/H34,"-") -> - | Q34: =IF(OR(H34>0,O34>0),"ok","-") -> -
C35: 70027 | D35: អាករលើតម្លៃបន្ថែម របបនាំចូល (ជាបន្ទុករបស់រដ្ឋ) | K35: =SUM(I35:J35) -> 0 | L35: =IFERROR(K35/H35,"-") -> - | P35: =IFERROR(O35/H35,"-") -> - | Q35: =IF(OR(H35>0,O35>0),"ok","-") -> -
B36: 7003 | D36: អាករពិសេស | E36: =SUM(E37:E42) -> 0 | F36: =SUM(F37:F42) -> 0 | G36: =SUM(G37:G42) -> 0 | H36: =SUM(H37:H42) -> 0 | I36: =SUM(I37:I42) -> 0 | J36: =SUM(J37:J42) -> 0 | K36: =SUM(K37:K42) -> 0 | L36: =IFERROR(K36/H36,"-") -> - | M36: =SUM(M37:M42) -> 0 | N36: =SUM(N37:N42) -> 0 | O36: =SUM(O37:O42) -> 0 | P36: =IFERROR(O36/H36,"-") -> - | Q36: =IF(OR(H36>0,O36>0),"ok","-") -> -
C37: 70031 | D37: អាករពិសេសលើទំនិញមួយចំនួន | K37: =SUM(I37:J37) -> 0 | L37: =IFERROR(K37/H37,"-") -> - | P37: =IFERROR(O37/H37,"-") -> - | Q37: =IF(OR(H37>0,O37>0),"ok","-") -> -
C38: 70032 | D38: អាករពិសេសលើទំនិញមួយចំនួន របបនាំចូល (សហគ្រាសប្រេងឥន្ធនៈ) | K38: =SUM(I38:J38) -> 0 | L38: =IFERROR(K38/H38,"-") -> - | P38: =IFERROR(O38/H38,"-") -> - | Q38: =IF(OR(H38>0,O38>0),"ok","-") -> -
C39: 70033 | D39: អាករពិសេសលើទំនិញមួយចំនួន របបនាំចូល (សហគ្រាសផ្សេងៗទៀត) | K39: =SUM(I39:J39) -> 0 | L39: =IFERROR(K39/H39,"-") -> - | P39: =IFERROR(O39/H39,"-") -> - | Q39: =IF(OR(H39>0,O39>0),"ok","-") -> -
C40: 70034 | D40: អាករពិសេសលើសេវាមួយចំនួន | K40: =SUM(I40:J40) -> 0 | L40: =IFERROR(K40/H40,"-") -> - | P40: =IFERROR(O40/H40,"-") -> - | Q40: =IF(OR(H40>0,O40>0),"ok","-") -> -
C41: 70035 | D41: អាករសម្រាប់បំភ្លឺសាធារណៈ | K41: =SUM(I41:J41) -> 0 | L41: =IFERROR(K41/H41,"-") -> - | P41: =IFERROR(O41/H41,"-") -> - | Q41: =IF(OR(H41>0,O41>0),"ok","-") -> -
C42: 70038 | D42: ផ្សេងៗ | K42: =SUM(I42:J42) -> 0 | L42: =IFERROR(K42/H42,"-") -> - | P42: =IFERROR(O42/H42,"-") -> - | Q42: =IF(OR(H42>0,O42>0),"ok","-") -> -
B43: 7004 | D43: អាករលើសេវាដែលបានកំណត់ | E43: =SUM(E44:E45) -> 0 | F43: =SUM(F44:F45) -> 0 | G43: =SUM(G44:G45) -> 0 | H43: =SUM(H44:H45) -> 0 | I43: =SUM(I44:I45) -> 0 | J43: =SUM(J44:J45) -> 0 | K43: =SUM(K44:K45) -> 0 | L43: =IFERROR(K43/H43,"-") -> - | M43: =SUM(M44:M45) -> 0 | N43: =SUM(N44:N45) -> 0 | O43: =SUM(O44:O45) -> 0 | P43: =IFERROR(O43/H43,"-") -> - | Q43: =IF(OR(H43>0,O43>0),"ok","-") -> -
C44: 70045 | D44: អាករលើការស្នាក់នៅ | K44: =SUM(I44:J44) -> 0 | L44: =IFERROR(K44/H44,"-") -> - | P44: =IFERROR(O44/H44,"-") -> - | Q44: =IF(OR(H44>0,O44>0),"ok","-") -> -
C45: 70046 | D45: ពន្ធសត្តឃាត | K45: =SUM(I45:J45) -> 0 | L45: =IFERROR(K45/H45,"-") -> - | P45: =IFERROR(O45/H45,"-") -> - | Q45: =IF(OR(H45>0,O45>0),"ok","-") -> -
B46: 7005 | D46: អាករលើការប្រើប្រាស់ទ្រព្យសម្បត្តិ ឬ ការអនុវត្តសកម្មភាព | E46: =SUM(E47:E49) -> 0 | F46: =SUM(F47:F49) -> 0 | G46: =SUM(G47:G49) -> 0 | H46: =SUM(H47:H49) -> 0 | I46: =SUM(I47:I49) -> 0 | J46: =SUM(J47:J49) -> 0 | K46: =SUM(K47:K49) -> 0 | L46: =IFERROR(K46/H46,"-") -> - | M46: =SUM(M47:M49) -> 0 | N46: =SUM(N47:N49) -> 0 | O46: =SUM(O47:O49) -> 0 | P46: =IFERROR(O46/H46,"-") -> - | Q46: =IF(OR(H46>0,O46>0),"ok","-") -> -
C47: 70053 | D47: ពន្ធប៉ាតង់ | K47: =SUM(I47:J47) -> 0 | L47: =IFERROR(K47/H47,"-") -> - | P47: =IFERROR(O47/H47,"-") -> - | Q47: =IF(OR(H47>0,O47>0),"ok","-") -> -
C48: 70054 | D48: ពន្ធលើមធ្យោបាយដឹកជញ្ជូន និងយានជំនិះគ្រប់ប្រភេទ | K48: =SUM(I48:J48) -> 0 | L48: =IFERROR(K48/H48,"-") -> - | P48: =IFERROR(O48/H48,"-") -> - | Q48: =IF(OR(H48>0,O48>0),"ok","-") -> -
C49: 70055 | D49: ពន្ធលើមធ្យោបាយដឹកជញ្ជូន និង​យានជំនិះគ្រប់ប្រភេទជាបន្ទុករបស់រដ្ឋ | K49: =SUM(I49:J49) -> 0 | L49: =IFERROR(K49/H49,"-") -> - | P49: =IFERROR(O49/H49,"-") -> - | Q49: =IF(OR(H49>0,O49>0),"ok","-") -> -
B50: 7006 | D50: ពន្ធប្រថាប់ត្រា | E50: =SUM(E51:E56) -> 0 | F50: =SUM(F51:F56) -> 0 | G50: =SUM(G51:G56) -> 0 | H50: =SUM(H51:H56) -> 0 | I50: =SUM(I51:I56) -> 0 | J50: =SUM(J51:J56) -> 0 | K50: =SUM(K51:K56) -> 0 | L50: =IFERROR(K50/H50,"-") -> - | M50: =SUM(M51:M56) -> 0 | N50: =SUM(N51:N56) -> 0 | O50: =SUM(O51:O56) -> 0 | P50: =IFERROR(O50/H50,"-") -> - | Q50: =IF(OR(H50>0,O50>0),"ok","-") -> -
C51: 70061 | D51: ពន្ធប្រថាប់ត្រា លើតម្លៃអចលនទ្រព្យចំពោះការផ្ទេរកម្មសិទ្ធិ ឬ សិទ្ធិកាន់កាប់ | K51: =SUM(I51:J51) -> 0 | L51: =IFERROR(K51/H51,"-") -> - | P51: =IFERROR(O51/H51,"-") -> - | Q51: =IF(OR(H51>0,O51>0),"ok","-") -> -
C52: 70062 | D52: ពន្ធប្រថាប់ត្រា លើតម្លៃមធ្យោបាយដឹកជញ្ជូន ឬ យានយន្តចំពោះការផ្ទេរកម្មសិទ្ធិ | K52: =SUM(I52:J52) -> 0 | L52: =IFERROR(K52/H52,"-") -> - | P52: =IFERROR(O52/H52,"-") -> - | Q52: =IF(OR(H52>0,O52>0),"ok","-") -> -
C53: 70063 | D53: ពន្ធប្រថាប់ត្រា លើតម្លៃភាគហ៊ុនចំពោះការផ្ទេរភាគហ៊ុន | K53: =SUM(I53:J53) -> 0 | L53: =IFERROR(K53/H53,"-") -> - | P53: =IFERROR(O53/H53,"-") -> - | Q53: =IF(OR(H53>0,O53>0),"ok","-") -> -
C54: 70064 | D54: ពន្ធប្រថាប់ត្រា លើតម្លៃកិច្ចសន្យាចំពោះការផ្គត់ផ្គង់ទំនិញ ឬ សេវា | K54: =SUM(I54:J54) -> 0 | L54: =IFERROR(K54/H54,"-") -> - | P54: =IFERROR(O54/H54,"-") -> - | Q54: =IF(OR(H54>0,O54>0),"ok","-") -> -
C55: 70065 | D55: ពន្ធប្រថាប់ត្រា លើលិខិតមានលក្ខណៈគតិយុត្ដ | K55: =SUM(I55:J55) -> 0 | L55: =IFERROR(K55/H55,"-") -> - | P55: =IFERROR(O55/H55,"-") -> - | Q55: =IF(OR(H55>0,O55>0),"ok","-") -> -
C56: 70066 | D56: ពន្ធប្រថាប់ត្រាលើការផ្ទេរកម្មសិទ្ធិ ឬ សិទ្ធិ​កាន់កាប់​អចលនទ្រព្យ​ក្នុង​រង្វង់ញាតិ និង​ការអនុគ្រោះពន្ធ ជាបន្ទុករបស់រដ្ឋ | K56: =SUM(I56:J56) -> 0 | L56: =IFERROR(K56/H56,"-") -> - | P56: =IFERROR(O56/H56,"-") -> - | Q56: =IF(OR(H56>0,O56>0),"ok","-") -> -
B57: 7007 | D57: ពន្ធលើអចលនទ្រព្យ | E57: =SUM(E58:E61) -> 0 | F57: =SUM(F58:F61) -> 0 | G57: =SUM(G58:G61) -> 0 | H57: =SUM(H58:H61) -> 0 | I57: =SUM(I58:I61) -> 0 | J57: =SUM(J58:J61) -> 0 | K57: =SUM(K58:K61) -> 0 | L57: =IFERROR(K57/H57,"-") -> - | M57: =SUM(M58:M61) -> 0 | N57: =SUM(N58:N61) -> 0 | O57: =SUM(O58:O61) -> 0 | P57: =IFERROR(O57/H57,"-") -> - | Q57: =IF(OR(H57>0,O57>0),"ok","-") -> -
C58: 70071 | D58: ពន្ធលើអចលនទ្រព្យ (រូបវន្តបុគ្គល) | K58: =SUM(I58:J58) -> 0 | L58: =IFERROR(K58/H58,"-") -> - | P58: =IFERROR(O58/H58,"-") -> - | Q58: =IF(OR(H58>0,O58>0),"ok","-") -> -
C59: 70072 | D59: ពន្ធលើអចលនទ្រព្យ (នីតិបុគ្គល) | K59: =SUM(I59:J59) -> 0 | L59: =IFERROR(K59/H59,"-") -> - | P59: =IFERROR(O59/H59,"-") -> - | Q59: =IF(OR(H59>0,O59>0),"ok","-") -> -
C60: 70073 | D60: ពន្ធលើដីធ្លីមិនបានប្រើប្រាស់ | K60: =SUM(I60:J60) -> 0 | L60: =IFERROR(K60/H60,"-") -> - | P60: =IFERROR(O60/H60,"-") -> - | Q60: =IF(OR(H60>0,O60>0),"ok","-") -> -
C61: 70074 | D61: ពន្ធលើអចលនទ្រព្យ ជាបន្ទុករបស់រដ្ឋ | K61: =SUM(I61:J61) -> 0 | L61: =IFERROR(K61/H61,"-") -> - | P61: =IFERROR(O61/H61,"-") -> - | Q61: =IF(OR(H61>0,O61>0),"ok","-") -> -
B62: 7008 | D62: ចំណូលសារពើពន្ធផ្សេងៗទៀត | E62: =SUM(E63:E64) -> 0 | F62: =SUM(F63:F64) -> 0 | G62: =SUM(G63:G64) -> 0 | H62: =SUM(H63:H64) -> 0 | I62: =SUM(I63:I64) -> 0 | J62: =SUM(J63:J64) -> 0 | K62: =SUM(K63:K64) -> 0 | L62: =IFERROR(K62/H62,"-") -> - | M62: =SUM(M63:M64) -> 0 | N62: =SUM(N63:N64) -> 0 | O62: =SUM(O63:O64) -> 0 | P62: =IFERROR(O62/H62,"-") -> - | Q62: =IF(OR(H62>0,O62>0),"ok","-") -> -
C63: 70081 | D63: ពន្ធតែមប្រិ៍ | K63: =SUM(I63:J63) -> 0 | L63: =IFERROR(K63/H63,"-") -> - | P63: =IFERROR(O63/H63,"-") -> - | Q63: =IF(OR(H63>0,O63>0),"ok","-") -> -
C64: 70082 | D64: ប្រាក់ទោសទណ្ឌសារពើពន្ធ | K64: =SUM(I64:J64) -> 0 | L64: =IFERROR(K64/H64,"-") -> - | P64: =IFERROR(O64/H64,"-") -> - | Q64: =IF(OR(H64>0,O64>0),"ok","-") -> -
A65: 71 | D65: ចំណូលពន្ធលើពាណិជ្ជកម្មក្រៅប្រទេស | E65: =E66+E75 -> 0 | F65: =F66+F75 -> 0 | G65: =G66+G75 -> 0 | H65: =H66+H75 -> 0 | I65: =I66+I75 -> 0 | J65: =J66+J75 -> 0 | K65: =K66+K75 -> 0 | L65: =IFERROR(K65/H65,"-") -> - | M65: =M66+M75 -> 0 | N65: =N66+N75 -> 0 | O65: =O66+O75 -> 0 | P65: =IFERROR(O65/H65,"-") -> - | Q65: =IF(OR(H65>0,O65>0),"ok","-") -> -
B66: 7100 | D66: ពន្ធនិងអាករលើការនាំចូល | E66: =SUM(E67:E74) -> 0 | F66: =SUM(F67:F74) -> 0 | G66: =SUM(G67:G74) -> 0 | H66: =SUM(H67:H74) -> 0 | I66: =SUM(I67:I74) -> 0 | J66: =SUM(J67:J74) -> 0 | K66: =SUM(K67:K74) -> 0 | L66: =IFERROR(K66/H66,"-") -> - | M66: =SUM(M67:M74) -> 0 | N66: =SUM(N67:N74) -> 0 | O66: =SUM(O67:O74) -> 0 | P66: =IFERROR(O66/H66,"-") -> - | Q66: =IF(OR(H66>0,O66>0),"ok","-") -> -
C67: 71001 | D67: ពន្ធគយពីការនាំចូល | K67: =SUM(I67:J67) -> 0 | L67: =IFERROR(K67/H67,"-") -> - | P67: =IFERROR(O67/H67,"-") -> - | Q67: =IF(OR(H67>0,O67>0),"ok","-") -> -
C68: 71002 | D68: កម្រៃពីការងារគយ | K68: =SUM(I68:J68) -> 0 | L68: =IFERROR(K68/H68,"-") -> - | P68: =IFERROR(O68/H68,"-") -> - | Q68: =IF(OR(H68>0,O68>0),"ok","-") -> -
C69: 71003 | D69: ពន្ធគយលើផលិតផលតេលសិលា | K69: =SUM(I69:J69) -> 0 | L69: =IFERROR(K69/H69,"-") -> - | P69: =IFERROR(O69/H69,"-") -> - | Q69: =IF(OR(H69>0,O69>0),"ok","-") -> -
C70: 71004 | D70: អាករបន្ថែមលើផលិតផលតេលសិលាសម្រាប់ថែទាំផ្លូវថ្នល់ | K70: =SUM(I70:J70) -> 0 | L70: =IFERROR(K70/H70,"-") -> - | P70: =IFERROR(O70/H70,"-") -> - | Q70: =IF(OR(H70>0,O70>0),"ok","-") -> -
C71: 71005 | D71: ផលពីការលក់ទំនិញរឹបអូស និងទំនិញគ្មានការទាមទារ | K71: =SUM(I71:J71) -> 0 | L71: =IFERROR(K71/H71,"-") -> - | P71: =IFERROR(O71/H71,"-") -> - | Q71: =IF(OR(H71>0,O71>0),"ok","-") -> -
C72: 71006 | D72: ពិន័យផ្សេងៗលើការនាំចូល | K72: =SUM(I72:J72) -> 0 | L72: =IFERROR(K72/H72,"-") -> - | P72: =IFERROR(O72/H72,"-") -> - | Q72: =IF(OR(H72>0,O72>0),"ok","-") -> -
C73: 71007 | D73: ពន្ធនាំចូល (ជាបន្ទុករបស់រដ្ឋ) | K73: =SUM(I73:J73) -> 0 | L73: =IFERROR(K73/H73,"-") -> - | P73: =IFERROR(O73/H73,"-") -> - | Q73: =IF(OR(H73>0,O73>0),"ok","-") -> -
C74: 71008 | D74: ពន្ធនិងអាករលើការនាំចូលផ្សេងៗ | K74: =SUM(I74:J74) -> 0 | L74: =IFERROR(K74/H74,"-") -> - | P74: =IFERROR(O74/H74,"-") -> - | Q74: =IF(OR(H74>0,O74>0),"ok","-") -> -
B75: 7101 | D75: ពន្ធនិងអាករលើការនាំចេញ | E75: =SUM(E76:E81) -> 0 | F75: =SUM(F76:F81) -> 0 | G75: =SUM(G76:G81) -> 0 | H75: =SUM(H76:H81) -> 0 | I75: =SUM(I76:I81) -> 0 | J75: =SUM(J76:J81) -> 0 | K75: =SUM(K76:K81) -> 0 | L75: =IFERROR(K75/H75,"-") -> - | M75: =SUM(M76:M81) -> 0 | N75: =SUM(N76:N81) -> 0 | O75: =SUM(O76:O81) -> 0 | P75: =IFERROR(O75/H75,"-") -> - | Q75: =IF(OR(H75>0,O75>0),"ok","-") -> -
C76: 71011 | D76: អាករលើការនាំចេញឈើ | K76: =SUM(I76:J76) -> 0 | L76: =IFERROR(K76/H76,"-") -> - | P76: =IFERROR(O76/H76,"-") -> - | Q76: =IF(OR(H76>0,O76>0),"ok","-") -> -
C77: 71012 | D77: អាករលើការនាំចេញកៅស៊ូ | K77: =SUM(I77:J77) -> 0 | L77: =IFERROR(K77/H77,"-") -> - | P77: =IFERROR(O77/H77,"-") -> - | Q77: =IF(OR(H77>0,O77>0),"ok","-") -> -
C78: 71013 | D78: អាករលើការនាំចេញផលិតផលតេលសិលា | K78: =SUM(I78:J78) -> 0 | L78: =IFERROR(K78/H78,"-") -> - | P78: =IFERROR(O78/H78,"-") -> - | Q78: =IF(OR(H78>0,O78>0),"ok","-") -> -
C79: 71014 | D79: អាករលើការនាំចេញទំនិញផ្សេងៗ | K79: =SUM(I79:J79) -> 0 | L79: =IFERROR(K79/H79,"-") -> - | P79: =IFERROR(O79/H79,"-") -> - | Q79: =IF(OR(H79>0,O79>0),"ok","-") -> -
C80: 71016 | D80: ពិន័យផ្សេងៗពីការនាំចេញ | K80: =SUM(I80:J80) -> 0 | L80: =IFERROR(K80/H80,"-") -> - | P80: =IFERROR(O80/H80,"-") -> - | Q80: =IF(OR(H80>0,O80>0),"ok","-") -> -
C81: 71018 | D81: ពន្ធនិងអាករលើការនាំចេញផ្សេងៗ | K81: =SUM(I81:J81) -> 0 | L81: =IFERROR(K81/H81,"-") -> - | P81: =IFERROR(O81/H81,"-") -> - | Q81: =IF(OR(H81>0,O81>0),"ok","-") -> -
A82: ប្រភេទទី២: ចំណូល​មិនមែន​សារពើពន្ធ | E82: =E83+E101+E163+E172+E222+E238 -> 0 | F82: =F83+F101+F163+F172+F222+F238 -> 0 | G82: =G83+G101+G163+G172+G222+G238 -> 0 | H82: =H83+H101+H163+H172+H222+H238 -> 0 | I82: =I83+I101+I163+I172+I222+I238 -> 0 | J82: =J83+J101+J163+J172+J222+J238 -> 0 | K82: =K83+K101+K163+K172+K222+K238 -> 0 | L82: =IFERROR(K82/H82,"-") -> - | M82: =M83+M101+M163+M172+M222+M238 -> 0 | N82: =N83+N101+N163+N172+N222+N238 -> 0 | O82: =O83+O101+O163+O172+O222+O238 -> 0 | P82: =IFERROR(O82/H82,"-") -> - | Q82: =IF(OR(H82>0,O82>0),"ok","-") -> -
A83: 72 | D83: ផលទុននៃទ្រព្យសម្បត្តិរដ្ឋ | E83: =E84+E96 -> 0 | F83: =F84+F96 -> 0 | G83: =G84+G96 -> 0 | H83: =H84+H96 -> 0 | I83: =I84+I96 -> 0 | J83: =J84+J96 -> 0 | K83: =K84+K96 -> 0 | L83: =IFERROR(K83/H83,"-") -> - | M83: =M84+M96 -> 0 | N83: =N84+N96 -> 0 | O83: =O84+O96 -> 0 | P83: =IFERROR(O83/H83,"-") -> - | Q83: =IF(OR(H83>0,O83>0),"ok","-") -> -
B84: 7200 | D84: ផលសម្បទាន | E84: =SUM(E85:E88,E92:E95) -> 0 | F84: =SUM(F85:F88,F92:F95) -> 0 | G84: =SUM(G85:G88,G92:G95) -> 0 | H84: =SUM(H85:H88,H92:H95) -> 0 | I84: =SUM(I85:I88,I92:I95) -> 0 | J84: =SUM(J85:J88,J92:J95) -> 0 | K84: =SUM(K85:K88,K92:K95) -> 0 | L84: =IFERROR(K84/H84,"-") -> - | M84: =SUM(M85:M88,M92:M95) -> 0 | N84: =SUM(N85:N88,N92:N95) -> 0 | O84: =SUM(O85:O88,O92:O95) -> 0 | P84: =IFERROR(O84/H84,"-") -> - | Q84: =IF(OR(H84>0,O84>0),"ok","-") -> -
C85: 72001 | D85: ផលពីនេសាទ | K85: =SUM(I85:J85) -> 0 | L85: =IFERROR(K85/H85,"-") -> - | P85: =IFERROR(O85/H85,"-") -> - | Q85: =IF(OR(H85>0,O85>0),"ok","-") -> -
C86: 72002 | D86: ផលពីព្រៃឈើ | K86: =SUM(I86:J86) -> 0 | L86: =IFERROR(K86/H86,"-") -> - | P86: =IFERROR(O86/H86,"-") -> - | Q86: =IF(OR(H86>0,O86>0),"ok","-") -> -
C87: 72003 | D87: សម្បទានប្រេងកាត | K87: =SUM(I87:J87) -> 0 | L87: =IFERROR(K87/H87,"-") -> - | P87: =IFERROR(O87/H87,"-") -> - | Q87: =IF(OR(H87>0,O87>0),"ok","-") -> -
C88: 72004 | D88: សម្បទានរ៉ែ | E88: =SUM(E89:E91) -> 0 | F88: =SUM(F89:F91) -> 0 | G88: =SUM(G89:G91) -> 0 | H88: =SUM(H89:H91) -> 0 | I88: =SUM(I89:I91) -> 0 | J88: =SUM(J89:J91) -> 0 | K88: =SUM(I88:J88) -> 0 | L88: =IFERROR(K88/H88,"-") -> - | M88: =SUM(M89:M91) -> 0 | N88: =SUM(N89:N91) -> 0 | O88: =SUM(O89:O91) -> 0 | P88: =IFERROR(O88/H88,"-") -> - | Q88: =IF(OR(H88>0,O88>0),"ok","-") -> -
D89: - អាជីវកម្មរ៉ែ | K89: =SUM(I89:J89) -> 0 | L89: =IFERROR(K89/H89,"-") -> - | P89: =IFERROR(O89/H89,"-") -> - | Q89: =IF(OR(H89>0,O89>0),"ok","-") -> -
D90: - សួយសារថ្លៃឈ្នួលប្រចាំឆ្នាំ | K90: =SUM(I90:J90) -> 0 | L90: =IFERROR(K90/H90,"-") -> - | P90: =IFERROR(O90/H90,"-") -> - | Q90: =IF(OR(H90>0,O90>0),"ok","-") -> -
D91: - សួយសារដី | K91: =SUM(I91:J91) -> 0 | L91: =IFERROR(K91/H91,"-") -> - | P91: =IFERROR(O91/H91,"-") -> - | Q91: =IF(OR(H91>0,O91>0),"ok","-") -> -
C92: 72005 | D92: សម្បទានដីសេដ្ឋកិច្ច | K92: =SUM(I92:J92) -> 0 | L92: =IFERROR(K92/H92,"-") -> - | P92: =IFERROR(O92/H92,"-") -> - | Q92: =IF(OR(H92>0,O92>0),"ok","-") -> -
C93: 72006 | D93: ចំណតយានជំនិះ | K93: =SUM(I93:J93) -> 0 | L93: =IFERROR(K93/H93,"-") -> - | P93: =IFERROR(O93/H93,"-") -> - | Q93: =IF(OR(H93>0,O93>0),"ok","-") -> -
C94: 72007 | D94: ចំណតជលយាន | K94: =SUM(I94:J94) -> 0 | L94: =IFERROR(K94/H94,"-") -> - | P94: =IFERROR(O94/H94,"-") -> - | Q94: =IF(OR(H94>0,O94>0),"ok","-") -> -
C95: 72008 | D95: ផលសម្បទានផ្សេងៗ | K95: =SUM(I95:J95) -> 0 | L95: =IFERROR(K95/H95,"-") -> - | P95: =IFERROR(O95/H95,"-") -> - | Q95: =IF(OR(H95>0,O95>0),"ok","-") -> -
B96: 7201 | D96: ផលទុនពីសហគ្រាសសាធារណៈ | E96: =SUM(E97:E100) -> 0 | F96: =SUM(F97:F100) -> 0 | G96: =SUM(G97:G100) -> 0 | H96: =SUM(H97:H100) -> 0 | I96: =SUM(I97:I100) -> 0 | J96: =SUM(J97:J100) -> 0 | K96: =SUM(K97:K100) -> 0 | L96: =IFERROR(K96/H96,"-") -> - | M96: =SUM(M97:M100) -> 0 | N96: =SUM(N97:N100) -> 0 | O96: =SUM(O97:O100) -> 0 | P96: =IFERROR(O96/H96,"-") -> - | Q96: =IF(OR(H96>0,O96>0),"ok","-") -> -
C97: 72011 | D97: ការដកចំនួនលើសនៃទុនចល័ត | K97: =SUM(I97:J97) -> 0 | L97: =IFERROR(K97/H97,"-") -> - | P97: =IFERROR(O97/H97,"-") -> - | Q97: =IF(OR(H97>0,O97>0),"ok","-") -> -
C98: 72012 | D98: ភាគលាភរបស់សហគ្រាសសាធារណៈ | K98: =SUM(I98:J98) -> 0 | L98: =IFERROR(K98/H98,"-") -> - | P98: =IFERROR(O98/H98,"-") -> - | Q98: =IF(OR(H98>0,O98>0),"ok","-") -> -
C99: 72014 | D99: ប្រាក់ធានារ៉ាប់រងសង្គម | K99: =SUM(I99:J99) -> 0 | L99: =IFERROR(K99/H99,"-") -> - | P99: =IFERROR(O99/H99,"-") -> - | Q99: =IF(OR(H99>0,O99>0),"ok","-") -> -
C100: 72018 | D100: ផលទុនផ្សេងៗពីសហគ្រាសសាធារណៈ | K100: =SUM(I100:J100) -> 0 | L100: =IFERROR(K100/H100,"-") -> - | P100: =IFERROR(O100/H100,"-") -> - | Q100: =IF(OR(H100>0,O100>0),"ok","-") -> -
A101: 73 | D101: ផលទុនពីការលក់ ជួលទ្រព្យសម្បត្តិ និងសេវា | E101: =E102+E111+E120+E126+E135+E142+E149+E155 -> 0 | F101: =F102+F111+F120+F126+F135+F142+F149+F155 -> 0 | G101: =G102+G111+G120+G126+G135+G142+G149+G155 -> 0 | H101: =H102+H111+H120+H126+H135+H142+H149+H155 -> 0 | I101: =I102+I111+I120+I126+I135+I142+I149+I155 -> 0 | J101: =J102+J111+J120+J126+J135+J142+J149+J155 -> 0 | K101: =K102+K111+K120+K126+K135+K142+K149+K155 -> 0 | L101: =IFERROR(K101/H101,"-") -> - | M101: =M102+M111+M120+M126+M135+M142+M149+M155 -> 0 | N101: =N102+N111+N120+N126+N135+N142+N149+N155 -> 0 | O101: =O102+O111+O120+O126+O135+O142+O149+O155 -> 0 | P101: =IFERROR(O101/H101,"-") -> - | Q101: =IF(OR(H101>0,O101>0),"ok","-") -> -
B102: 7300 | D102: ផលទុនតាមវិស័យ | E102: =SUM(E103:E110) -> 0 | F102: =SUM(F103:F110) -> 0 | G102: =SUM(G103:G110) -> 0 | H102: =SUM(H103:H110) -> 0 | I102: =SUM(I103:I110) -> 0 | J102: =SUM(J103:J110) -> 0 | K102: =SUM(K103:K110) -> 0 | L102: =IFERROR(K102/H102,"-") -> - | M102: =SUM(M103:M110) -> 0 | N102: =SUM(N103:N110) -> 0 | O102: =SUM(O103:O110) -> 0 | P102: =IFERROR(O102/H102,"-") -> - | Q102: =IF(OR(H102>0,O102>0),"ok","-") -> -
C103: 73001 | D103: ផលទុនអាកាសចរស៊ីវិល | K103: =SUM(I103:J103) -> 0 | L103: =IFERROR(K103/H103,"-") -> - | P103: =IFERROR(O103/H103,"-") -> - | Q103: =IF(OR(H103>0,O103>0),"ok","-") -> -
C104: 73002 | D104: ផលទុននៃសកម្មភាពភាពយន្ត | K104: =SUM(I104:J104) -> 0 | L104: =IFERROR(K104/H104,"-") -> - | P104: =IFERROR(O104/H104,"-") -> - | Q104: =IF(OR(H104>0,O104>0),"ok","-") -> -
C105: 73003 | D105: ផលទុននៃសកម្មភាពទេសចរណ៍ | K105: =SUM(I105:J105) -> 0 | L105: =IFERROR(K105/H105,"-") -> - | P105: =IFERROR(O105/H105,"-") -> - | Q105: =IF(OR(H105>0,O105>0),"ok","-") -> -
C106: 73004 | D106: ផលទុននៃសកម្មភាពវប្បធម៌ | K106: =SUM(I106:J106) -> 0 | L106: =IFERROR(K106/H106,"-") -> - | P106: =IFERROR(O106/H106,"-") -> - | Q106: =IF(OR(H106>0,O106>0),"ok","-") -> -
...

Sheet PB2-Exp
A5: គម្រោងថវិកាឆ្នាំ២០២៣
A6: គម្រោងចំណាយថវិកាតាមចំណាត់ថ្នាក់សេដ្ឋកិច្ច
A7: =Costing!$K$11 -> អគ្គនាយកដ្ឋានគោលនយោបាយ
T8: តារាងទី២ (តារាង ២"ក" ក្នុងសារាចររៀបចំគម្រោងថវិកាប្រចាំឆ្នាំ)
T9: ឯកតា៖ លានរៀល
D10: កូដអនុកម្មវិធី
A12: ជំពូក | B12: គណនី | C12: អនុគណនី | D12: ចំណាត់ថ្នាក់ចំណាយ (តាមតារាងមាតិកាថវិកា ) | E12: ចំណាយ ឆ្នាំ២០២១ (អនុវត្ត) | F12: ច្បាប់ហិរញ្ញវត្ថុឆ្នាំ២០២២ | I12: ប៉ាន់ស្មានអនុវត្តឆ្នាំ២០២២ | N12: គម្រោងថវិកាឆ្នាំ២០២៣ | Q12: កើន/ថយធៀប'២២ | S12: ចំណាយមិនប្រចាំ | T12: សង្ខេបបរិយាយមូលហេតុកើន/ថយ​ តាមគណនី ឬអនុគណនី
F13: ឥណទានដើមឆ្នាំ | G13: ឥណទាន វិចារណកម្ម | H13: ឥណទានថ្មី | I13: អនុវត្ដជាក់ស្ដែង ឆមាសទី១ | J13: ប៉ាន់ស្មានឆមាសទី២ | K13: ប៉ាន់​ស្មាន​ប្រចាំ​ឆ្នាំ | N13: ទឹកប្រាក់ | O13: %ឥ.ច្ប ២០២២ | P13: %ឥ.ថ្មី ២០២២ | Q13: ទឹកប្រាក់ | R13: %ឥ.ច្ប ២០២២
K14: ទឹកប្រាក់ | L14: %ឥ.ច្ប | M14: %ឥ.ថ្មី
A15: សរុបចំណាយថវិកាទូទៅរបស់រដ្ឋ (ក+ខ) | E15: =E16+E343 -> 21633.013 | F15: =F16+F343 -> 2069.399 | G15: =G16+G343 -> 0 | H15: =H16+H343 -> 2069.399 | I15: =I16+I343 -> 992.87 | J15: =J16+J343 -> 1076.529 | K15: =K16+K343 -> 2069.399 | L15: =IFERROR(K15/F15,"-") -> 1 | M15: =IFERROR(K15/H15,"-") -> 1 | N15: =N16+N343 -> #REF! | O15: =IFERROR(N15/F15,"-") -> - | P15: =IFERROR(N15/H15,"-") -> - | Q15: =Q16+Q343 -> #REF! | R15: =IFERROR(Q15/F15,"-") -> - | S15: =S16+S343 -> #REF! | U15: =IF(OR(F15>0,H15>0,N15>0),"ok","-") -> #REF!
A16: ក/.សរុបចំណាយចរន្ត (ក្រុមទី១+ក្រុមទី២) | E16: =E17+E324 -> 21633.013 | F16: =F17+F324 -> 2069.399 | G16: =G17+G324 -> 0 | H16: =H17+H324 -> 2069.399 | I16: =I17+I324 -> 992.87 | J16: =J17+J324 -> 1076.529 | K16: =K17+K324 -> 2069.399 | L16: =IFERROR(K16/F16,"-") -> 1 | M16: =IFERROR(K16/H16,"-") -> 1 | N16: =N17+N324 -> #REF! | O16: =IFERROR(N16/F16,"-") -> - | P16: =IFERROR(N16/H16,"-") -> - | Q16: =Q17+Q324 -> #REF! | R16: =IFERROR(Q16/F16,"-") -> - | S16: =S17+S324 -> #REF! | U16: =IF(OR(F16>0,H16>0,N16>0),"ok","-") -> #REF!
A17: ក្រុមទី១:ចំណាយពិត (ប្រភេទ១+២+៣+៤) | E17: =E18+E201+E215+E295 -> 21633.013 | F17: =F18+F201+F215+F295 -> 2069.399 | G17: =G18+G201+G215+G295 -> 0 | H17: =H18+H201+H215+H295 -> 2069.399 | I17: =I18+I201+I215+I295 -> 992.87 | J17: =J18+J201+J215+J295 -> 1076.529 | K17: =K18+K201+K215+K295 -> 2069.399 | L17: =IFERROR(K17/F17,"-") -> 1 | M17: =IFERROR(K17/H17,"-") -> 1 | N17: =N18+N201+N215+N295 -> #REF! | O17: =IFERROR(N17/F17,"-") -> - | P17: =IFERROR(N17/H17,"-") -> - | Q17: =Q18+Q201+Q215+Q295 -> #REF! | R17: =IFERROR(Q17/F17,"-") -> - | S17: =S18+S201+S215+S295 -> #REF! | U17: =IF(OR(F17>0,H17>0,N17>0),"ok","-") -> #REF!
A18: ប្រភេទទី១:មធ្យោបាយសេវា | E18: =E19+E63+E148 -> 1633.013 | F18: =F19+F63+F148 -> 2069.399 | G18: =G19+G63+G148 -> 0 | H18: =H19+H63+H148 -> 2069.399 | I18: =I19+I63+I148 -> 992.87 | J18: =J19+J63+J148 -> 1076.529 | K18: =K19+K63+K148 -> 2069.399 | L18: =IFERROR(K18/F18,"-") -> 1 | M18: =IFERROR(K18/H18,"-") -> 1 | N18: =N19+N63+N148 -> #REF! | O18: =IFERROR(N18/F18,"-") -> - | P18: =IFERROR(N18/H18,"-") -> - | Q18: =Q19+Q63+Q148 -> #REF! | R18: =IFERROR(Q18/F18,"-") -> - | S18: =S19+S63+S148 -> #REF! | U18: =IF(OR(F18>0,H18>0,N18>0),"ok","-") -> #REF!
A19: 60 | D19: ការទិញ | E19: =E20+E27+E32+E41+E46+E53+E57+E61 -> 247.847 | F19: =F20+F27+F32+F41+F46+F53+F57+F61 -> 322 | G19: =G20+G27+G32+G41+G46+G53+G57+G61 -> 0 | H19: =H20+H27+H32+H41+H46+H53+H57+H61 -> 322 | I19: =I20+I27+I32+I41+I46+I53+I57+I61 -> 279.97 | J19: =J20+J27+J32+J41+J46+J53+J57+J61 -> 42.03 | K19: =K20+K27+K32+K41+K46+K53+K57+K61 -> 322 | L19: =IFERROR(K19/F19,"-") -> 1 | M19: =IFERROR(K19/H19,"-") -> 1 | N19: =N20+N27+N32+N41+N46+N53+N57+N61 -> #REF! | O19: =IFERROR(N19/F19,"-") -> - | P19: =IFERROR(N19/H19,"-") -> - | Q19: =Q20+Q27+Q32+Q41+Q46+Q53+Q57+Q61 -> #REF! | R19: =IFERROR(Q19/F19,"-") -> - | S19: =S20+S27+S32+S41+S46+S53+S57+S61 -> #REF! | U19: =IF(OR(F19>0,H19>0,N19>0),"ok","-") -> #REF!
B20: 6001 | D20: សម្ភារផ្គត់ផ្គង់ថែទាំ | E20: =SUM(E21:E26) -> 86.662 | F20: =SUM(F21:F26) -> 104.3 | G20: =SUM(G21:G26) -> 0 | H20: =SUM(H21:H26) -> 104.3 | I20: =SUM(I21:I26) -> 96.81 | J20: =SUM(J21:J26) -> 7.49 | K20: =SUM(K21:K26) -> 104.3 | L20: =IFERROR(K20/F20,"-") -> 1 | M20: =IFERROR(K20/H20,"-") -> 1 | N20: =SUM(N21:N26) -> #REF! | O20: =IFERROR(N20/F20,"-") -> - | P20: =IFERROR(N20/H20,"-") -> - | Q20: =SUM(Q21:Q26) -> #REF! | R20: =IFERROR(Q20/F20,"-") -> - | S20: =SUM(S21:S26) -> #REF! | U20: =IF(OR(F20>0,H20>0,N20>0),"ok","-") -> #REF!
C21: 60011 | D21: សម្ភារផ្គត់ផ្គង់សម្អាតនិងអនាម័យ | E21: 33.355 | F21: 48.4 | H21: 48.4 | I21: 40.92 | J21: =H21-I21 -> 7.48 | K21: =SUM(I21:J21) -> 48.4 | L21: =IFERROR(K21/F21,"-") -> 1 | M21: =IFERROR(K21/H21,"-") -> 1 | N21: =#REF! -> #REF! | O21: =IFERROR(N21/F21,"-") -> - | P21: =IFERROR(N21/H21,"-") -> - | Q21: =N21-F21 -> #REF! | R21: =IFERROR(Q21/F21,"-") -> - | S21: =#REF! -> #REF! | T21: កើនលើការបន្ថែមសម្ភារៈអនាម័យសម្រាប់នាយកដ្ឋានថ្មី២ | U21: =IF(OR(F21>0,H21>0,N21>0),"ok","-") -> #REF!
C22: 60012 | D22: សម្ភារផ្គត់ផ្គង់សម្រាប់ថែទាំអគារ ប្រាសាទ និងសំណង់ផ្សេងៗ | J22: =H22-I22 -> 0 | K22: =SUM(I22:J22) -> 0 | L22: =IFERROR(K22/F22,"-") -> - | M22: =IFERROR(K22/H22,"-") -> - | N22: =#REF! -> #REF! | O22: =IFERROR(N22/F22,"-") -> - | P22: =IFERROR(N22/H22,"-") -> - | Q22: =N22-F22 -> #REF! | R22: =IFERROR(Q22/F22,"-") -> - | S22: =#REF! -> #REF! | U22: =IF(OR(F22>0,H22>0,N22>0),"ok","-") -> #REF!
C23: 60013 | D23: សម្ភារផ្គត់ផ្គង់សម្រាប់ថែទាំផ្លូវថ្នល់ ស្ពាន និងលូ | J23: =H23-I23 -> 0 | K23: =SUM(I23:J23) -> 0 | L23: =IFERROR(K23/F23,"-") -> - | M23: =IFERROR(K23/H23,"-") -> - | N23: =#REF! -> #REF! | O23: =IFERROR(N23/F23,"-") -> - | P23: =IFERROR(N23/H23,"-") -> - | Q23: =N23-F23 -> #REF! | R23: =IFERROR(Q23/F23,"-") -> - | S23: =#REF! -> #REF! | U23: =IF(OR(F23>0,H23>0,N23>0),"ok","-") -> #REF!
C24: 60014 | D24: សម្ភារផ្គត់ផ្គង់សម្រាប់ថែទាំសម្ភារ ឧបករណ៍ | E24: 26.207 | F24: 28.8 | H24: 28.8 | I24: 28.79 | J24: =H24-I24 -> 0.01 | K24: =SUM(I24:J24) -> 28.8 | L24: =IFERROR(K24/F24,"-") -> 1 | M24: =IFERROR(K24/H24,"-") -> 1 | N24: =#REF! -> #REF! | O24: =IFERROR(N24/F24,"-") -> - | P24: =IFERROR(N24/H24,"-") -> - | Q24: =N24-F24 -> #REF! | R24: =IFERROR(Q24/F24,"-") -> - | S24: =#REF! -> #REF! | T24: កើនលើការបន្ថែមការទិញសំបកកង់រថយន្តជូនថ្នាក់ដឹកនាំសម្រាប់នាយកដ្ឋានថ្មី២ | U24: =IF(OR(F24>0,H24>0,N24>0),"ok","-") -> #REF!
C25: 60015 | D25: ប្រេងឥន្ធនៈនិងប្រេងរំអិល | E25: =54.2/2 -> 27.1 | F25: 27.1 | H25: 27.1 | I25: 27.1 | J25: =H25-I25 -> 0 | K25: =SUM(I25:J25) -> 27.1 | L25: =IFERROR(K25/F25,"-") -> 1 | M25: =IFERROR(K25/H25,"-") -> 1 | N25: =#REF! -> #REF! | O25: =IFERROR(N25/F25,"-") -> - | P25: =IFERROR(N25/H25,"-") -> - | Q25: =N25-F25 -> #REF! | R25: =IFERROR(Q25/F25,"-") -> - | S25: =#REF! -> #REF! | T25: កើនដោយសារតម្លៃប្រេងលើទីផ្សារកើនឡើង និងលើការបន្ថែមថវិកាសម្រាប់នាយកដ្ឋានថ្មី២ | U25: =IF(OR(F25>0,H25>0,N25>0),"ok","-") -> #REF!
C26: 60018 | D26: សម្ភារផ្គត់ផ្គង់ថែទាំផ្សេងៗ | J26: =H26-I26 -> 0 | K26: =SUM(I26:J26) -> 0 | L26: =IFERROR(K26/F26,"-") -> - | M26: =IFERROR(K26/H26,"-") -> - | N26: =#REF! -> #REF! | O26: =IFERROR(N26/F26,"-") -> - | P26: =IFERROR(N26/H26,"-") -> - | Q26: =N26-F26 -> #REF! | R26: =IFERROR(Q26/F26,"-") -> - | S26: =#REF! -> #REF! | U26: =IF(OR(F26>0,H26>0,N26>0),"ok","-") -> #REF!
B27: 6002 | D27: សម្ភារផ្គត់ផ្គង់ផ្នែករដ្ឋបាល | E27: =SUM(E28:E31) -> 98.34 | F27: =SUM(F28:F31) -> 106 | G27: =SUM(G28:G31) -> 0 | H27: =SUM(H28:H31) -> 106 | I27: =SUM(I28:I31) -> 88.29 | J27: =SUM(J28:J31) -> 17.71 | K27: =SUM(K28:K31) -> 106 | L27: =IFERROR(K27/F27,"-") -> 1 | M27: =IFERROR(K27/H27,"-") -> 1 | N27: =SUM(N28:N31) -> #REF! | O27: =IFERROR(N27/F27,"-") -> - | P27: =IFERROR(N27/H27,"-") -> - | Q27: =SUM(Q28:Q31) -> #REF! | R27: =IFERROR(Q27/F27,"-") -> - | S27: =SUM(S28:S31) -> #REF! | U27: =IF(OR(F27>0,H27>0,N27>0),"ok","-") -> #REF!
C28: 60021 | D28: សម្ភារការិយាល័យ | E28: 73.468 | F28: 106 | H28: 106 | I28: 88.29 | J28: =H28-I28 -> 17.71 | K28: =SUM(I28:J28) -> 106 | L28: =IFERROR(K28/F28,"-") -> 1 | M28: =IFERROR(K28/H28,"-") -> 1 | N28: =#REF! -> #REF! | O28: =IFERROR(N28/F28,"-") -> - | P28: =IFERROR(N28/H28,"-") -> - | Q28: =N28-F28 -> #REF! | R28: =IFERROR(Q28/F28,"-") -> - | S28: =#REF! -> #REF! | T28: កើនលើការបន្ថែមសម្ភារៈការិយាល័យសម្រាប់នាយកដ្ឋានថ្មី២ | U28: =IF(OR(F28>0,H28>0,N28>0),"ok","-") -> #REF!
C29: 60022 | D29: សៀវភៅមើលនិងឯកសារ | J29: =I29-H29 -> 0 | K29: =SUM(I29:J29) -> 0 | L29: =IFERROR(K29/F29,"-") -> - | M29: =IFERROR(K29/H29,"-") -> - | N29: =#REF! -> #REF! | O29: =IFERROR(N29/F29,"-") -> - | P29: =IFERROR(N29/H29,"-") -> - | Q29: =N29-F29 -> #REF! | R29: =IFERROR(Q29/F29,"-") -> - | S29: =#REF! -> #REF! | U29: =IF(OR(F29>0,H29>0,N29>0),"ok","-") -> #REF!
C30: 60023 | D30: ការបោះពុម្ព | E30: 24.872 | J30: =I30-H30 -> 0 | K30: =SUM(I30:J30) -> 0 | L30: =IFERROR(K30/F30,"-") -> - | M30: =IFERROR(K30/H30,"-") -> - | N30: =#REF! -> #REF! | O30: =IFERROR(N30/F30,"-") -> - | P30: =IFERROR(N30/H30,"-") -> - | Q30: =N30-F30 -> #REF! | R30: =IFERROR(Q30/F30,"-") -> - | S30: =#REF! -> #REF! | U30: =IF(OR(F30>0,H30>0,N30>0),"ok","-") -> #REF!
C31: 60028 | D31: សម្ភារផ្គត់ផ្គង់ផ្នែករដ្ឋបាលផ្សេងៗ | J31: =I31-H31 -> 0 | K31: =SUM(I31:J31) -> 0 | L31: =IFERROR(K31/F31,"-") -> - | M31: =IFERROR(K31/H31,"-") -> - | N31: =#REF! -> #REF! | O31: =IFERROR(N31/F31,"-") -> - | P31: =IFERROR(N31/H31,"-") -> - | Q31: =N31-F31 -> #REF! | R31: =IFERROR(Q31/F31,"-") -> - | S31: =#REF! -> #REF! | U31: =IF(OR(F31>0,H31>0,N31>0),"ok","-") -> #REF!
B32: 6003 | D32: ស្បៀងអាហារនិងផលិតផលកសិកម្ម | E32: =SUM(E33:E40) -> 42.934 | F32: =SUM(F33:F40) -> 56.8 | G32: =SUM(G33:G40) -> 0 | H32: =SUM(H33:H40) -> 56.8 | I32: =SUM(I33:I40) -> 47.36 | J32: =SUM(J33:J40) -> 9.44 | K32: =SUM(K33:K40) -> 56.8 | L32: =IFERROR(K32/F32,"-") -> 1 | M32: =IFERROR(K32/H32,"-") -> 1 | N32: =SUM(N33:N40) -> #REF! | O32: =IFERROR(N32/F32,"-") -> - | P32: =IFERROR(N32/H32,"-") -> - | Q32: =SUM(Q33:Q40) -> #REF! | R32: =IFERROR(Q32/F32,"-") -> - | S32: =SUM(S33:S40) -> #REF! | U32: =IF(OR(F32>0,H32>0,N32>0),"ok","-") -> #REF!
C33: 60031 | D33: ស្បៀង | K33: =SUM(I33:J33) -> 0 | L33: =IFERROR(K33/F33,"-") -> - | M33: =IFERROR(K33/H33,"-") -> - | N33: =#REF! -> #REF! | O33: =IFERROR(N33/F33,"-") -> - | P33: =IFERROR(N33/H33,"-") -> - | Q33: =N33-F33 -> #REF! | R33: =IFERROR(Q33/F33,"-") -> - | S33: =#REF! -> #REF! | U33: =IF(OR(F33>0,H33>0,N33>0),"ok","-") -> #REF!
C34: 60032 | D34: ចំណីសត្វ | K34: =SUM(I34:J34) -> 0 | L34: =IFERROR(K34/F34,"-") -> - | M34: =IFERROR(K34/H34,"-") -> - | N34: =#REF! -> #REF! | O34: =IFERROR(N34/F34,"-") -> - | P34: =IFERROR(N34/H34,"-") -> - | Q34: =N34-F34 -> #REF! | R34: =IFERROR(Q34/F34,"-") -> - | S34: =#REF! -> #REF! | U34: =IF(OR(F34>0,H34>0,N34>0),"ok","-") -> #REF!
C35: 60033 | D35: ពូជនិងកូនរុក្ខជាតិ | K35: =SUM(I35:J35) -> 0 | L35: =IFERROR(K35/F35,"-") -> - | M35: =IFERROR(K35/H35,"-") -> - | N35: =#REF! -> #REF! | O35: =IFERROR(N35/F35,"-") -> - | P35: =IFERROR(N35/H35,"-") -> - | Q35: =N35-F35 -> #REF! | R35: =IFERROR(Q35/F35,"-") -> - | S35: =#REF! -> #REF! | U35: =IF(OR(F35>0,H35>0,N35>0),"ok","-") -> #REF!
C36: 60034 | D36: ផលិតផលការពារសុខុមាលភាពរុក្ខជាតិនិងជី | K36: =SUM(I36:J36) -> 0 | L36: =IFERROR(K36/F36,"-") -> - | M36: =IFERROR(K36/H36,"-") -> - | N36: =#REF! -> #REF! | O36: =IFERROR(N36/F36,"-") -> - | P36: =IFERROR(N36/H36,"-") -> - | Q36: =N36-F36 -> #REF! | R36: =IFERROR(Q36/F36,"-") -> - | S36: =#REF! -> #REF! | U36: =IF(OR(F36>0,H36>0,N36>0),"ok","-") -> #REF!
C37: 60035 | D37: ពូជសត្វ | K37: =SUM(I37:J37) -> 0 | L37: =IFERROR(K37/F37,"-") -> - | M37: =IFERROR(K37/H37,"-") -> - | N37: =#REF! -> #REF! | O37: =IFERROR(N37/F37,"-") -> - | P37: =IFERROR(N37/H37,"-") -> - | Q37: =N37-F37 -> #REF! | R37: =IFERROR(Q37/F37,"-") -> - | S37: =#REF! -> #REF! | U37: =IF(OR(F37>0,H37>0,N37>0),"ok","-") -> #REF!
C38: 60036 | D38: ឱសថ និងវត្ថុធាតុសម្រាប់បសុពេទ្យ | K38: =SUM(I38:J38) -> 0 | L38: =IFERROR(K38/F38,"-") -> - | M38: =IFERROR(K38/H38,"-") -> - | N38: =#REF! -> #REF! | O38: =IFERROR(N38/F38,"-") -> - | P38: =IFERROR(N38/H38,"-") -> - | Q38: =N38-F38 -> #REF! | R38: =IFERROR(Q38/F38,"-") -> - | S38: =#REF! -> #REF! | U38: =IF(OR(F38>0,H38>0,N38>0),"ok","-") -> #REF!
C39: 60037 | D39: ស្បៀងសម្រាប់រដ្ឋបាល | E39: 42.934 | F39: 56.8 | H39: 56.8 | I39: 47.36 | J39: =H39-I39 -> 9.44 | K39: =SUM(I39:J39) -> 56.8 | L39: =IFERROR(K39/F39,"-") -> 1 | M39: =IFERROR(K39/H39,"-") -> 1 | N39: =#REF! -> #REF! | O39: =IFERROR(N39/F39,"-") -> - | P39: =IFERROR(N39/H39,"-") -> - | Q39: =N39-F39 -> #REF! | R39: =IFERROR(Q39/F39,"-") -> - | S39: =#REF! -> #REF! | T39: កើនលើការបន្ថែមស្បៀងសម្រាប់ប្រើប្រាស់លើនាយកដ្ឋានថ្មី២ | U39: =IF(OR(F39>0,H39>0,N39>0),"ok","-") -> #REF!
C40: 60038 | D40: ស្បៀងអាហារ និងផលិតផលកសិកម្មផ្សេងៗ | K40: =SUM(I40:J40) -> 0 | L40: =IFERROR(K40/F40,"-") -> - | M40: =IFERROR(K40/H40,"-") -> - | N40: =#REF! -> #REF! | O40: =IFERROR(N40/F40,"-") -> - | P40: =IFERROR(N40/H40,"-") -> - | Q40: =N40-F40 -> #REF! | R40: =IFERROR(Q40/F40,"-") -> - | S40: =#REF! -> #REF! | U40: =IF(OR(F40>0,H40>0,N40>0),"ok","-") -> #REF!
B41: 6004 | D41: សំលៀកបំពាក់និងការតុបតែង | E41: =SUM(E42:E45) -> 0 | F41: =SUM(F42:F45) -> 0 | G41: =SUM(G42:G45) -> 0 | H41: =SUM(H42:H45) -> 0 | I41: =SUM(I42:I45) -> 0 | J41: =SUM(J42:J45) -> 0 | K41: =SUM(K42:K45) -> 0 | L41: =IFERROR(K41/F41,"-") -> - | M41: =IFERROR(K41/H41,"-") -> - | N41: =SUM(N42:N45) -> #REF! | O41: =IFERROR(N41/F41,"-") -> - | P41: =IFERROR(N41/H41,"-") -> - | Q41: =SUM(Q42:Q45) -> #REF! | R41: =IFERROR(Q41/F41,"-") -> - | S41: =SUM(S42:S45) -> #REF! | U41: =IF(OR(F41>0,H41>0,N41>0),"ok","-") -> #REF!
C42: 60041 | D42: ឯកសណ្ឋាន | K42: =SUM(I42:J42) -> 0 | L42: =IFERROR(K42/F42,"-") -> - | M42: =IFERROR(K42/H42,"-") -> - | N42: =#REF! -> #REF! | O42: =IFERROR(N42/F42,"-") -> - | P42: =IFERROR(N42/H42,"-") -> - | Q42: =N42-F42 -> #REF! | R42: =IFERROR(Q42/F42,"-") -> - | S42: =#REF! -> #REF! | U42: =IF(OR(F42>0,H42>0,N42>0),"ok","-") -> #REF!
C43: 60042 | D43: សំលៀកបំពាក់ការពារសុវត្ថិភាព | K43: =SUM(I43:J43) -> 0 | L43: =IFERROR(K43/F43,"-") -> - | M43: =IFERROR(K43/H43,"-") -> - | N43: =#REF! -> #REF! | O43: =IFERROR(N43/F43,"-") -> - | P43: =IFERROR(N43/H43,"-") -> - | Q43: =N43-F43 -> #REF! | R43: =IFERROR(Q43/F43,"-") -> - | S43: =#REF! -> #REF! | U43: =IF(OR(F43>0,H43>0,N43>0),"ok","-") -> #REF!
C44: 60043 | D44: មេដាយ (គ្រឿងឥស្សរិយយស) | K44: =SUM(I44:J44) -> 0 | L44: =IFERROR(K44/F44,"-") -> - | M44: =IFERROR(K44/H44,"-") -> - | N44: =#REF! -> #REF! | O44: =IFERROR(N44/F44,"-") -> - | P44: =IFERROR(N44/H44,"-") -> - | Q44: =N44-F44 -> #REF! | R44: =IFERROR(Q44/F44,"-") -> - | S44: =#REF! -> #REF! | U44: =IF(OR(F44>0,H44>0,N44>0),"ok","-") -> #REF!
C45: 60048 | D45: សំលៀកបំពាក់និងការតុបតែងផ្សេងៗ | K45: =SUM(I45:J45) -> 0 | L45: =IFERROR(K45/F45,"-") -> - | M45: =IFERROR(K45/H45,"-") -> - | N45: =#REF! -> #REF! | O45: =IFERROR(N45/F45,"-") -> - | P45: =IFERROR(N45/H45,"-") -> - | Q45: =N45-F45 -> #REF! | R45: =IFERROR(Q45/F45,"-") -> - | S45: =#REF! -> #REF! | U45: =IF(OR(F45>0,H45>0,N45>0),"ok","-") -> #REF!
B46: 6005 | D46: សម្ភារតូចតាច សង្ហារឹម និងសម្ភារបរិក្ខារ | E46: =SUM(E47:E52) -> 19.911 | F46: =SUM(F47:F52) -> 54.9 | G46: =SUM(G47:G52) -> 0 | H46: =SUM(H47:H52) -> 54.9 | I46: =SUM(I47:I52) -> 47.51 | J46: =SUM(J47:J52) -> 7.39 | K46: =SUM(K47:K52) -> 54.9 | L46: =IFERROR(K46/F46,"-") -> 1 | M46: =IFERROR(K46/H46,"-") -> 1 | N46: =SUM(N47:N52) -> #REF! | O46: =IFERROR(N46/F46,"-") -> - | P46: =IFERROR(N46/H46,"-") -> - | Q46: =SUM(Q47:Q52) -> #REF! | R46: =IFERROR(Q46/F46,"-") -> - | S46: =SUM(S47:S52) -> #REF! | U46: =IF(OR(F46>0,H46>0,N46>0),"ok","-") -> #REF!
C47: 60051 | D47: សម្ភារនិងបរិក្ខារបច្ចេកទេសមិនមែនព័ត៌មានវិទ្យា | E47: 0.298 | F47: 4 | H47: 4 | I47: 4 | J47: =H47-I47 -> 0 | K47: =SUM(I47:J47) -> 4 | L47: =IFERROR(K47/F47,"-") -> 1 | M47: =IFERROR(K47/H47,"-") -> 1 | N47: =#REF! -> #REF! | O47: =IFERROR(N47/F47,"-") -> - | P47: =IFERROR(N47/H47,"-") -> - | Q47: =N47-F47 -> #REF! | R47: =IFERROR(Q47/F47,"-") -> - | S47: =#REF! -> #REF! | T47: កើនលើការទិញទូទឹកកក និងម៉ាស៊ីនទឹកក្តៅ សម្រាប់នាយកដ្ឋានថ្មី២ | U47: =IF(OR(F47>0,H47>0,N47>0),"ok","-") -> #REF!
C48: 60052 | D48: សង្ហារឹម | E48: 6.988 | F48: 10.9 | H48: 10.9 | I48: 9.5 | J48: =H48-I48 -> 1.4 | K48: =SUM(I48:J48) -> 10.9 | L48: =IFERROR(K48/F48,"-") -> 1 | M48: =IFERROR(K48/H48,"-") -> 1 | N48: =#REF! -> #REF! | O48: =IFERROR(N48/F48,"-") -> - | P48: =IFERROR(N48/H48,"-") -> - | Q48: =N48-F48 -> #REF! | R48: =IFERROR(Q48/F48,"-") -> - | S48: =#REF! -> #REF! | T48: កើនលើការទិញតុ និងកៅអី សម្រាប់មន្ត្រីក្នុងនាយកដ្ឋានថ្មី២ | U48: =IF(OR(F48>0,H48>0,N48>0),"ok","-") -> #REF!
C49: 60053 | D49: សម្ភារប្រើប្រាស់ | E49: 4.085 | F49: 12 | H49: 12 | I49: 10 | J49: =H49-I49 -> 2 | K49: =SUM(I49:J49) -> 12 | L49: =IFERROR(K49/F49,"-") -> 1 | M49: =IFERROR(K49/H49,"-") -> 1 | N49: =#REF! -> #REF! | O49: =IFERROR(N49/F49,"-") -> - | P49: =IFERROR(N49/H49,"-") -> - | Q49: =N49-F49 -> #REF! | R49: =IFERROR(Q49/F49,"-") -> - | S49: =#REF! -> #REF! | U49: =IF(OR(F49>0,H49>0,N49>0),"ok","-") -> #REF!
C50: 60054 | D50: សម្ភារនិងឧបករណ៍ដឹកជញ្ជូន | J50: =H50-I50 -> 0 | K50: =SUM(I50:J50) -> 0 | L50: =IFERROR(K50/F50,"-") -> - | M50: =IFERROR(K50/H50,"-") -> - | N50: =#REF! -> #REF! | O50: =IFERROR(N50/F50,"-") -> - | P50: =IFERROR(N50/H50,"-") -> - | Q50: =N50-F50 -> #REF! | R50: =IFERROR(Q50/F50,"-") -> - | S50: =#REF! -> #REF! | U50: =IF(OR(F50>0,H50>0,N50>0),"ok","-") -> #REF!
C51: 60055 | D51: សម្ភារនិងបរិក្ខារបច្ចេកទេសព័ត៌មានវិទ្យា | E51: 4.968 | F51: 20 | H51: 20 | I51: 17.01 | J51: =H51-I51 -> 2.99 | K51: =SUM(I51:J51) -> 20 | L51: =IFERROR(K51/F51,"-") -> 1 | M51: =IFERROR(K51/H51,"-") -> 1 | N51: =#REF! -> #REF! | O51: =IFERROR(N51/F51,"-") -> - | P51: =IFERROR(N51/H51,"-") -> - | Q51: =N51-F51 -> #REF! | R51: =IFERROR(Q51/F51,"-") -> - | S51: =#REF! -> #REF! | T51: កើនលើការគ្រោងទិញម៉ាស៊ីនព្រីនធ័រ និង projector សម្រាប់នាយកដ្ឋានថ្មី២ | U51: =IF(OR(F51>0,H51>0,N51>0),"ok","-") -> #REF!
C52: 60058 | D52: សម្ភារតូចតាច សង្ហារឹម និងសម្ភារបរិក្ខារផ្សេងៗ | E52: 3.572 | F52: 8 | H52: 8 | I52: 7 | J52: =H52-I52 -> 1 | K52: =SUM(I52:J52) -> 8 | L52: =IFERROR(K52/F52,"-") -> 1 | M52: =IFERROR(K52/H52,"-") -> 1 | N52: =#REF! -> #REF! | O52: =IFERROR(N52/F52,"-") -> - | P52: =IFERROR(N52/H52,"-") -> - | Q52: =N52-F52 -> #REF! | R52: =IFERROR(Q52/F52,"-") -> - | S52: =#REF! -> #REF! | U52: =IF(OR(F52>0,H52>0,N52>0),"ok","-") -> #REF!
B53: 6006 | D53: ថាមពលនិងទឹក | E53: =SUM(E54:E56) -> 0 | F53: =SUM(F54:F56) -> 0 | G53: =SUM(G54:G56) -> 0 | H53: =SUM(H54:H56) -> 0 | I53: =SUM(I54:I56) -> 0 | J53: =SUM(J54:J56) -> 0 | K53: =SUM(K54:K56) -> 0 | L53: =IFERROR(K53/F53,"-") -> - | M53: =IFERROR(K53/H53,"-") -> - | N53: =SUM(N54:N56) -> #REF! | O53: =IFERROR(N53/F53,"-") -> - | P53: =IFERROR(N53/H53,"-") -> - | Q53: =SUM(Q54:Q56) -> #REF! | R53: =IFERROR(Q53/F53,"-") -> - | S53: =SUM(S54:S56) -> #REF! | U53: =IF(OR(F53>0,H53>0,N53>0),"ok","-") -> #REF!
C54: 60061 | D54: អគ្គិសនី | K54: =SUM(I54:J54) -> 0 | L54: =IFERROR(K54/F54,"-") -> - | M54: =IFERROR(K54/H54,"-") -> - | N54: =#REF! -> #REF! | O54: =IFERROR(N54/F54,"-") -> - | P54: =IFERROR(N54/H54,"-") -> - | Q54: =N54-F54 -> #REF! | R54: =IFERROR(Q54/F54,"-") -> - | S54: =#REF! -> #REF! | U54: =IF(OR(F54>0,H54>0,N54>0),"ok","-") -> #REF!
C55: 60062 | D55: ទឹក | K55: =SUM(I55:J55) -> 0 | L55: =IFERROR(K55/F55,"-") -> - | M55: =IFERROR(K55/H55,"-") -> - | N55: =#REF! -> #REF! | O55: =IFERROR(N55/F55,"-") -> - | P55: =IFERROR(N55/H55,"-") -> - | Q55: =N55-F55 -> #REF! | R55: =IFERROR(Q55/F55,"-") -> - | S55: =#REF! -> #REF! | U55: =IF(OR(F55>0,H55>0,N55>0),"ok","-") -> #REF!
C56: 60068 | D56: ផ្សេងៗ | K56: =SUM(I56:J56) -> 0 | L56: =IFERROR(K56/F56,"-") -> - | M56: =IFERROR(K56/H56,"-") -> - | N56: =#REF! -> #REF! | O56: =IFERROR(N56/F56,"-") -> - | P56: =IFERROR(N56/H56,"-") -> - | Q56: =N56-F56 -> #REF! | R56: =IFERROR(Q56/F56,"-") -> - | S56: =#REF! -> #REF! | U56: =IF(OR(F56>0,H56>0,N56>0),"ok","-") -> #REF!
B57: 6007 | D57: សម្ភារបរិក្ខារថែទាំសុខភាព | E57: =SUM(E58:E60) -> 0 | F57: =SUM(F58:F60) -> 0 | G57: =SUM(G58:G60) -> 0 | H57: =SUM(H58:H60) -> 0 | I57: =SUM(I58:I60) -> 0 | J57: =SUM(J58:J60) -> 0 | K57: =SUM(K58:K60) -> 0 | L57: =IFERROR(K57/F57,"-") -> - | M57: =IFERROR(K57/H57,"-") -> - | N57: =SUM(N58:N60) -> #REF! | O57: =IFERROR(N57/F57,"-") -> - | P57: =IFERROR(N57/H57,"-") -> - | Q57: =SUM(Q58:Q60) -> #REF! | R57: =IFERROR(Q57/F57,"-") -> - | S57: =SUM(S58:S60) -> #REF! | U57: =IF(OR(F57>0,H57>0,N57>0),"ok","-") -> #REF!
C58: 60071 | D58: បំពង់ហ្គាសនិងអុកស៊ីសែន | K58: =SUM(I58:J58) -> 0 | L58: =IFERROR(K58/F58,"-") -> - | M58: =IFERROR(K58/H58,"-") -> - | N58: =#REF! -> #REF! | O58: =IFERROR(N58/F58,"-") -> - | P58: =IFERROR(N58/H58,"-") -> - | Q58: =N58-F58 -> #REF! | R58: =IFERROR(Q58/F58,"-") -> - | S58: =#REF! -> #REF! | U58: =IF(OR(F58>0,H58>0,N58>0),"ok","-") -> #REF!
C59: 60072 | D59: សម្ភារបរិក្ខារពេទ្យ | K59: =SUM(I59:J59) -> 0 | L59: =IFERROR(K59/F59,"-") -> - | M59: =IFERROR(K59/H59,"-") -> - | N59: =#REF! -> #REF! | O59: =IFERROR(N59/F59,"-") -> - | P59: =IFERROR(N59/H59,"-") -> - | Q59: =N59-F59 -> #REF! | R59: =IFERROR(Q59/F59,"-") -> - | S59: =#REF! -> #REF! | U59: =IF(OR(F59>0,H59>0,N59>0),"ok","-") -> #REF!
C60: 60078 | D60: សម្ភារបរិក្ខារថែទាំសុខភាពផ្សេងៗ | K60: =SUM(I60:J60) -> 0 | L60: =IFERROR(K60/F60,"-") -> - | M60: =IFERROR(K60/H60,"-") -> - | N60: =#REF! -> #REF! | O60: =IFERROR(N60/F60,"-") -> - | P60: =IFERROR(N60/H60,"-") -> - | Q60: =N60-F60 -> #REF! | R60: =IFERROR(Q60/F60,"-") -> - | S60: =#REF! -> #REF! | U60: =IF(OR(F60>0,H60>0,N60>0),"ok","-") -> #REF!
B61: 6098 | D61: សម្ភារផ្គត់ផ្គង់ផ្សេងៗ | E61: =E62 -> 0 | F61: =F62 -> 0 | G61: =G62 -> 0 | H61: =H62 -> 0 | I61: =I62 -> 0 | J61: =J62 -> 0 | K61: =K62 -> 0 | L61: =IFERROR(K61/F61,"-") -> - | M61: =IFERROR(K61/H61,"-") -> - | N61: =N62 -> #REF! | O61: =IFERROR(N61/F61,"-") -> - | P61: =IFERROR(N61/H61,"-") -> - | Q61: =Q62 -> #REF! | R61: =IFERROR(Q61/F61,"-") -> - | S61: =S62 -> #REF! | U61: =IF(OR(F61>0,H61>0,N61>0),"ok","-") -> #REF!
C62: 60981 | D62: សម្ភារផ្គត់ផ្គង់ផ្សេងៗ | K62: =SUM(I62:J62) -> 0 | L62: =IFERROR(K62/F62,"-") -> - | M62: =IFERROR(K62/H62,"-") -> - | N62: =#REF! -> #REF! | O62: =IFERROR(N62/F62,"-") -> - | P62: =IFERROR(N62/H62,"-") -> - | Q62: =N62-F62 -> #REF! | R62: =IFERROR(Q62/F62,"-") -> - | S62: =#REF! -> #REF! | U62: =IF(OR(F62>0,H62>0,N62>0),"ok","-") -> #REF!
A63: 61 | D63: សេវាកម្ម | E63: =E64+E68+E71+E75+E78+E87+E92+E98+E101+E107+E116+E121+E126+E131+E135+E137+E146 -> 150.377 | F63: =F64+F68+F71+F75+F78+F87+F92+F98+F101+F107+F116+F121+F126+F131+F135+F137+F146 -> 528.999 | G63: =G64+G68+G71+G75+G78+G87+G92+G98+G101+G107+G116+G121+G126+G131+G135+G137+G146 -> 0 | H63: =H64+H68+H71+H75+H78+H87+H92+H98+H101+H107+H116+H121+H126+H131+H135+H137+H146 -> 528.999 | I63: =I64+I68+I71+I75+I78+I87+I92+I98+I101+I107+I116+I121+I126+I131+I135+I137+I146 -> 166.59 | J63: =J64+J68+J71+J75+J78+J87+J92+J98+J101+J107+J116+J121+J126+J131+J135+J137+J146 -> 362.409 | K63: =K64+K68+K71+K75+K78+K87+K92+K98+K101+K107+K116+K121+K126+K131+K135+K137+K146 -> 528.999 | L63: =IFERROR(K63/F63,"-") -> 1 | M63: =IFERROR(K63/H63,"-") -> 1 | N63: =N64+N68+N71+N75+N78+N87+N92+N98+N101+N107+N116+N121+N126+N131+N135+N137+N146 -> #REF! | O63: =IFERROR(N63/F63,"-") -> - | P63: =IFERROR(N63/H63,"-") -> - | Q63: =Q64+Q68+Q71+Q75+Q78+Q87+Q92+Q98+Q101+Q107+Q116+Q121+Q126+Q131+Q135+Q137+Q146 -> #REF! | R63: =IFERROR(Q63/F63,"-") -> - | S63: =S64+S68+S71+S75+S78+S87+S92+S98+S101+S107+S116+S121+S126+S131+S135+S137+S146 -> #REF! | U63: =IF(OR(F63>0,H63>0,N63>0),"ok","-") -> #REF!
B64: 6101 | D64: កិច្ចសន្យានៃការផ្តល់សេវាជាមួយសហគ្រាស | E64: =SUM(E65:E67) -> 0 | F64: =SUM(F65:F67) -> 0 | G64: =SUM(G65:G67) -> 0 | H64: =SUM(H65:H67) -> 0 | I64: =SUM(I65:I67) -> 0 | J64: =SUM(J65:J67) -> 0 | K64: =SUM(K65:K67) -> 0 | L64: =IFERROR(K64/F64,"-") -> - | M64: =IFERROR(K64/H64,"-") -> - | N64: =SUM(N65:N67) -> #REF! | O64: =IFERROR(N64/F64,"-") -> - | P64: =IFERROR(N64/H64,"-") -> - | Q64: =SUM(Q65:Q67) -> #REF! | R64: =IFERROR(Q64/F64,"-") -> - | S64: =SUM(S65:S67) -> #REF! | U64: =IF(OR(F64>0,H64>0,N64>0),"ok","-") -> #REF!
C65: 61011 | D65: សេវាអនាម័យ | K65: =SUM(I65:J65) -> 0 | L65: =IFERROR(K65/F65,"-") -> - | M65: =IFERROR(K65/H65,"-") -> - | N65: =#REF! -> #REF! | O65: =IFERROR(N65/F65,"-") -> - | P65: =IFERROR(N65/H65,"-") -> - | Q65: =N65-F65 -> #REF! | R65: =IFERROR(Q65/F65,"-") -> - | S65: =#REF! -> #REF! | U65: =IF(OR(F65>0,H65>0,N65>0),"ok","-") -> #REF!
C66: 61012 | D66: សេវារដ្ឋបាល | K66: =SUM(I66:J66) -> 0 | L66: =IFERROR(K66/F66,"-") -> - | M66: =IFERROR(K66/H66,"-") -> - | N66: =#REF! -> #REF! | O66: =IFERROR(N66/F66,"-") -> - | P66: =IFERROR(N66/H66,"-") -> - | Q66: =N66-F66 -> #REF! | R66: =IFERROR(Q66/F66,"-") -> - | S66: =#REF! -> #REF! | U66: =IF(OR(F66>0,H66>0,N66>0),"ok","-") -> #REF!
C67: 61018 | D67: សេវាផ្សេងៗ | K67: =SUM(I67:J67) -> 0 | L67: =IFERROR(K67/F67,"-") -> - | M67: =IFERROR(K67/H67,"-") -> - | N67: =#REF! -> #REF! | O67: =IFERROR(N67/F67,"-") -> - | P67: =IFERROR(N67/H67,"-") -> - | Q67: =N67-F67 -> #REF! | R67: =IFERROR(Q67/F67,"-") -> - | S67: =#REF! -> #REF! | U67: =IF(OR(F67>0,H67>0,N67>0),"ok","-") -> #REF!
B68: 6102 | D68: ការជួលមធ្យោបាយដឹកជញ្ជូន | E68: =SUM(E69:E70) -> 0 | F68: =SUM(F69:F70) -> 4 | G68: =SUM(G69:G70) -> 0 | H68: =SUM(H69:H70) -> 4 | I68: =SUM(I69:I70) -> 0 | J68: =SUM(J69:J70) -> 4 | K68: =SUM(K69:K70) -> 4 | L68: =IFERROR(K68/F68,"-") -> 1 | M68: =IFERROR(K68/H68,"-") -> 1 | N68: =SUM(N69:N70) -> #REF! | O68: =IFERROR(N68/F68,"-") -> - | P68: =IFERROR(N68/H68,"-") -> - | Q68: =SUM(Q69:Q70) -> #REF! | R68: =IFERROR(Q68/F68,"-") -> - | S68: =SUM(S69:S70) -> #REF! | U68: =IF(OR(F68>0,H68>0,N68>0),"ok","-") -> #REF!
C69: 61021 | D69: ការជួលមធ្យោបាយដឹកជញ្ជូន | F69: 4 | H69: 4 | J69: =H69-I69 -> 4 | K69: =SUM(I69:J69) -> 4 | L69: =IFERROR(K69/F69,"-") -> 1 | M69: =IFERROR(K69/H69,"-") -> 1 | N69: =#REF! -> #REF! | O69: =IFERROR(N69/F69,"-") -> - | P69: =IFERROR(N69/H69,"-") -> - | Q69: =N69-F69 -> #REF! | R69: =IFERROR(Q69/F69,"-") -> - | S69: =#REF! -> #REF! | U69: =IF(OR(F69>0,H69>0,N69>0),"ok","-") -> #REF!
C70: 61028 | D70: ការជួលមធ្យោបាយដឹកជញ្ជូនផ្សេងៗ | K70: =SUM(I70:J70) -> 0 | L70: =IFERROR(K70/F70,"-") -> - | M70: =IFERROR(K70/H70,"-") -> - | N70: =#REF! -> #REF! | O70: =IFERROR(N70/F70,"-") -> - | P70: =IFERROR(N70/H70,"-") -> - | Q70: =N70-F70 -> #REF! | R70: =IFERROR(Q70/F70,"-") -> - | S70: =#REF! -> #REF! | U70: =IF(OR(F70>0,H70>0,N70>0),"ok","-") -> #REF!
B71: 6103 | D71: ថ្លៃឈ្នួល និងបន្ទុក (អសង្ហារឹម) ក្នុងនិងក្រៅប្រទេស | E71: =SUM(E72:E74) -> 0 | F71: =SUM(F72:F74) -> 0 | G71: =SUM(G72:G74) -> 0 | H71: =SUM(H72:H74) -> 0 | I71: =SUM(I72:I74) -> 0 | J71: =SUM(J72:J74) -> 0 | K71: =SUM(K72:K74) -> 0 | L71: =IFERROR(K71/F71,"-") -> - | M71: =IFERROR(K71/H71,"-") -> - | N71: =SUM(N72:N74) -> #REF! | O71: =IFERROR(N71/F71,"-") -> - | P71: =IFERROR(N71/H71,"-") -> - | Q71: =SUM(Q72:Q74) -> #REF! | R71: =IFERROR(Q71/F71,"-") -> - | S71: =SUM(S72:S74) -> #REF! | U71: =IF(OR(F71>0,H71>0,N71>0),"ok","-") -> #REF!
C72: 61031 | D72: ថ្លៃឈ្នួល និងបន្ទុក (អសង្ហារឹម) ក្នុងប្រទេស | K72: =SUM(I72:J72) -> 0 | L72: =IFERROR(K72/F72,"-") -> - | M72: =IFERROR(K72/H72,"-") -> - | N72: =#REF! -> #REF! | O72: =IFERROR(N72/F72,"-") -> - | P72: =IFERROR(N72/H72,"-") -> - | Q72: =N72-F72 -> #REF! | R72: =IFERROR(Q72/F72,"-") -> - | S72: =#REF! -> #REF! | U72: =IF(OR(F72>0,H72>0,N72>0),"ok","-") -> #REF!
C73: 61032 | D73: ថ្លៃឈ្នួល និងបន្ទុក (អសង្ហារឹម) ក្រៅប្រទេស | K73: =SUM(I73:J73) -> 0 | L73: =IFERROR(K73/F73,"-") -> - | M73: =IFERROR(K73/H73,"-") -> - | N73: =#REF! -> #REF! | O73: =IFERROR(N73/F73,"-") -> - | P73: =IFERROR(N73/H73,"-") -> - | Q73: =N73-F73 -> #REF! | R73: =IFERROR(Q73/F73,"-") -> - | S73: =#REF! -> #REF! | U73: =IF(OR(F73>0,H73>0,N73>0),"ok","-") -> #REF!
C74: 61038 | D74: ថ្លៃឈ្នួល និងបន្ទុក (អសង្ហារឹម) ផ្សេងៗ | K74: =SUM(I74:J74) -> 0 | L74: =IFERROR(K74/F74,"-") -> - | M74: =IFERROR(K74/H74,"-") -> - | N74: =#REF! -> #REF! | O74: =IFERROR(N74/F74,"-") -> - | P74: =IFERROR(N74/H74,"-") -> - | Q74: =N74-F74 -> #REF! | R74: =IFERROR(Q74/F74,"-") -> - | S74: =#REF! -> #REF! | U74: =IF(OR(F74>0,H74>0,N74>0),"ok","-") -> #REF!
B75: 6104 | D75: សោហ៊ុយបណ្តុះបណ្តាលក្នុងនិងក្រៅប្រទេស | E75: =SUM(E76:E77) -> 0 | F75: =SUM(F76:F77) -> 0 | G75: =SUM(G76:G77) -> 0 | H75: =SUM(H76:H77) -> 0 | I75: =SUM(I76:I77) -> 0 | J75: =SUM(J76:J77) -> 0 | K75: =SUM(K76:K77) -> 0 | L75: =IFERROR(K75/F75,"-") -> - | M75: =IFERROR(K75/H75,"-") -> - | N75: =SUM(N76:N77) -> #REF! | O75: =IFERROR(N75/F75,"-") -> - | P75: =IFERROR(N75/H75,"-") -> - | Q75: =SUM(Q76:Q77) -> #REF! | R75: =IFERROR(Q75/F75,"-") -> - | S75: =SUM(S76:S77) -> #REF! | U75: =IF(OR(F75>0,H75>0,N75>0),"ok","-") -> #REF!
C76: 61041 | D76: សោហ៊ុយបណ្តុះបណ្តាលក្នុងនិងក្រៅប្រទេស | K76: =SUM(I76:J76) -> 0 | L76: =IFERROR(K76/F76,"-") -> - | M76: =IFERROR(K76/H76,"-") -> - | N76: =#REF! -> #REF! | O76: =IFERROR(N76/F76,"-") -> - | P76: =IFERROR(N76/H76,"-") -> - | Q76: =N76-F76 -> #REF! | R76: =IFERROR(Q76/F76,"-") -> - | S76: =#REF! -> #REF! | U76: =IF(OR(F76>0,H76>0,N76>0),"ok","-") -> #REF!
C77: 61048 | D77: សោហ៊ុយបណ្តុះបណ្តាលផ្សេងៗក្នុងនិងក្រៅប្រទេស | K77: =SUM(I77:J77) -> 0 | L77: =IFERROR(K77/F77,"-") -> - | M77: =IFERROR(K77/H77,"-") -> - | N77: =#REF! -> #REF! | O77: =IFERROR(N77/F77,"-") -> - | P77: =IFERROR(N77/H77,"-") -> - | Q77: =N77-F77 -> #REF! | R77: =IFERROR(Q77/F77,"-") -> - | S77: =#REF! -> #REF! | U77: =IF(OR(F77>0,H77>0,N77>0),"ok","-") -> #REF!
B78: 6105 | D78: ការថែទាំនិងជួសជុល | E78: =SUM(E79:E86) -> 99.819 | F78: =SUM(F79:F86) -> 133.2 | G78: =SUM(G79:G86) -> 0 | H78: =SUM(H79:H86) -> 133.2 | I78: =SUM(I79:I86) -> 111.04 | J78: =SUM(J79:J86) -> 22.16 | K78: =SUM(K79:K86) -> 133.2 | L78: =IFERROR(K78/F78,"-") -> 1 | M78: =IFERROR(K78/H78,"-") -> 1 | N78: =SUM(N79:N86) -> #REF! | O78: =IFERROR(N78/F78,"-") -> - | P78: =IFERROR(N78/H78,"-") -> - | Q78: =SUM(Q79:Q86) -> #REF! | R78: =IFERROR(Q78/F78,"-") -> - | S78: =SUM(S79:S86) -> #REF! | U78: =IF(OR(F78>0,H78>0,N78>0),"ok","-") -> #REF!
C79: 61051 | D79: ការថែទាំដីធ្លី សួនច្បារ ព្រៃឈើ តំបន់ឆ្នេរ និងដែននេសាទ | K79: =SUM(I79:J79) -> 0 | L79: =IFERROR(K79/F79,"-") -> - | M79: =IFERROR(K79/H79,"-") -> - | N79: =#REF! -> #REF! | O79: =IFERROR(N79/F79,"-") -> - | P79: =IFERROR(N79/H79,"-") -> - | Q79: =N79-F79 -> #REF! | R79: =IFERROR(Q79/F79,"-") -> - | S79: =#REF! -> #REF! | U79: =IF(OR(F79>0,H79>0,N79>0),"ok","-") -> #REF!
C80: 61052 | D80: ការថែទាំ ជួសជុលអាគារផ្សេងៗ និងប្រាសាទ | K80: =SUM(I80:J80) -> 0 | L80: =IFERROR(K80/F80,"-") -> - | M80: =IFERROR(K80/H80,"-") -> - | N80: =#REF! -> #REF! | O80: =IFERROR(N80/F80,"-") -> - | P80: =IFERROR(N80/H80,"-") -> - | Q80: =N80-F80 -> #REF! | R80: =IFERROR(Q80/F80,"-") -> - | S80: =#REF! -> #REF! | U80: =IF(OR(F80>0,H80>0,N80>0),"ok","-") -> #REF!
C81: 61053 | D81: ការថែទាំនិងជួសជុល ផ្លូវ ផ្លូវលំ ស្ពាន ​និងលូ | K81: =SUM(I81:J81) -> 0 | L81: =IFERROR(K81/F81,"-") -> - | M81: =IFERROR(K81/H81,"-") -> - | N81: =#REF! -> #REF! | O81: =IFERROR(N81/F81,"-") -> - | P81: =IFERROR(N81/H81,"-") -> - | Q81: =N81-F81 -> #REF! | R81: =IFERROR(Q81/F81,"-") -> - | S81: =#REF! -> #REF! | U81: =IF(OR(F81>0,H81>0,N81>0),"ok","-") -> #REF!
C82: 61054 | D82: ការថែទាំបណ្តាញផ្សេងៗ | K82: =SUM(I82:J82) -> 0 | L82: =IFERROR(K82/F82,"-") -> - | M82: =IFERROR(K82/H82,"-") -> - | N82: =#REF! -> #REF! | O82: =IFERROR(N82/F82,"-") -> - | P82: =IFERROR(N82/H82,"-") -> - | Q82: =N82-F82 -> #REF! | R82: =IFERROR(Q82/F82,"-") -> - | S82: =#REF! -> #REF! | U82: =IF(OR(F82>0,H82>0,N82>0),"ok","-") -> #REF!
C83: 61055 | D83: ការថែទាំប្រព័ន្ធធារាសាស្រ្ត | K83: =SUM(I83:J83) -> 0 | L83: =IFERROR(K83/F83,"-") -> - | M83: =IFERROR(K83/H83,"-") -> - | N83: =#REF! -> #REF! | O83: =IFERROR(N83/F83,"-") -> - | P83: =IFERROR(N83/H83,"-") -> - | Q83: =N83-F83 -> #REF! | R83: =IFERROR(Q83/F83,"-") -> - | S83: =#REF! -> #REF! | U83: =IF(OR(F83>0,H83>0,N83>0),"ok","-") -> #REF!
C84: 61056 | D84: ការថែទាំនិងជួសជុលមធ្យោបាយដឹកជញ្ជូន | E84: 58.001 | F84: 76.7 | H84: 76.7 | I84: 65.09 | J84: =H84-I84 -> 11.61 | K84: =SUM(I84:J84) -> 76.7 | L84: =IFERROR(K84/F84,"-") -> 1 | M84: =IFERROR(K84/H84,"-") -> 1 | N84: =#REF! -> #REF! | O84: =IFERROR(N84/F84,"-") -> - | P84: =IFERROR(N84/H84,"-") -> - | Q84: =N84-F84 -> #REF! | R84: =IFERROR(Q84/F84,"-") -> - | S84: =#REF! -> #REF! | T84: កើនដោយសារមានការគ្រោងសម្រាប់ការជួសជុលរថយន្តសម្រាប់ថ្នាក់កនាំនាយកដ្ឋានថ្មី២ | U84: =IF(OR(F84>0,H84>0,N84>0),"ok","-") -> #REF!
C85: 61057 | D85: ការថែទាំនិងជួសជុលសម្ភារនិងឧបករណ៍បច្ចេកទេស | E85: 41.818 | F85: 56.5 | H85: 56.5 | I85: 45.95 | J85: =H85-I85 -> 10.55 | K85: =SUM(I85:J85) -> 56.5 | L85: =IFERROR(K85/F85,"-") -> 1 | M85: =IFERROR(K85/H85,"-") -> 1 | N85: =#REF! -> #REF! | O85: =IFERROR(N85/F85,"-") -> - | P85: =IFERROR(N85/H85,"-") -> - | Q85: =N85-F85 -> #REF! | R85: =IFERROR(Q85/F85,"-") -> - | S85: =#REF! -> #REF! | T85: កើនដោយសារមានការគ្រោងសម្រាប់ការជួសជុលម៉ាស៊ីនព្រីនធ័រចាស់ដែលមានស្រាប់ និងសម្រាប់នាយកដ្ឋានថ្មី២ | U85: =IF(OR(F85>0,H85>0,N85>0),"ok","-") -> #REF!
C86: 61058 | D86: ការថែទាំនិងជួសជុលផ្សេងៗ | J86: =H86-I86 -> 0 | K86: =SUM(I86:J86) -> 0 | L86: =IFERROR(K86/F86,"-") -> - | M86: =IFERROR(K86/H86,"-") -> - | N86: =#REF! -> #REF! | O86: =IFERROR(N86/F86,"-") -> - | P86: =IFERROR(N86/H86,"-") -> - | Q86: =N86-F86 -> #REF! | R86: =IFERROR(Q86/F86,"-") -> - | S86: =#REF! -> #REF! | U86: =IF(OR(F86>0,H86>0,N86>0),"ok","-") -> #REF!
B87: 6106 | D87: សោហ៊ុយធានារ៉ាប់រង | E87: =SUM(E88:E91) -> 0 | F87: =SUM(F88:F91) -> 0 | G87: =SUM(G88:G91) -> 0 | H87: =SUM(H88:H91) -> 0 | I87: =SUM(I88:I91) -> 0 | J87: =H87-I87 -> 0 | K87: =SUM(K88:K91) -> 0 | L87: =IFERROR(K87/F87,"-") -> - | M87: =IFERROR(K87/H87,"-") -> - | N87: =SUM(N88:N91) -> #REF! | O87: =IFERROR(N87/F87,"-") -> - | P87: =IFERROR(N87/H87,"-") -> - | Q87: =SUM(Q88:Q91) -> #REF! | R87: =IFERROR(Q87/F87,"-") -> - | S87: =SUM(S88:S91) -> #REF! | U87: =IF(OR(F87>0,H87>0,N87>0),"ok","-") -> #REF!
C88: 61061 | D88: សោហ៊ុយធានារ៉ាប់រងលើអគារ | J88: =H88-I88 -> 0 | K88: =SUM(I88:J88) -> 0 | L88: =IFERROR(K88/F88,"-") -> - | M88: =IFERROR(K88/H88,"-") -> - | N88: =#REF! -> #REF! | O88: =IFERROR(N88/F88,"-") -> - | P88: =IFERROR(N88/H88,"-") -> - | Q88: =N88-F88 -> #REF! | R88: =IFERROR(Q88/F88,"-") -> - | S88: =#REF! -> #REF! | U88: =IF(OR(F88>0,H88>0,N88>0),"ok","-") -> #REF!
C89: 61062 | D89: សោហ៊ុយធានារ៉ាប់រងលើយានយន្ត | J89: =H89-I89 -> 0 | K89: =SUM(I89:J89) -> 0 | L89: =IFERROR(K89/F89,"-") -> - | M89: =IFERROR(K89/H89,"-") -> - | N89: =#REF! -> #REF! | O89: =IFERROR(N89/F89,"-") -> - | P89: =IFERROR(N89/H89,"-") -> - | Q89: =N89-F89 -> #REF! | R89: =IFERROR(Q89/F89,"-") -> - | S89: =#REF! -> #REF! | U89: =IF(OR(F89>0,H89>0,N89>0),"ok","-") -> #REF!
C90: 61063 | D90: សោហ៊ុយធានារ៉ាប់រងលើសុខភាព | J90: =H90-I90 -> 0 | K90: =SUM(I90:J90) -> 0 | L90: =IFERROR(K90/F90,"-") -> - | M90: =IFERROR(K90/H90,"-") -> - | N90: =#REF! -> #REF! | O90: =IFERROR(N90/F90,"-") -> - | P90: =IFERROR(N90/H90,"-") -> - | Q90: =N90-F90 -> #REF! | R90: =IFERROR(Q90/F90,"-") -> - | S90: =#REF! -> #REF! | U90: =IF(OR(F90>0,H90>0,N90>0),"ok","-") -> #REF!
C91: 61068 | D91: សោហ៊ុយធានារ៉ាប់រងផ្សេងៗទៀត | J91: =H91-I91 -> 0 | K91: =SUM(I91:J91) -> 0 | L91: =IFERROR(K91/F91,"-") -> - | M91: =IFERROR(K91/H91,"-") -> - | N91: =#REF! -> #REF! | O91: =IFERROR(N91/F91,"-") -> - | P91: =IFERROR(N91/H91,"-") -> - | Q91: =N91-F91 -> #REF! | R91: =IFERROR(Q91/F91,"-") -> - | S91: =#REF! -> #REF! | U91: =IF(OR(F91>0,H91>0,N91>0),"ok","-") -> #REF!
B92: 6107 | D92: សោហ៊ុយសិក្សាពិសោធន៍ សោហ៊ុយនៃការប្រើប្រាស់សេវា សោហ៊ុយនៃការប្រើប្រាស់សិទ្ធិ និងសំណងផ្សេងៗ | E92: =SUM(E93:E97) -> 0 | F92: =SUM(F93:F97) -> 0 | G92: =SUM(G93:G97) -> 0 | H92: =SUM(H93:H97) -> 0 | I92: =SUM(I93:I97) -> 0 | J92: =H92-I92 -> 0 | K92: =SUM(K93:K97) -> 0 | L92: =IFERROR(K92/F92,"-") -> - | M92: =IFERROR(K92/H92,"-") -> - | N92: =SUM(N93:N97) -> #REF! | O92: =IFERROR(N92/F92,"-") -> - | P92: =IFERROR(N92/H92,"-") -> - | Q92: =SUM(Q93:Q97) -> #REF! | R92: =IFERROR(Q92/F92,"-") -> - | S92: =SUM(S93:S97) -> #REF! | U92: =IF(OR(F92>0,H92>0,N92>0),"ok","-") -> #REF!
C93: 61071 | D93: សោហ៊ុយសិក្សាពិសោធន៍ | J93: =H93-I93 -> 0 | K93: =SUM(I93:J93) -> 0 | L93: =IFERROR(K93/F93,"-") -> - | M93: =IFERROR(K93/H93,"-") -> - | N93: =#REF! -> #REF! | O93: =IFERROR(N93/F93,"-") -> - | P93: =IFERROR(N93/H93,"-") -> - | Q93: =N93-F93 -> #REF! | R93: =IFERROR(Q93/F93,"-") -> - | S93: =#REF! -> #REF! | U93: =IF(OR(F93>0,H93>0,N93>0),"ok","-") -> #REF!
C94: 61072 | D94: សោហ៊ុយនៃការប្រើប្រាស់សេវា | J94: =H94-I94 -> 0 | K94: =SUM(I94:J94) -> 0 | L94: =IFERROR(K94/F94,"-") -> - | M94: =IFERROR(K94/H94,"-") -> - | N94: =#REF! -> #REF! | O94: =IFERROR(N94/F94,"-") -> - | P94: =IFERROR(N94/H94,"-") -> - | Q94: =N94-F94 -> #REF! | R94: =IFERROR(Q94/F94,"-") -> - | S94: =#REF! -> #REF! | U94: =IF(OR(F94>0,H94>0,N94>0),"ok","-") -> #REF!
C95: 61073 | D95: សោហ៊ុយនៃការប្រើប្រាស់សិទ្ធិ | J95: =H95-I95 -> 0 | K95: =SUM(I95:J95) -> 0 | L95: =IFERROR(K95/F95,"-") -> - | M95: =IFERROR(K95/H95,"-") -> - | N95: =#REF! -> #REF! | O95: =IFERROR(N95/F95,"-") -> - | P95: =IFERROR(N95/H95,"-") -> - | Q95: =N95-F95 -> #REF! | R95: =IFERROR(Q95/F95,"-") -> - | S95: =#REF! -> #REF! | U95: =IF(OR(F95>0,H95>0,N95>0),"ok","-") -> #REF!
C96: 61074 | D96: សំណងផ្នែកស៊ីវិល | J96: =H96-I96 -> 0 | K96: =SUM(I96:J96) -> 0 | L96: =IFERROR(K96/F96,"-") -> - | M96: =IFERROR(K96/H96,"-") -> - | N96: =#REF! -> #REF! | O96: =IFERROR(N96/F96,"-") -> - | P96: =IFERROR(N96/H96,"-") -> - | Q96: =N96-F96 -> #REF! | R96: =IFERROR(Q96/F96,"-") -> - | S96: =#REF! -> #REF! | U96: =IF(OR(F96>0,H96>0,N96>0),"ok","-") -> #REF!
C97: 61078 | D97: សោហ៊ុយ និងសំណងផ្សេងៗ | J97: =H97-I97 -> 0 | K97: =SUM(I97:J97) -> 0 | L97: =IFERROR(K97/F97,"-") -> - | M97: =IFERROR(K97/H97,"-") -> - | N97: =#REF! -> #REF! | O97: =IFERROR(N97/F97,"-") -> - | P97: =IFERROR(N97/H97,"-") -> - | Q97: =N97-F97 -> #REF! | R97: =IFERROR(Q97/F97,"-") -> - | S97: =#REF! -> #REF! | U97: =IF(OR(F97>0,H97>0,N97>0),"ok","-") -> #REF!
B98: 6108 | D98: សោហ៊ុយដឹកជញ្ជូន | E98: =SUM(E99:E100) -> 0 | F98: =SUM(F99:F100) -> 0 | G98: =SUM(G99:G100) -> 0 | H98: =SUM(H99:H100) -> 0 | I98: =SUM(I99:I100) -> 0 | J98: =H98-I98 -> 0 | K98: =SUM(K99:K100) -> 0 | L98: =IFERROR(K98/F98,"-") -> - | M98: =IFERROR(K98/H98,"-") -> - | N98: =SUM(N99:N100) -> #REF! | O98: =IFERROR(N98/F98,"-") -> - | P98: =IFERROR(N98/H98,"-") -> - | Q98: =SUM(Q99:Q100) -> #REF! | R98: =IFERROR(Q98/F98,"-") -> - | S98: =SUM(S99:S100) -> #REF! | U98: =IF(OR(F98>0,H98>0,N98>0),"ok","-") -> #REF!
C99: 61081 | D99: សម្ភារ​និងទំនិញ | J99: =H99-I99 -> 0 | K99: =SUM(I99:J99) -> 0 | L99: =IFERROR(K99/F99,"-") -> - | M99: =IFERROR(K99/H99,"-") -> - | N99: =#REF! -> #REF! | O99: =IFERROR(N99/F99,"-") -> - | P99: =IFERROR(N99/H99,"-") -> - | Q99: =N99-F99 -> #REF! | R99: =IFERROR(Q99/F99,"-") -> - | S99: =#REF! -> #REF! | U99: =IF(OR(F99>0,H99>0,N99>0),"ok","-") -> #REF!
C100: 61088 | D100: សោហ៊ុយដឹកជញ្ជូនផ្សេងៗ | J100: =H100-I100 -> 0 | K100: =SUM(I100:J100) -> 0 | L100: =IFERROR(K100/F100,"-") -> - | M100: =IFERROR(K100/H100,"-") -> - | N100: =#REF! -> #REF! | O100: =IFERROR(N100/F100,"-") -> - | P100: =IFERROR(N100/H100,"-") -> - | Q100: =N100-F100 -> #REF! | R100: =IFERROR(Q100/F100,"-") -> - | S100: =#REF! -> #REF! | U100: =IF(OR(F100>0,H100>0,N100>0),"ok","-") -> #REF!
B101: 6109 | D101: បុគ្គលិកខាងក្រៅ | E101: =SUM(E102:E106) -> 0 | F101: =SUM(F102:F106) -> 0 | G101: =SUM(G102:G106) -> 0 | H101: =SUM(H102:H106) -> 0 | I101: =SUM(I102:I106) -> 0 | J101: =H101-I101 -> 0 | K101: =SUM(K102:K106) -> 0 | L101: =IFERROR(K101/F101,"-") -> - | M101: =IFERROR(K101/H101,"-") -> - | N101: =SUM(N102:N106) -> #REF! | O101: =IFERROR(N101/F101,"-") -> - | P101: =IFERROR(N101/H101,"-") -> - | Q101: =SUM(Q102:Q106) -> #REF! | R101: =IFERROR(Q101/F101,"-") -> - | S101: =SUM(S102:S106) -> #REF! | U101: =IF(OR(F101>0,H101>0,N101>0),"ok","-") -> #REF!
C102: 61091 | D102: ភ្នាក់ងារជាតិជាប់កិច្ចសន្យា | J102: =H102-I102 -> 0 | K102: =SUM(I102:J102) -> 0 | L102: =IFERROR(K102/F102,"-") -> - | M102: =IFERROR(K102/H102,"-") -> - | N102: =#REF! -> #REF! | O102: =IFERROR(N102/F102,"-") -> - | P102: =IFERROR(N102/H102,"-") -> - | Q102: =N102-F102 -> #REF! | R102: =IFERROR(Q102/F102,"-") -> - | S102: =#REF! -> #REF! | U102: =IF(OR(F102>0,H102>0,N102>0),"ok","-") -> #REF!
C103: 61092 | D103: ភ្នាក់ងារបរទេសជាប់កិច្ចសន្យា | J103: =H103-I103 -> 0 | K103: =SUM(I103:J103) -> 0 | L103: =IFERROR(K103/F103,"-") -> - | M103: =IFERROR(K103/H103,"-") -> - | N103: =#REF! -> #REF! | O103: =IFERROR(N103/F103,"-") -> - | P103: =IFERROR(N103/H103,"-") -> - | Q103: =N103-F103 -> #REF! | R103: =IFERROR(Q103/F103,"-") -> - | S103: =#REF! -> #REF! | U103: =IF(OR(F103>0,H103>0,N103>0),"ok","-") -> #REF!
C104: 61093 | D104: បុគ្គលិកសមូហភាពសាធារណៈផ្សេងៗ | J104: =H104-I104 -> 0 | K104: =SUM(I104:J104) -> 0 | L104: =IFERROR(K104/F104,"-") -> - | M104: =IFERROR(K104/H104,"-") -> - | N104: =#REF! -> #REF! | O104: =IFERROR(N104/F104,"-") -> - | P104: =IFERROR(N104/H104,"-") -> - | Q104: =N104-F104 -> #REF! | R104: =IFERROR(Q104/F104,"-") -> - | S104: =#REF! -> #REF! | U104: =IF(OR(F104>0,H104>0,N104>0),"ok","-") -> #REF!
C105: 61094 | D105: ប្រាក់វិភាជន៍សង្គមសម្រាប់បុគ្គលិកខាងក្រៅ | J105: =H105-I105 -> 0 | K105: =SUM(I105:J105) -> 0 | L105: =IFERROR(K105/F105,"-") -> - | M105: =IFERROR(K105/H105,"-") -> - | N105: =#REF! -> #REF! | O105: =IFERROR(N105/F105,"-") -> - | P105: =IFERROR(N105/H105,"-") -> - | Q105: =N105-F105 -> #REF! | R105: =IFERROR(Q105/F105,"-") -> - | S105: =#REF! -> #REF! | U105: =IF(OR(F105>0,H105>0,N105>0),"ok","-") -> #REF!
...

Sheet Prog
C5: គម្រោងថវិកាឆ្នាំ២០២៣
C6: គោលបំណង និងការទទួលខុសត្រូវលើអនុកម្មវិធី
C7: =Costing!$K$11 -> អគ្គនាយកដ្ឋានគោលនយោបាយ
E8: តារាងទី៥ (តារាង ៥"ក" ក្នុងសារាចររៀបចំគម្រោងថវិកាប្រចាំឆ្នាំ)
E9: ឯកតា៖ លានរៀល
A12: Check | B12: កូដកម្មវិធី | C12: បរិយាយកម្មវិធី និងអនុកម្មវិធី | D12: អង្គភាពទទួលខុសត្រូវ | E12: ការពណ៌នាគោលបំណង (អនុកម្មវិធី) (អាចដកស្រង់ចេញពីផែនការយុទ្ធសាស្ត្រថវិកា២០២២-២០២៤)
B13: =A14 -> 101 | C13: =#REF! -> #REF! | F13: =IF(AND(C13<>"",D13<>""),"ok","-") -> #REF!
A14: =LEFT(B14,3) -> 101 | B14: =Costing!$G$11 -> 10101 | C14: =IF(#REF!<>"",#REF!,"") -> #REF! | D14: =IF(#REF!<>"",#REF!,"") -> #REF! | F14: =IF(AND(C14<>"",D14<>""),"ok","-") -> #REF!
A15: =LEFT(B15,5) -> 10101 | B15: =$B$14&"01" -> 1010101 | C15: =IF(#REF!<>"",#REF!,"") -> #REF! | D15: =IF(#REF!<>"",#REF!,"") -> #REF! | F15: =IF(AND(C15<>"",D15<>""),"ok","-") -> #REF!
A16: =LEFT(B16,7) -> 1010101 | B16: =B15&"01" -> 101010101 | C16: =IF(#REF!<>"",#REF!,"") -> #REF! | D16: =IF(#REF!<>"",#REF!,"") -> #REF! | F16: =IF(AND(C16<>"",D16<>""),"ok","-") -> #REF!
A17: =LEFT(B17,7) -> 1010101 | B17: =B15&"02" -> 101010102 | C17: =IF(#REF!<>"",#REF!,"") -> #REF! | D17: =IF(#REF!<>"",#REF!,"") -> #REF! | F17: =IF(AND(C17<>"",D17<>""),"ok","-") -> #REF!
A18: =LEFT(B18,7) -> 1010101 | B18: =B15&"03" -> 101010103 | C18: =IF(#REF!<>"",#REF!,"") -> #REF! | D18: =IF(#REF!<>"",#REF!,"") -> #REF! | F18: =IF(AND(C18<>"",D18<>""),"ok","-") -> #REF!
A19: =LEFT(B19,7) -> 1010101 | B19: =B15&"04" -> 101010104 | C19: =IF(#REF!<>"",#REF!,"") -> #REF! | D19: =IF(#REF!<>"",#REF!,"") -> #REF! | F19: =IF(AND(C19<>"",D19<>""),"ok","-") -> #REF!
A20: =LEFT(B20,7) -> 1010101 | B20: =B15&"05" -> 101010105 | C20: =IF(#REF!<>"",#REF!,"") -> #REF! | D20: =IF(#REF!<>"",#REF!,"") -> #REF! | F20: =IF(AND(C20<>"",D20<>""),"ok","-") -> #REF!
A21: =LEFT(B21,7) -> 1010101 | B21: =B15&"06" -> 101010106 | C21: =IF(#REF!<>"",#REF!,"") -> #REF! | D21: =IF(#REF!<>"",#REF!,"") -> #REF! | F21: =IF(AND(C21<>"",D21<>""),"ok","-") -> #REF!
A22: =LEFT(B22,7) -> 1010101 | B22: =B15&"07" -> 101010107 | C22: =IF(#REF!<>"",#REF!,"") -> #REF! | D22: =IF(#REF!<>"",#REF!,"") -> #REF! | F22: =IF(AND(C22<>"",D22<>""),"ok","-") -> #REF!
A23: =LEFT(B23,7) -> 1010101 | B23: =B15&"08" -> 101010108 | C23: =IF(#REF!<>"",#REF!,"") -> #REF! | D23: =IF(#REF!<>"",#REF!,"") -> #REF! | F23: =IF(AND(C23<>"",D23<>""),"ok","-") -> #REF!
A24: =LEFT(B24,7) -> 1010101 | B24: =B15&"09" -> 101010109 | C24: =IF(#REF!<>"",#REF!,"") -> #REF! | D24: =IF(#REF!<>"",#REF!,"") -> #REF! | F24: =IF(AND(C24<>"",D24<>""),"ok","-") -> #REF!
A25: =LEFT(B25,7) -> 1010101 | B25: =B15&"10" -> 101010110 | C25: =IF(#REF!<>"",#REF!,"") -> #REF! | D25: =IF(#REF!<>"",#REF!,"") -> #REF! | F25: =IF(AND(C25<>"",D25<>""),"ok","-") -> #REF!
A26: =LEFT(B26,7) -> 1010101 | B26: =B15&"11" -> 101010111 | C26: =IF(#REF!<>"",#REF!,"") -> #REF! | D26: =IF(#REF!<>"",#REF!,"") -> #REF! | F26: =IF(AND(C26<>"",D26<>""),"ok","-") -> #REF!
A27: =LEFT(B27,7) -> 1010101 | B27: =B15&"12" -> 101010112 | C27: =IF(#REF!<>"",#REF!,"") -> #REF! | D27: =IF(#REF!<>"",#REF!,"") -> #REF! | F27: =IF(AND(C27<>"",D27<>""),"ok","-") -> #REF!
A28: =LEFT(B28,5) -> 10101 | B28: =$B$14&"02" -> 1010102 | C28: =IF(#REF!<>"",#REF!,"") -> #REF! | D28: =IF(#REF!<>"",#REF!,"") -> #REF! | F28: =IF(AND(C28<>"",D28<>""),"ok","-") -> #REF!
A29: =LEFT(B29,7) -> 1010102 | B29: =B28&"01" -> 101010201 | C29: =IF(#REF!<>"",#REF!,"") -> #REF! | D29: =IF(#REF!<>"",#REF!,"") -> #REF! | F29: =IF(AND(C29<>"",D29<>""),"ok","-") -> #REF!
A30: =LEFT(B30,7) -> 1010102 | B30: =B28&"02" -> 101010202 | C30: =IF(#REF!<>"",#REF!,"") -> #REF! | D30: =IF(#REF!<>"",#REF!,"") -> #REF! | F30: =IF(AND(C30<>"",D30<>""),"ok","-") -> #REF!
A31: =LEFT(B31,7) -> 1010102 | B31: =B28&"03" -> 101010203 | C31: =IF(#REF!<>"",#REF!,"") -> #REF! | D31: =IF(#REF!<>"",#REF!,"") -> #REF! | F31: =IF(AND(C31<>"",D31<>""),"ok","-") -> #REF!
A32: =LEFT(B32,7) -> 1010102 | B32: =B28&"04" -> 101010204 | C32: =IF(#REF!<>"",#REF!,"") -> #REF! | D32: =IF(#REF!<>"",#REF!,"") -> #REF! | F32: =IF(AND(C32<>"",D32<>""),"ok","-") -> #REF!
A33: =LEFT(B33,7) -> 1010102 | B33: =B28&"05" -> 101010205 | C33: =IF(#REF!<>"",#REF!,"") -> #REF! | D33: =IF(#REF!<>"",#REF!,"") -> #REF! | F33: =IF(AND(C33<>"",D33<>""),"ok","-") -> #REF!
A34: =LEFT(B34,7) -> 1010102 | B34: =B28&"06" -> 101010206 | C34: =IF(#REF!<>"",#REF!,"") -> #REF! | D34: =IF(#REF!<>"",#REF!,"") -> #REF! | F34: =IF(AND(C34<>"",D34<>""),"ok","-") -> #REF!
A35: =LEFT(B35,7) -> 1010102 | B35: =B28&"07" -> 101010207 | C35: =IF(#REF!<>"",#REF!,"") -> #REF! | D35: =IF(#REF!<>"",#REF!,"") -> #REF! | F35: =IF(AND(C35<>"",D35<>""),"ok","-") -> #REF!
A36: =LEFT(B36,7) -> 1010102 | B36: =B28&"08" -> 101010208 | C36: =IF(#REF!<>"",#REF!,"") -> #REF! | D36: =IF(#REF!<>"",#REF!,"") -> #REF! | F36: =IF(AND(C36<>"",D36<>""),"ok","-") -> #REF!
A37: =LEFT(B37,7) -> 1010102 | B37: =B28&"09" -> 101010209 | C37: =IF(#REF!<>"",#REF!,"") -> #REF! | D37: =IF(#REF!<>"",#REF!,"") -> #REF! | F37: =IF(AND(C37<>"",D37<>""),"ok","-") -> #REF!
A38: =LEFT(B38,7) -> 1010102 | B38: =B28&"10" -> 101010210 | C38: =IF(#REF!<>"",#REF!,"") -> #REF! | D38: =IF(#REF!<>"",#REF!,"") -> #REF! | F38: =IF(AND(C38<>"",D38<>""),"ok","-") -> #REF!
A39: =LEFT(B39,7) -> 1010102 | B39: =B28&"11" -> 101010211 | C39: =IF(#REF!<>"",#REF!,"") -> #REF! | D39: =IF(#REF!<>"",#REF!,"") -> #REF! | F39: =IF(AND(C39<>"",D39<>""),"ok","-") -> #REF!
A40: =LEFT(B40,7) -> 1010102 | B40: =B28&"12" -> 101010212 | C40: =IF(#REF!<>"",#REF!,"") -> #REF! | D40: =IF(#REF!<>"",#REF!,"") -> #REF! | F40: =IF(AND(C40<>"",D40<>""),"ok","-") -> #REF!
A41: =LEFT(B41,5) -> 10101 | B41: =$B$14&"03" -> 1010103 | C41: =IF(#REF!<>"",#REF!,"") -> #REF! | D41: =IF(#REF!<>"",#REF!,"") -> #REF! | F41: =IF(AND(C41<>"",D41<>""),"ok","-") -> #REF!
A42: =LEFT(B42,7) -> 1010103 | B42: =B41&"01" -> 101010301 | C42: =IF(#REF!<>"",#REF!,"") -> #REF! | D42: =IF(#REF!<>"",#REF!,"") -> #REF! | F42: =IF(AND(C42<>"",D42<>""),"ok","-") -> #REF!
A43: =LEFT(B43,7) -> 1010103 | B43: =B41&"02" -> 101010302 | C43: =IF(#REF!<>"",#REF!,"") -> #REF! | D43: =IF(#REF!<>"",#REF!,"") -> #REF! | F43: =IF(AND(C43<>"",D43<>""),"ok","-") -> #REF!
A44: =LEFT(B44,7) -> 1010103 | B44: =B41&"03" -> 101010303 | C44: =IF(#REF!<>"",#REF!,"") -> #REF! | D44: =IF(#REF!<>"",#REF!,"") -> #REF! | F44: =IF(AND(C44<>"",D44<>""),"ok","-") -> #REF!
A45: =LEFT(B45,7) -> 1010103 | B45: =B41&"04" -> 101010304 | C45: =IF(#REF!<>"",#REF!,"") -> #REF! | D45: =IF(#REF!<>"",#REF!,"") -> #REF! | F45: =IF(AND(C45<>"",D45<>""),"ok","-") -> #REF!
A46: =LEFT(B46,7) -> 1010103 | B46: =B41&"05" -> 101010305 | C46: =IF(#REF!<>"",#REF!,"") -> #REF! | D46: =IF(#REF!<>"",#REF!,"") -> #REF! | F46: =IF(AND(C46<>"",D46<>""),"ok","-") -> #REF!
A47: =LEFT(B47,7) -> 1010103 | B47: =B41&"06" -> 101010306 | C47: =IF(#REF!<>"",#REF!,"") -> #REF! | D47: =IF(#REF!<>"",#REF!,"") -> #REF! | F47: =IF(AND(C47<>"",D47<>""),"ok","-") -> #REF!
A48: =LEFT(B48,7) -> 1010103 | B48: =B41&"07" -> 101010307 | C48: =IF(#REF!<>"",#REF!,"") -> #REF! | D48: =IF(#REF!<>"",#REF!,"") -> #REF! | F48: =IF(AND(C48<>"",D48<>""),"ok","-") -> #REF!
A49: =LEFT(B49,7) -> 1010103 | B49: =B41&"08" -> 101010308 | C49: =IF(#REF!<>"",#REF!,"") -> #REF! | D49: =IF(#REF!<>"",#REF!,"") -> #REF! | F49: =IF(AND(C49<>"",D49<>""),"ok","-") -> #REF!
A50: =LEFT(B50,7) -> 1010103 | B50: =B41&"09" -> 101010309 | C50: =IF(#REF!<>"",#REF!,"") -> #REF! | D50: =IF(#REF!<>"",#REF!,"") -> #REF! | F50: =IF(AND(C50<>"",D50<>""),"ok","-") -> #REF!
A51: =LEFT(B51,7) -> 1010103 | B51: =B41&"10" -> 101010310 | C51: =IF(#REF!<>"",#REF!,"") -> #REF! | D51: =IF(#REF!<>"",#REF!,"") -> #REF! | F51: =IF(AND(C51<>"",D51<>""),"ok","-") -> #REF!
A52: =LEFT(B52,7) -> 1010103 | B52: =B41&"11" -> 101010311 | C52: =IF(#REF!<>"",#REF!,"") -> #REF! | D52: =IF(#REF!<>"",#REF!,"") -> #REF! | F52: =IF(AND(C52<>"",D52<>""),"ok","-") -> #REF!
A53: =LEFT(B53,7) -> 1010103 | B53: =B41&"12" -> 101010312 | C53: =IF(#REF!<>"",#REF!,"") -> #REF! | D53: =IF(#REF!<>"",#REF!,"") -> #REF! | F53: =IF(AND(C53<>"",D53<>""),"ok","-") -> #REF!
A54: =LEFT(B54,5) -> 10101 | B54: =$B$14&"04" -> 1010104 | C54: =IF(#REF!<>"",#REF!,"") -> #REF! | D54: =IF(#REF!<>"",#REF!,"") -> #REF! | F54: =IF(AND(C54<>"",D54<>""),"ok","-") -> #REF!
A55: =LEFT(B55,7) -> 1010104 | B55: =B54&"01" -> 101010401 | C55: =IF(#REF!<>"",#REF!,"") -> #REF! | D55: =IF(#REF!<>"",#REF!,"") -> #REF! | F55: =IF(AND(C55<>"",D55<>""),"ok","-") -> #REF!
A56: =LEFT(B56,7) -> 1010104 | B56: =B54&"02" -> 101010402 | C56: =IF(#REF!<>"",#REF!,"") -> #REF! | D56: =IF(#REF!<>"",#REF!,"") -> #REF! | F56: =IF(AND(C56<>"",D56<>""),"ok","-") -> #REF!
A57: =LEFT(B57,7) -> 1010104 | B57: =B54&"03" -> 101010403 | C57: =IF(#REF!<>"",#REF!,"") -> #REF! | D57: =IF(#REF!<>"",#REF!,"") -> #REF! | F57: =IF(AND(C57<>"",D57<>""),"ok","-") -> #REF!
A58: =LEFT(B58,7) -> 1010104 | B58: =B54&"04" -> 101010404 | C58: =IF(#REF!<>"",#REF!,"") -> #REF! | D58: =IF(#REF!<>"",#REF!,"") -> #REF! | F58: =IF(AND(C58<>"",D58<>""),"ok","-") -> #REF!
A59: =LEFT(B59,7) -> 1010104 | B59: =B54&"05" -> 101010405 | C59: =IF(#REF!<>"",#REF!,"") -> #REF! | D59: =IF(#REF!<>"",#REF!,"") -> #REF! | F59: =IF(AND(C59<>"",D59<>""),"ok","-") -> #REF!
A60: =LEFT(B60,7) -> 1010104 | B60: =B54&"06" -> 101010406 | C60: =IF(#REF!<>"",#REF!,"") -> #REF! | D60: =IF(#REF!<>"",#REF!,"") -> #REF! | F60: =IF(AND(C60<>"",D60<>""),"ok","-") -> #REF!
A61: =LEFT(B61,7) -> 1010104 | B61: =B54&"07" -> 101010407 | C61: =IF(#REF!<>"",#REF!,"") -> #REF! | D61: =IF(#REF!<>"",#REF!,"") -> #REF! | F61: =IF(AND(C61<>"",D61<>""),"ok","-") -> #REF!
A62: =LEFT(B62,7) -> 1010104 | B62: =B54&"08" -> 101010408 | C62: =IF(#REF!<>"",#REF!,"") -> #REF! | D62: =IF(#REF!<>"",#REF!,"") -> #REF! | F62: =IF(AND(C62<>"",D62<>""),"ok","-") -> #REF!
A63: =LEFT(B63,7) -> 1010104 | B63: =B54&"09" -> 101010409 | C63: =IF(#REF!<>"",#REF!,"") -> #REF! | D63: =IF(#REF!<>"",#REF!,"") -> #REF! | F63: =IF(AND(C63<>"",D63<>""),"ok","-") -> #REF!
A64: =LEFT(B64,7) -> 1010104 | B64: =B54&"10" -> 101010410 | C64: =IF(#REF!<>"",#REF!,"") -> #REF! | D64: =IF(#REF!<>"",#REF!,"") -> #REF! | F64: =IF(AND(C64<>"",D64<>""),"ok","-") -> #REF!
A65: =LEFT(B65,7) -> 1010104 | B65: =B54&"11" -> 101010411 | C65: =IF(#REF!<>"",#REF!,"") -> #REF! | D65: =IF(#REF!<>"",#REF!,"") -> #REF! | F65: =IF(AND(C65<>"",D65<>""),"ok","-") -> #REF!
A66: =LEFT(B66,7) -> 1010104 | B66: =B54&"12" -> 101010412 | C66: =IF(#REF!<>"",#REF!,"") -> #REF! | D66: =IF(#REF!<>"",#REF!,"") -> #REF! | F66: =IF(AND(C66<>"",D66<>""),"ok","-") -> #REF!
A67: =LEFT(B67,5) -> 10101 | B67: =$B$14&"05" -> 1010105 | C67: =IF(#REF!<>"",#REF!,"") -> #REF! | D67: =IF(#REF!<>"",#REF!,"") -> #REF! | F67: =IF(AND(C67<>"",D67<>""),"ok","-") -> #REF!
A68: =LEFT(B68,7) -> 1010105 | B68: =B67&"01" -> 101010501 | C68: =IF(#REF!<>"",#REF!,"") -> #REF! | D68: =IF(#REF!<>"",#REF!,"") -> #REF! | F68: =IF(AND(C68<>"",D68<>""),"ok","-") -> #REF!
A69: =LEFT(B69,7) -> 1010105 | B69: =B67&"02" -> 101010502 | C69: =IF(#REF!<>"",#REF!,"") -> #REF! | D69: =IF(#REF!<>"",#REF!,"") -> #REF! | F69: =IF(AND(C69<>"",D69<>""),"ok","-") -> #REF!
A70: =LEFT(B70,7) -> 1010105 | B70: =B67&"03" -> 101010503 | C70: =IF(#REF!<>"",#REF!,"") -> #REF! | D70: =IF(#REF!<>"",#REF!,"") -> #REF! | F70: =IF(AND(C70<>"",D70<>""),"ok","-") -> #REF!
A71: =LEFT(B71,7) -> 1010105 | B71: =B67&"04" -> 101010504 | C71: =IF(#REF!<>"",#REF!,"") -> #REF! | D71: =IF(#REF!<>"",#REF!,"") -> #REF! | F71: =IF(AND(C71<>"",D71<>""),"ok","-") -> #REF!
A72: =LEFT(B72,7) -> 1010105 | B72: =B67&"05" -> 101010505 | C72: =IF(#REF!<>"",#REF!,"") -> #REF! | D72: =IF(#REF!<>"",#REF!,"") -> #REF! | F72: =IF(AND(C72<>"",D72<>""),"ok","-") -> #REF!
A73: =LEFT(B73,7) -> 1010105 | B73: =B67&"06" -> 101010506 | C73: =IF(#REF!<>"",#REF!,"") -> #REF! | D73: =IF(#REF!<>"",#REF!,"") -> #REF! | F73: =IF(AND(C73<>"",D73<>""),"ok","-") -> #REF!
A74: =LEFT(B74,7) -> 1010105 | B74: =B67&"07" -> 101010507 | C74: =IF(#REF!<>"",#REF!,"") -> #REF! | D74: =IF(#REF!<>"",#REF!,"") -> #REF! | F74: =IF(AND(C74<>"",D74<>""),"ok","-") -> #REF!
A75: =LEFT(B75,7) -> 1010105 | B75: =B67&"08" -> 101010508 | C75: =IF(#REF!<>"",#REF!,"") -> #REF! | D75: =IF(#REF!<>"",#REF!,"") -> #REF! | F75: =IF(AND(C75<>"",D75<>""),"ok","-") -> #REF!
A76: =LEFT(B76,7) -> 1010105 | B76: =B67&"09" -> 101010509 | C76: =IF(#REF!<>"",#REF!,"") -> #REF! | D76: =IF(#REF!<>"",#REF!,"") -> #REF! | F76: =IF(AND(C76<>"",D76<>""),"ok","-") -> #REF!
A77: =LEFT(B77,7) -> 1010105 | B77: =B67&"10" -> 101010510 | C77: =IF(#REF!<>"",#REF!,"") -> #REF! | D77: =IF(#REF!<>"",#REF!,"") -> #REF! | F77: =IF(AND(C77<>"",D77<>""),"ok","-") -> #REF!
A78: =LEFT(B78,7) -> 1010105 | B78: =B67&"11" -> 101010511 | C78: =IF(#REF!<>"",#REF!,"") -> #REF! | D78: =IF(#REF!<>"",#REF!,"") -> #REF! | F78: =IF(AND(C78<>"",D78<>""),"ok","-") -> #REF!
A79: =LEFT(B79,7) -> 1010105 | B79: =B67&"12" -> 101010512 | C79: =IF(#REF!<>"",#REF!,"") -> #REF! | D79: =IF(#REF!<>"",#REF!,"") -> #REF! | F79: =IF(AND(C79<>"",D79<>""),"ok","-") -> #REF!
A80: =LEFT(B80,5) -> 10101 | B80: =$B$14&"06" -> 1010106 | C80: =IF(#REF!<>"",#REF!,"") -> #REF! | D80: =IF(#REF!<>"",#REF!,"") -> #REF! | F80: =IF(AND(C80<>"",D80<>""),"ok","-") -> #REF!
A81: =LEFT(B81,7) -> 1010106 | B81: =B80&"01" -> 101010601 | C81: =IF(#REF!<>"",#REF!,"") -> #REF! | D81: =IF(#REF!<>"",#REF!,"") -> #REF! | F81: =IF(AND(C81<>"",D81<>""),"ok","-") -> #REF!
A82: =LEFT(B82,7) -> 1010106 | B82: =B80&"02" -> 101010602 | C82: =IF(#REF!<>"",#REF!,"") -> #REF! | D82: =IF(#REF!<>"",#REF!,"") -> #REF! | F82: =IF(AND(C82<>"",D82<>""),"ok","-") -> #REF!
A83: =LEFT(B83,7) -> 1010106 | B83: =B80&"03" -> 101010603 | C83: =IF(#REF!<>"",#REF!,"") -> #REF! | D83: =IF(#REF!<>"",#REF!,"") -> #REF! | F83: =IF(AND(C83<>"",D83<>""),"ok","-") -> #REF!
A84: =LEFT(B84,7) -> 1010106 | B84: =B80&"04" -> 101010604 | C84: =IF(#REF!<>"",#REF!,"") -> #REF! | D84: =IF(#REF!<>"",#REF!,"") -> #REF! | F84: =IF(AND(C84<>"",D84<>""),"ok","-") -> #REF!
A85: =LEFT(B85,7) -> 1010106 | B85: =B80&"05" -> 101010605 | C85: =IF(#REF!<>"",#REF!,"") -> #REF! | D85: =IF(#REF!<>"",#REF!,"") -> #REF! | F85: =IF(AND(C85<>"",D85<>""),"ok","-") -> #REF!
A86: =LEFT(B86,7) -> 1010106 | B86: =B80&"06" -> 101010606 | C86: =IF(#REF!<>"",#REF!,"") -> #REF! | D86: =IF(#REF!<>"",#REF!,"") -> #REF! | F86: =IF(AND(C86<>"",D86<>""),"ok","-") -> #REF!
A87: =LEFT(B87,7) -> 1010106 | B87: =B80&"07" -> 101010607 | C87: =IF(#REF!<>"",#REF!,"") -> #REF! | D87: =IF(#REF!<>"",#REF!,"") -> #REF! | F87: =IF(AND(C87<>"",D87<>""),"ok","-") -> #REF!
A88: =LEFT(B88,7) -> 1010106 | B88: =B80&"08" -> 101010608 | C88: =IF(#REF!<>"",#REF!,"") -> #REF! | D88: =IF(#REF!<>"",#REF!,"") -> #REF! | F88: =IF(AND(C88<>"",D88<>""),"ok","-") -> #REF!
A89: =LEFT(B89,7) -> 1010106 | B89: =B80&"09" -> 101010609 | C89: =IF(#REF!<>"",#REF!,"") -> #REF! | D89: =IF(#REF!<>"",#REF!,"") -> #REF! | F89: =IF(AND(C89<>"",D89<>""),"ok","-") -> #REF!
A90: =LEFT(B90,7) -> 1010106 | B90: =B80&"10" -> 101010610 | C90: =IF(#REF!<>"",#REF!,"") -> #REF! | D90: =IF(#REF!<>"",#REF!,"") -> #REF! | F90: =IF(AND(C90<>"",D90<>""),"ok","-") -> #REF!
A91: =LEFT(B91,7) -> 1010106 | B91: =B80&"11" -> 101010611 | C91: =IF(#REF!<>"",#REF!,"") -> #REF! | D91: =IF(#REF!<>"",#REF!,"") -> #REF! | F91: =IF(AND(C91<>"",D91<>""),"ok","-") -> #REF!
A92: =LEFT(B92,7) -> 1010106 | B92: =B80&"12" -> 101010612 | C92: =IF(#REF!<>"",#REF!,"") -> #REF! | D92: =IF(#REF!<>"",#REF!,"") -> #REF! | F92: =IF(AND(C92<>"",D92<>""),"ok","-") -> #REF!
A93: =LEFT(B93,5) -> 10101 | B93: =$B$14&"07" -> 1010107 | C93: =IF(#REF!<>"",#REF!,"") -> #REF! | D93: =IF(#REF!<>"",#REF!,"") -> #REF! | F93: =IF(AND(C93<>"",D93<>""),"ok","-") -> #REF!
A94: =LEFT(B94,7) -> 1010107 | B94: =B93&"01" -> 101010701 | C94: =IF(#REF!<>"",#REF!,"") -> #REF! | D94: =IF(#REF!<>"",#REF!,"") -> #REF! | F94: =IF(AND(C94<>"",D94<>""),"ok","-") -> #REF!
A95: =LEFT(B95,7) -> 1010107 | B95: =B93&"02" -> 101010702 | C95: =IF(#REF!<>"",#REF!,"") -> #REF! | D95: =IF(#REF!<>"",#REF!,"") -> #REF! | F95: =IF(AND(C95<>"",D95<>""),"ok","-") -> #REF!
A96: =LEFT(B96,7) -> 1010107 | B96: =B93&"03" -> 101010703 | C96: =IF(#REF!<>"",#REF!,"") -> #REF! | D96: =IF(#REF!<>"",#REF!,"") -> #REF! | F96: =IF(AND(C96<>"",D96<>""),"ok","-") -> #REF!
A97: =LEFT(B97,7) -> 1010107 | B97: =B93&"04" -> 101010704 | C97: =IF(#REF!<>"",#REF!,"") -> #REF! | D97: =IF(#REF!<>"",#REF!,"") -> #REF! | F97: =IF(AND(C97<>"",D97<>""),"ok","-") -> #REF!
A98: =LEFT(B98,7) -> 1010107 | B98: =B93&"05" -> 101010705 | C98: =IF(#REF!<>"",#REF!,"") -> #REF! | D98: =IF(#REF!<>"",#REF!,"") -> #REF! | F98: =IF(AND(C98<>"",D98<>""),"ok","-") -> #REF!
A99: =LEFT(B99,7) -> 1010107 | B99: =B93&"06" -> 101010706 | C99: =IF(#REF!<>"",#REF!,"") -> #REF! | D99: =IF(#REF!<>"",#REF!,"") -> #REF! | F99: =IF(AND(C99<>"",D99<>""),"ok","-") -> #REF!
A100: =LEFT(B100,7) -> 1010107 | B100: =B93&"07" -> 101010707 | C100: =IF(#REF!<>"",#REF!,"") -> #REF! | D100: =IF(#REF!<>"",#REF!,"") -> #REF! | F100: =IF(AND(C100<>"",D100<>""),"ok","-") -> #REF!
A101: =LEFT(B101,7) -> 1010107 | B101: =B93&"08" -> 101010708 | C101: =IF(#REF!<>"",#REF!,"") -> #REF! | D101: =IF(#REF!<>"",#REF!,"") -> #REF! | F101: =IF(AND(C101<>"",D101<>""),"ok","-") -> #REF!
A102: =LEFT(B102,7) -> 1010107 | B102: =B93&"09" -> 101010709 | C102: =IF(#REF!<>"",#REF!,"") -> #REF! | D102: =IF(#REF!<>"",#REF!,"") -> #REF! | F102: =IF(AND(C102<>"",D102<>""),"ok","-") -> #REF!
A103: =LEFT(B103,7) -> 1010107 | B103: =B93&"10" -> 101010710 | C103: =IF(#REF!<>"",#REF!,"") -> #REF! | D103: =IF(#REF!<>"",#REF!,"") -> #REF! | F103: =IF(AND(C103<>"",D103<>""),"ok","-") -> #REF!
A104: =LEFT(B104,7) -> 1010107 | B104: =B93&"11" -> 101010711 | C104: =IF(#REF!<>"",#REF!,"") -> #REF! | D104: =IF(#REF!<>"",#REF!,"") -> #REF! | F104: =IF(AND(C104<>"",D104<>""),"ok","-") -> #REF!
A105: =LEFT(B105,7) -> 1010107 | B105: =B93&"12" -> 101010712 | C105: =IF(#REF!<>"",#REF!,"") -> #REF! | D105: =IF(#REF!<>"",#REF!,"") -> #REF! | F105: =IF(AND(C105<>"",D105<>""),"ok","-") -> #REF!
A106: =LEFT(B106,5) -> 10101 | B106: =$B$14&"08" -> 1010108 | C106: =IF(#REF!<>"",#REF!,"") -> #REF! | D106: =IF(#REF!<>"",#REF!,"") -> #REF! | F106: =IF(AND(C106<>"",D106<>""),"ok","-") -> #REF!
...

Sheet Costing
D6: តារាងឧបសម្ព័ន្ធ
D7: ការគណនាតម្រូវការចំណាយលម្អិតឆ្នាំ២០២៣ តាមសកម្មភាព ចង្កោមសកម្មភាព អនុកម្មវិធី
D8: ="របស់"&K11 -> របស់អគ្គនាយកដ្ឋានគោលនយោបាយ
S9: តារាងទី១០
S10: ឯកតា៖ រៀល
D11: រចនាសម្ព័ន្ធកម្មវិធី | G11: 10101 | H11: អនុកម្មវិធីទី១.១ | I11: អង្គភាព | J11: 1002 | K11: អគ្គនាយកដ្ឋានគោលនយោបាយ
D13: សង្ខេបគម្រោងចំណាយ | I13: ប្រចាំ/មិនប្រចាំ | O13: ចំណាយតាមខែ | R13: ចំណាយតាមមុខសញ្ញា | W13: ប្រចាំ/មិនប្រចាំ | X13: រូបិយបណ្ណ | Y13: ខែ | Z13: មុខសញ្ញា
D14: ជំពូក | E14: ចំណាត់ថ្នាក់ចំណាយ | H14: គ្រោងឆ្នាំ២០២៣ | I14: ប្រចាំ | J14: មិនប្រចាំ | K14: row | O14: ខែ | P14: សរុបចំណាយ | R14: មុខសញ្ញា | S14: សរុបចំណាយ | W14: Regular | X14: KHR | Y14: 1 | Z14: លទ្ធកម្ម
D15: 60 | E15: ការទិញ | H15: =SUMIFS($P$32:$P$6606,$B$32:$B$6606,D15,$A$32:$A$6606,$G$11) -> 446300000 | I15: =SUMIFS($P$32:$P$6606,$B$32:$B$6606,$D15,$A$32:$A$6606,$G$11,$I$32:$I$6606,$W$14) -> 394100000 | J15: =SUMIFS($P$32:$P$6606,$B$32:$B$6606,$D15,$A$32:$A$6606,$G$11,$I$32:$I$6606,$W$15) -> 52200000 | K15: =MATCH(D15,#REF!,0) -> #REF! | O15: 1 | P15: =SUMIFS($P$32:$P$6606,$A$32:$A$6606,$G$11,$Q$32:$Q$6606,$O15) -> 0 | R15: លទ្ធកម្ម | S15: =SUMIFS($P$32:$P$6606,$A$32:$A$6606,$G$11,$R$32:$R$6606,$R15) -> 0 | W15: Irregular | Y15: 2 | Z15: រជ្ជទេយ្យ
D16: 61 | E16: សេវាកម្ម | H16: =SUMIFS($P$32:$P$6606,$B$32:$B$6606,D16,$A$32:$A$6606,$G$11) -> 1402600000 | I16: =SUMIFS($P$32:$P$6606,$B$32:$B$6606,$D16,$A$32:$A$6606,$G$11,$I$32:$I$6606,$W$14) -> 1402600000 | J16: =SUMIFS($P$32:$P$6606,$B$32:$B$6606,$D16,$A$32:$A$6606,$G$11,$I$32:$I$6606,$W$15) -> 0 | K16: =MATCH(D16,#REF!,0) -> #REF! | O16: 2 | P16: =SUMIFS($P$32:$P$6606,$A$32:$A$6606,$G$11,$Q$32:$Q$6606,$O16) -> 0 | R16: រជ្ជទេយ្យ | S16: =SUMIFS($P$32:$P$6606,$A$32:$A$6606,$G$11,$R$32:$R$6606,$R16) -> 0 | Y16: 3 | Z16: បើកប្រាក់មុន
D17: 62 | E17: អត្ថប្រយោជន៍សង្គម | H17: =SUMIFS($P$32:$P$6606,$B$32:$B$6606,D17,$A$32:$A$6606,$G$11) -> 0 | I17: =SUMIFS($P$32:$P$6606,$B$32:$B$6606,$D17,$A$32:$A$6606,$G$11,$I$32:$I$6606,$W$14) -> 0 | J17: =SUMIFS($P$32:$P$6606,$B$32:$B$6606,$D17,$A$32:$A$6606,$G$11,$I$32:$I$6606,$W$15) -> 0 | K17: =MATCH(D17,#REF!,0) -> #REF! | O17: 3 | P17: =SUMIFS($P$32:$P$6606,$A$32:$A$6606,$G$11,$Q$32:$Q$6606,$O17) -> 0 | R17: បើកប្រាក់មុន | S17: =SUMIFS($P$32:$P$6606,$A$32:$A$6606,$G$11,$R$32:$R$6606,$R17) -> 0 | Y17: 4 | Z17: បុរេប្រទាន
D18: 63 | E18: ពន្ធនិងអាករ | H18: =SUMIFS($P$32:$P$6606,$B$32:$B$6606,D18,$A$32:$A$6606,$G$11) -> 0 | I18: =SUMIFS($P$32:$P$6606,$B$32:$B$6606,$D18,$A$32:$A$6606,$G$11,$I$32:$I$6606,$W$14) -> 0 | J18: =SUMIFS($P$32:$P$6606,$B$32:$B$6606,$D18,$A$32:$A$6606,$G$11,$I$32:$I$6606,$W$15) -> 0 | K18: =MATCH(D18,#REF!,0) -> #REF! | O18: 4 | P18: =SUMIFS($P$32:$P$6606,$A$32:$A$6606,$G$11,$Q$32:$Q$6606,$O18) -> 0 | R18: បុរេប្រទាន | S18: =SUMIFS($P$32:$P$6606,$A$32:$A$6606,$G$11,$R$32:$R$6606,$R18) -> 0 | Y18: 5 | Z18: ផ្សេងៗ
D19: 64 | E19: បន្ទុកបុគ្គលិក | H19: =SUMIFS($P$32:$P$6606,$B$32:$B$6606,D19,$A$32:$A$6606,$G$11) -> 1261800000 | I19: =SUMIFS($P$32:$P$6606,$B$32:$B$6606,$D19,$A$32:$A$6606,$G$11,$I$32:$I$6606,$W$14) -> 1261800000 | J19: =SUMIFS($P$32:$P$6606,$B$32:$B$6606,$D19,$A$32:$A$6606,$G$11,$I$32:$I$6606,$W$15) -> 0 | K19: =MATCH(D19,#REF!,0) -> #REF! | O19: 5 | P19: =SUMIFS($P$32:$P$6606,$A$32:$A$6606,$G$11,$Q$32:$Q$6606,$O19) -> 0 | R19: ផ្សេងៗ | S19: =SUMIFS($P$32:$P$6606,$A$32:$A$6606,$G$11,$R$32:$R$6606,$R19) -> 0 | Y19: 6
D20: 65 | E20: ឧបត្ថម្ភធន | H20: =SUMIFS($P$32:$P$6606,$B$32:$B$6606,D20,$A$32:$A$6606,$G$11) -> 0 | I20: =SUMIFS($P$32:$P$6606,$B$32:$B$6606,$D20,$A$32:$A$6606,$G$11,$I$32:$I$6606,$W$14) -> 0 | J20: =SUMIFS($P$32:$P$6606,$B$32:$B$6606,$D20,$A$32:$A$6606,$G$11,$I$32:$I$6606,$W$15) -> 0 | K20: =MATCH(D20,#REF!,0) -> #REF! | O20: 6 | P20: =SUMIFS($P$32:$P$6606,$A$32:$A$6606,$G$11,$Q$32:$Q$6606,$O20) -> 0 | R20: សរុប | S20: =SUM(S15:S19) -> 0 | Y20: 7
D21: 66 | E21: បន្ទុកហិរញ្ញវត្ថុ | H21: =SUMIFS($P$32:$P$6606,$B$32:$B$6606,D21,$A$32:$A$6606,$G$11) -> 0 | I21: =SUMIFS($P$32:$P$6606,$B$32:$B$6606,$D21,$A$32:$A$6606,$G$11,$I$32:$I$6606,$W$14) -> 0 | J21: =SUMIFS($P$32:$P$6606,$B$32:$B$6606,$D21,$A$32:$A$6606,$G$11,$I$32:$I$6606,$W$15) -> 0 | K21: =MATCH(D21,#REF!,0) -> #REF! | O21: 7 | P21: =SUMIFS($P$32:$P$6606,$A$32:$A$6606,$G$11,$Q$32:$Q$6606,$O21) -> 0 | Y21: 8
D22: 67 | E22: បន្ទុកពិសេស | H22: =SUMIFS($P$32:$P$6606,$B$32:$B$6606,D22,$A$32:$A$6606,$G$11) -> 0 | I22: =SUMIFS($P$32:$P$6606,$B$32:$B$6606,$D22,$A$32:$A$6606,$G$11,$I$32:$I$6606,$W$14) -> 0 | J22: =SUMIFS($P$32:$P$6606,$B$32:$B$6606,$D22,$A$32:$A$6606,$G$11,$I$32:$I$6606,$W$15) -> 0 | K22: =MATCH(D22,#REF!,0) -> #REF! | O22: 8 | P22: =SUMIFS($P$32:$P$6606,$A$32:$A$6606,$G$11,$Q$32:$Q$6606,$O22) -> 0 | Y22: 9
D23: 68 | E23: ទាយជ្ជទានឱ្យដល់រំលស់អចលកម្ម | H23: =SUMIFS($P$32:$P$6606,$B$32:$B$6606,D23,$A$32:$A$6606,$G$11) -> 0 | I23: =SUMIFS($P$32:$P$6606,$B$32:$B$6606,$D23,$A$32:$A$6606,$G$11,$I$32:$I$6606,$W$14) -> 0 | J23: =SUMIFS($P$32:$P$6606,$B$32:$B$6606,$D23,$A$32:$A$6606,$G$11,$I$32:$I$6606,$W$15) -> 0 | K23: =MATCH(D23,#REF!,0) -> #REF! | O23: 9 | P23: =SUMIFS($P$32:$P$6606,$A$32:$A$6606,$G$11,$Q$32:$Q$6606,$O23) -> 0 | Y23: 10
D24: 69 | E24: ចំណាយមិនបានគ្រោងទុក | H24: =SUMIFS($P$32:$P$6606,$B$32:$B$6606,D24,$A$32:$A$6606,$G$11) -> 0 | I24: =SUMIFS($P$32:$P$6606,$B$32:$B$6606,$D24,$A$32:$A$6606,$G$11,$I$32:$I$6606,$W$14) -> 0 | J24: =SUMIFS($P$32:$P$6606,$B$32:$B$6606,$D24,$A$32:$A$6606,$G$11,$I$32:$I$6606,$W$15) -> 0 | K24: =MATCH(D24,#REF!,0) -> #REF! | O24: 10 | P24: =SUMIFS($P$32:$P$6606,$A$32:$A$6606,$G$11,$Q$32:$Q$6606,$O24) -> 0 | Y24: 11
D25: សរុប | H25: =SUM(H15:H24) -> 3110700000 | I25: =SUM(I15:I24) -> 3058500000 | J25: =SUM(J15:J24) -> 52200000 | O25: 11 | P25: =SUMIFS($P$32:$P$6606,$A$32:$A$6606,$G$11,$Q$32:$Q$6606,$O25) -> 0 | Y25: 12
O26: 12 | P26: =SUMIFS($P$32:$P$6606,$A$32:$A$6606,$G$11,$Q$32:$Q$6606,$O26) -> 0
O27: សរុប | P27: =SUM(P15:P26) -> 0
A29: កូដកម្មវិធី | B29: ជំពូក | C29: លេខ | D29: ល.រ. | E29: កូដច.ស. | F29: កូដសកម្មភាព | G29: អនុគណនី | H29: បរិយាយមុខសញ្ញា | I29: ប្រចាំ/មិនប្រចាំ | J29: ឯកតា | K29: បរិមាណ | L29: រូបិយបណ្ណ | M29: តម្លៃឯកតា | N29: តម្លៃ១លើក | O29: លើក/ឆ្នាំ | P29: សរុបប្រចាំឆ្នាំ | Q29: ខែ | R29: មុខសញ្ញា | S29: ផ្សេងៗ | U29: Check | V29: Check | W29: Check
D30: Line # | E30: Act. Cluster | F30: Prog. Activity | G30: Sub-Account | H30: Item Description | I30: Ir/Regular | J30: Unit Measure | K30: # of Units | L30: Currency | M30: Unit Price | N30: Total Amount | O30: # Times | P30: Total Annual Amount | Q30: Month | R30: Expense Type | S30: Misc. | U30: បរិមាណ | V30: តម្លៃឯកតា | W30: ចំនួនលើក
D31: 1 | E31: 2 | F31: 3 | G31: 4 | H31: 5 | I31: 6 | J31: 7 | K31: 8 | L31: 9 | M31: 10 | N31: 11=8*10 | O31: 12 | P31: 13=11*12 | Q31: 14 | R31: 15 | S31: 16
A32: =IF(AND(F32<>"",G32<>""),LEFT(E32,5),"") | B32: =IF(AND(F32<>"",G32<>""),LEFT(G32,2),"") | C32: =IF(AND(F32<>"",G32<>""),COUNT($C31:C$32)+1,"") | D32: =IF(C32<>"","LN"&TEXT(C32,"0000"),"") | E32: =IF(AND(F32<>"",G32<>""),LEFT(F32,7),"") | F32: =$G$11 -> 10101 | H32: =$H$11&" : "&$K$11 -> អនុកម្មវិធីទី១.១ : អគ្គនាយកដ្ឋានគោលនយោបាយ | N32: =IF(AND(F32<>"",G32<>""),K32*M32,"") | P32: =SUMIF($A33:$A$6606,F32,$P33:$P$6606) -> 3110700000 | T32: =IF(AND(F32<>"",G32<>""),"ok","-") -> -
A33: =IF(AND(F33<>"",G33<>""),LEFT(E33,5),"") | B33: =IF(AND(F33<>"",G33<>""),LEFT(G33,2),"") | C33: =IF(AND(F33<>"",G33<>""),COUNT($C$32:C32)+1,"") | D33: =IF(C33<>"","LN"&TEXT(C33,"0000"),"") | E33: =IF(AND(F33<>"",G33<>""),LEFT(F33,7),"") | F33: 1010101 | H33: ចង្កោមសកម្មភាពទី១៖ លេខាធិការដ្ឋាន | N33: =IF(AND(F33<>"",G33<>""),K33*M33,"") | P33: =SUMIF($E34:$E$6606,F33,$P34:$P$6606) -> 1211100000 | T33: =IF(AND(F33<>"",G33<>""),"ok","-") -> -
A34: =IF(AND(F34<>"",G34<>""),LEFT(E34,5),"") | B34: =IF(AND(F34<>"",G34<>""),LEFT(G34,2),"") | C34: =IF(AND(F34<>"",G34<>""),COUNT($C$32:C33)+1,"") | D34: =IF(C34<>"","LN"&TEXT(C34,"0000"),"") | E34: =IF(AND(F34<>"",G34<>""),LEFT(F34,7),"") | F34: 101010101 | H34: សកម្មភាពទី១ នៃចង្កោមសកម្មភាពទី១៖ បំពេញមុខងារជាលេខាធិការដ្ឋាន | N34: =IF(AND(F34<>"",G34<>""),K34*M34,"") | P34: =SUMIF($F35:$F$6606,F34,$P35:$P$6606) -> 1185100000 | T34: =IF(AND(F34<>"",G34<>""),"ok","-") -> -
A35: =IF(AND(F35<>"",G35<>""),LEFT(E35,5),"") | B35: =IF(AND(F35<>"",G35<>""),LEFT(G35,2),"") | C35: =IF(AND(F35<>"",G35<>""),COUNT($C$32:C34)+1,"") | D35: =IF(C35<>"","LN"&TEXT(C35,"0000"),"") | E35: =IF(AND(F35<>"",G35<>""),LEFT(F35,7),"") | H35: ១.បន្ទុកបុគ្គលិក | N35: =IF(AND(F35<>"",G35<>""),K35*M35,"") | P35: =SUM(P36:P46) -> 1114200000 | T35: =IF(AND(F35<>"",G35<>""),"ok","-") -> -
A36: =IF(AND(F36<>"",G36<>""),LEFT(E36,5),"") -> 10101 | B36: =IF(AND(F36<>"",G36<>""),LEFT(G36,2),"") -> 64 | C36: =IF(AND(F36<>"",G36<>""),COUNT($C$32:C35)+1,"") -> 1 | D36: =IF(C36<>"","LN"&TEXT(C36,"0000"),"") -> LN0001 | E36: =IF(AND(F36<>"",G36<>""),LEFT(F36,7),"") -> 1010101 | F36: 101010101 | G36: 64021 | H36: ប្រាក់បៀវត្សមូលដ្ឋានមន្ត្រីរាជការ ចំនួន ៥៦នាក់ | I36: Regular | J36: ខែ | K36: 1 | L36: KHR | M36: 50216000 | N36: =IF(AND(F36<>"",G36<>""),K36*M36,"") -> 50216000 | O36: 12 | P36: =IF(AND(F36<>"",G36<>""),N36*O36,"") -> 602592000 | T36: =IF(AND(F36<>"",G36<>""),"ok","-") -> ok | U36: =MOD(K36,1) -> 0 | V36: =MOD(M36,1) -> 0 | W36: =MOD(O36,1) -> 0
A37: =IF(AND(F37<>"",G37<>""),LEFT(E37,5),"") -> 10101 | B37: =IF(AND(F37<>"",G37<>""),LEFT(G37,2),"") -> 64 | C37: =IF(AND(F37<>"",G37<>""),COUNT($C$32:C36)+1,"") -> 2 | D37: =IF(C37<>"","LN"&TEXT(C37,"0000"),"") -> LN0002 | E37: =IF(AND(F37<>"",G37<>""),LEFT(F37,7),"") -> 1010101 | F37: 101010101 | G37: 64021 | H37: បង្រ្គប់ប្រាក់បៀវត្សមូលដ្ឋានមន្ត្រីរាជការ ចំនួន ៥៦នាក់ | I37: Regular | J37: ខែ | K37: 1 | L37: KHR | M37: 8000 | N37: =IF(AND(F37<>"",G37<>""),K37*M37,"") -> 8000 | O37: 1 | P37: =IF(AND(F37<>"",G37<>""),N37*O37,"") -> 8000 | T37: =IF(AND(F37<>"",G37<>""),"ok","-") -> ok | U37: =MOD(K37,1) -> 0 | V37: =MOD(M37,1) -> 0 | W37: =MOD(O37,1) -> 0
A38: =IF(AND(F38<>"",G38<>""),LEFT(E38,5),"") -> 10101 | B38: =IF(AND(F38<>"",G38<>""),LEFT(G38,2),"") -> 64 | C38: =IF(AND(F38<>"",G38<>""),COUNT($C$32:C37)+1,"") -> 3 | D38: =IF(C38<>"","LN"&TEXT(C38,"0000"),"") -> LN0003 | E38: =IF(AND(F38<>"",G38<>""),LEFT(F38,7),"") -> 1010101 | F38: 101010101 | G38: 64022 | H38: ប្រាក់បំណាច់មុខងារ ចំនួន ៥៦ នាក់ | I38: Regular | J38: ខែ | K38: 1 | L38: KHR | M38: 40050000 | N38: =IF(AND(F38<>"",G38<>""),K38*M38,"") -> 40050000 | O38: 12 | P38: =IF(AND(F38<>"",G38<>""),N38*O38,"") -> 480600000 | T38: =IF(AND(F38<>"",G38<>""),"ok","-") -> ok | U38: =MOD(K38,1) -> 0 | V38: =MOD(M38,1) -> 0 | W38: =MOD(O38,1) -> 0
A39: =IF(AND(F39<>"",G39<>""),LEFT(E39,5),"") -> 10101 | B39: =IF(AND(F39<>"",G39<>""),LEFT(G39,2),"") -> 64 | C39: =IF(AND(F39<>"",G39<>""),COUNT($C$32:C38)+1,"") -> 4 | D39: =IF(C39<>"","LN"&TEXT(C39,"0000"),"") -> LN0004 | E39: =IF(AND(F39<>"",G39<>""),LEFT(F39,7),"") -> 1010101 | F39: 101010101 | G39: 64022 | H39: បង្រ្គប់ប្រាក់បំណាច់មុខងារ ចំនួន ៥៦ នាក់ | I39: Regular | J39: ខែ | K39: 1 | L39: KHR | M39: 400000 | N39: =IF(AND(F39<>"",G39<>""),K39*M39,"") -> 400000 | O39: 1 | P39: =IF(AND(F39<>"",G39<>""),N39*O39,"") -> 400000 | T39: =IF(AND(F39<>"",G39<>""),"ok","-") -> ok | U39: =MOD(K39,1) -> 0 | V39: =MOD(M39,1) -> 0 | W39: =MOD(O39,1) -> 0
A40: =IF(AND(F40<>"",G40<>""),LEFT(E40,5),"") -> 10101 | B40: =IF(AND(F40<>"",G40<>""),LEFT(G40,2),"") -> 64 | C40: =IF(AND(F40<>"",G40<>""),COUNT($C$32:C39)+1,"") -> 5 | D40: =IF(C40<>"","LN"&TEXT(C40,"0000"),"") -> LN0005 | E40: =IF(AND(F40<>"",G40<>""),LEFT(F40,7),"") -> 1010101 | F40: 101010101 | G40: 64052 | H40: អ្នកសំរាលកូន (មាតុភាព) | I40: Regular | J40: នាក់ | K40: 3 | L40: KHR | M40: 800000 | N40: =IF(AND(F40<>"",G40<>""),K40*M40,"") -> 2400000 | O40: 1 | P40: =IF(AND(F40<>"",G40<>""),N40*O40,"") -> 2400000 | T40: =IF(AND(F40<>"",G40<>""),"ok","-") -> ok | U40: =MOD(K40,1) -> 0 | V40: =MOD(M40,1) -> 0 | W40: =MOD(O40,1) -> 0
A41: =IF(AND(F41<>"",G41<>""),LEFT(E41,5),"") -> 10101 | B41: =IF(AND(F41<>"",G41<>""),LEFT(G41,2),"") -> 64 | C41: =IF(AND(F41<>"",G41<>""),COUNT($C$32:C40)+1,"") -> 6 | D41: =IF(C41<>"","LN"&TEXT(C41,"0000"),"") -> LN0006 | E41: =IF(AND(F41<>"",G41<>""),LEFT(F41,7),"") -> 1010101 | F41: 101010101 | G41: 64061 | H41: កូនមានអាយុក្រោម 20ឆ្នាំ | I41: Regular | J41: នាក់ | K41: 32 | L41: KHR | M41: 10000 | N41: =IF(AND(F41<>"",G41<>""),K41*M41,"") -> 320000 | O41: 12 | P41: =IF(AND(F41<>"",G41<>""),N41*O41,"") -> 3840000 | T41: =IF(AND(F41<>"",G41<>""),"ok","-") -> ok | U41: =MOD(K41,1) -> 0 | V41: =MOD(M41,1) -> 0 | W41: =MOD(O41,1) -> 0
A42: =IF(AND(F42<>"",G42<>""),LEFT(E42,5),"") -> 10101 | B42: =IF(AND(F42<>"",G42<>""),LEFT(G42,2),"") -> 64 | C42: =IF(AND(F42<>"",G42<>""),COUNT($C$32:C39)+1,"") -> 5 | D42: =IF(C42<>"","LN"&TEXT(C42,"0000"),"") -> LN0005 | E42: =IF(AND(F42<>"",G42<>""),LEFT(F42,7),"") -> 1010101 | F42: 101010101 | G42: 64061 | H42: បង្គ្រប់កូនមានអាយុក្រោម 20ឆ្នាំ | I42: Regular | J42: នាក់ | K42: 1 | L42: KHR | M42: 60000 | N42: =IF(AND(F42<>"",G42<>""),K42*M42,"") -> 60000 | O42: 1 | P42: =IF(AND(F42<>"",G42<>""),N42*O42,"") -> 60000 | T42: =IF(AND(F42<>"",G42<>""),"ok","-") -> ok | U42: =MOD(K42,1) -> 0 | V42: =MOD(M42,1) -> 0 | W42: =MOD(O42,1) -> 0 | AA42: =AA49+AA219+AA382+AA383+AA617+AA768+AA872+AA873 -> 17664500
A43: =IF(AND(F43<>"",G43<>""),LEFT(E43,5),"") -> 10101 | B43: =IF(AND(F43<>"",G43<>""),LEFT(G43,2),"") -> 64 | C43: =IF(AND(F43<>"",G43<>""),COUNT($C$32:C42)+1,"") -> 8 | D43: =IF(C43<>"","LN"&TEXT(C43,"0000"),"") -> LN0008 | E43: =IF(AND(F43<>"",G43<>""),LEFT(F43,7),"") -> 1010101 | F43: 101010101 | G43: 64063 | H43: ប្រាក់បំណាច់អ្នកក្នុងបន្ទុក | I43: Regular | J43: នាក់ | K43: 10 | L43: KHR | M43: 15000 | N43: =IF(AND(F43<>"",G43<>""),K43*M43,"") -> 150000 | O43: 12 | P43: =IF(AND(F43<>"",G43<>""),N43*O43,"") -> 1800000 | T43: =IF(AND(F43<>"",G43<>""),"ok","-") -> ok | U43: =MOD(K43,1) -> 0 | V43: =MOD(M43,1) -> 0 | W43: =MOD(O43,1) -> 0
A44: =IF(AND(F44<>"",G44<>""),LEFT(E44,5),"") -> 10101 | B44: =IF(AND(F44<>"",G44<>""),LEFT(G44,2),"") -> 64 | C44: =IF(AND(F44<>"",G44<>""),COUNT($C$32:C41)+1,"") -> 7 | D44: =IF(C44<>"","LN"&TEXT(C44,"0000"),"") -> LN0007 | E44: =IF(AND(F44<>"",G44<>""),LEFT(F44,7),"") -> 1010101 | F44: 101010101 | G44: 64981 | H44: បន្ទុកផ្សេងៗទៀត | I44: Regular | J44: នាក់ | K44: 54 | L44: KHR | M44: 50000 | N44: =IF(AND(F44<>"",G44<>""),K44*M44,"") -> 2700000 | O44: 2 | P44: =IF(AND(F44<>"",G44<>""),N44*O44,"") -> 5400000 | T44: =IF(AND(F44<>"",G44<>""),"ok","-") -> ok | U44: =MOD(K44,1) -> 0 | V44: =MOD(M44,1) -> 0 | W44: =MOD(O44,1) -> 0 | AA44: =AA51+AA221+AA384+AA385+AA619+AA770+AA874+AA875 -> 0
A45: =IF(AND(F45<>"",G45<>""),LEFT(E45,5),"") -> 10101 | B45: =IF(AND(F45<>"",G45<>""),LEFT(G45,2),"") -> 64 | C45: =IF(AND(F45<>"",G45<>""),COUNT($C$32:C42)+1,"") -> 8 | D45: =IF(C45<>"","LN"&TEXT(C45,"0000"),"") -> LN0008 | E45: =IF(AND(F45<>"",G45<>""),LEFT(F45,7),"") -> 1010101 | F45: 101010101 | G45: 64041 | H45: ភ្នាក់ងារជាប់កិច្ចសន្យា ចំនួន ២នាក់ | I45: Regular | J45: នាក់ | K45: 2 | L45: KHR | M45: 710000 | N45: =IF(AND(F45<>"",G45<>""),K45*M45,"") -> 1420000 | O45: 12 | P45: =IF(AND(F45<>"",G45<>""),N45*O45,"") -> 17040000 | T45: =IF(AND(F45<>"",G45<>""),"ok","-") -> ok | U45: =MOD(K45,1) -> 0 | V45: =MOD(M45,1) -> 0 | W45: =MOD(O45,1) -> 0
A46: =IF(AND(F46<>"",G46<>""),LEFT(E46,5),"") -> 10101 | B46: =IF(AND(F46<>"",G46<>""),LEFT(G46,2),"") -> 64 | C46: =IF(AND(F46<>"",G46<>""),COUNT($C$32:C45)+1,"") -> 11 | D46: =IF(C46<>"","LN"&TEXT(C46,"0000"),"") -> LN0011 | E46: =IF(AND(F46<>"",G46<>""),LEFT(F46,7),"") -> 1010101 | F46: 101010101 | G46: 64041 | H46: បង្គ្រប់ភ្នាក់ងារជាប់កិច្ចសន្យា ចំនួន ២នាក់ | I46: Regular | J46: នាក់ | K46: 1 | L46: KHR | M46: 60000 | N46: =IF(AND(F46<>"",G46<>""),K46*M46,"") -> 60000 | O46: 1 | P46: =IF(AND(F46<>"",G46<>""),N46*O46,"") -> 60000 | T46: =IF(AND(F46<>"",G46<>""),"ok","-") -> ok | U46: =MOD(K46,1) -> 0 | V46: =MOD(M46,1) -> 0 | W46: =MOD(O46,1) -> 0 | AA46: =AA49+AA219+AA382+AA383+AA617 -> 14714500
A47: =IF(AND(F47<>"",G47<>""),LEFT(E47,5),"") | B47: =IF(AND(F47<>"",G47<>""),LEFT(G47,2),"") | C47: =IF(AND(F47<>"",G47<>""),COUNT($C$32:C46)+1,"") | D47: =IF(C47<>"","LN"&TEXT(C47,"0000"),"") | E47: =IF(AND(F47<>"",G47<>""),LEFT(F47,7),"") | H47: ២.ចំណាយលេខាធិការដ្ឋាន | N47: =IF(AND(F47<>"",G47<>""),K47*M47,"") | P47: =SUM(P48:P82) -> 69900000 | T47: =IF(AND(F47<>"",G47<>""),"ok","-") -> - | U47: =MOD(K47,1) -> 0 | V47: =MOD(M47,1) -> 0 | W47: =MOD(O47,1) -> 0
A48: =IF(AND(F48<>"",G48<>""),LEFT(E48,5),"") -> 10101 | B48: =IF(AND(F48<>"",G48<>""),LEFT(G48,2),"") -> 60 | C48: =IF(AND(F48<>"",G48<>""),COUNT($C$32:C47)+1,"") -> 12 | D48: =IF(C48<>"","LN"&TEXT(C48,"0000"),"") -> LN0012 | E48: =IF(AND(F48<>"",G48<>""),LEFT(F48,7),"") -> 1010101 | F48: 101010101 | G48: 60014 | H48: ទិញសំបកកង់ឡាន | I48: Regular | J48: សំបកកង់ | K48: 4 | L48: KHR | M48: 800000 | N48: =IF(AND(F48<>"",G48<>""),K48*M48,"") -> 3200000 | O48: 1 | P48: =IF(AND(F48<>"",G48<>""),N48*O48,"") -> 3200000 | T48: =IF(AND(F48<>"",G48<>""),"ok","-") -> ok | U48: =MOD(K48,1) -> 0 | V48: =MOD(M48,1) -> 0 | W48: =MOD(O48,1) -> 0 | Y48: old | Z48: new | AA48: different
A49: =IF(AND(F49<>"",G49<>""),LEFT(E49,5),"") -> 10101 | B49: =IF(AND(F49<>"",G49<>""),LEFT(G49,2),"") -> 60 | C49: =IF(AND(F49<>"",G49<>""),COUNT($C$32:C48)+1,"") -> 13 | D49: =IF(C49<>"","LN"&TEXT(C49,"0000"),"") -> LN0013 | E49: =IF(AND(F49<>"",G49<>""),LEFT(F49,7),"") -> 1010101 | F49: 101010101 | G49: 60015 | H49: ប្រេងឥន្ធនៈ និងប្រេងរំអិល | I49: Regular | J49: លីត្រ | K49: =50+18+104-7-1 -> 164 | L49: KHR | M49: 5500 | N49: =IF(AND(F49<>"",G49<>""),K49*M49,"") -> 902000 | O49: 12 | P49: =IF(AND(F49<>"",G49<>""),N49*O49,"") -> 10824000 | T49: =IF(AND(F49<>"",G49<>""),"ok","-") -> ok | U49: =MOD(K49,1) -> 0 | V49: =MOD(M49,1) -> 0 | W49: =MOD(O49,1) -> 0 | Y49: 2376000 | Z49: 11352000 | AA49: =Z49-Y49 -> 8976000
A50: =IF(AND(F50<>"",G50<>""),LEFT(E50,5),"") -> 10101 | B50: =IF(AND(F50<>"",G50<>""),LEFT(G50,2),"") -> 60 | C50: =IF(AND(F50<>"",G50<>""),COUNT($C$32:C49)+1,"") -> 14 | D50: =IF(C50<>"","LN"&TEXT(C50,"0000"),"") -> LN0014 | E50: =IF(AND(F50<>"",G50<>""),LEFT(F50,7),"") -> 1010101 | F50: 101010101 | G50: 60021 | H50: ក្រដាស double A4/ ៥រ៉ាម/កេះ/80g | I50: Regular | J50: កេស | K50: 4 | L50: KHR | M50: 73800 | N50: =IF(AND(F50<>"",G50<>""),K50*M50,"") -> 295200 | O50: 11 | P50: =IF(AND(F50<>"",G50<>""),N50*O50,"") -> 3247200 | T50: =IF(AND(F50<>"",G50<>""),"ok","-") -> ok | U50: =MOD(K50,1) -> 0 | V50: =MOD(M50,1) -> 0 | W50: =MOD(O50,1) -> 0
A51: =IF(AND(F51<>"",G51<>""),LEFT(E51,5),"") -> 10101 | B51: =IF(AND(F51<>"",G51<>""),LEFT(G51,2),"") -> 60 | C51: =IF(AND(F51<>"",G51<>""),COUNT($C$32:C50)+1,"") -> 15 | D51: =IF(C51<>"","LN"&TEXT(C51,"0000"),"") -> LN0015 | E51: =IF(AND(F51<>"",G51<>""),LEFT(F51,7),"") -> 1010101 | F51: 101010101 | G51: 60021 | H51: ក្រដាស double A4/ ៥រ៉ាម/កេះ/80g | I51: Regular | J51: កេស | K51: 1 | L51: KHR | M51: 184800 | N51: =IF(AND(F51<>"",G51<>""),K51*M51,"") -> 184800 | O51: 1 | P51: =IF(AND(F51<>"",G51<>""),N51*O51,"") -> 184800 | T51: =IF(AND(F51<>"",G51<>""),"ok","-") -> ok | U51: =MOD(K51,1) -> 0 | V51: =MOD(M51,1) -> 0 | W51: =MOD(O51,1) -> 0
A52: =IF(AND(F52<>"",G52<>""),LEFT(E52,5),"") -> 10101 | B52: =IF(AND(F52<>"",G52<>""),LEFT(G52,2),"") -> 60 | C52: =IF(AND(F52<>"",G52<>""),COUNT($C$32:C51)+1,"") -> 16 | D52: =IF(C52<>"","LN"&TEXT(C52,"0000"),"") -> LN0016 | E52: =IF(AND(F52<>"",G52<>""),LEFT(F52,7),"") -> 1010101 | F52: 101010101 | G52: 60021 | H52: ប៊ិចខៀវ | I52: Regular | J52: ប្រអប់ | K52: 4 | L52: KHR | M52: 32000 | N52: =IF(AND(F52<>"",G52<>""),K52*M52,"") -> 128000 | O52: 1 | P52: =IF(AND(F52<>"",G52<>""),N52*O52,"") -> 128000 | T52: =IF(AND(F52<>"",G52<>""),"ok","-") -> ok | U52: =MOD(K52,1) -> 0 | V52: =MOD(M52,1) -> 0 | W52: =MOD(O52,1) -> 0
A53: =IF(AND(F53<>"",G53<>""),LEFT(E53,5),"") -> 10101 | B53: =IF(AND(F53<>"",G53<>""),LEFT(G53,2),"") -> 60 | C53: =IF(AND(F53<>"",G53<>""),COUNT($C$32:C52)+1,"") -> 17 | D53: =IF(C53<>"","LN"&TEXT(C53,"0000"),"") -> LN0017 | E53: =IF(AND(F53<>"",G53<>""),LEFT(F53,7),"") -> 1010101 | F53: 101010101 | G53: 60021 | H53: ប៊ិចប្រហម | I53: Regular | J53: ប្រអប់ | K53: 2 | L53: KHR | M53: 32000 | N53: =IF(AND(F53<>"",G53<>""),K53*M53,"") -> 64000 | O53: 1 | P53: =IF(AND(F53<>"",G53<>""),N53*O53,"") -> 64000 | T53: =IF(AND(F53<>"",G53<>""),"ok","-") -> ok | U53: =MOD(K53,1) -> 0 | V53: =MOD(M53,1) -> 0 | W53: =MOD(O53,1) -> 0
A54: =IF(AND(F54<>"",G54<>""),LEFT(E54,5),"") -> 10101 | B54: =IF(AND(F54<>"",G54<>""),LEFT(G54,2),"") -> 60 | C54: =IF(AND(F54<>"",G54<>""),COUNT($C$32:C53)+1,"") -> 18 | D54: =IF(C54<>"","LN"&TEXT(C54,"0000"),"") -> LN0018 | E54: =IF(AND(F54<>"",G54<>""),LEFT(F54,7),"") -> 1010101 | F54: 101010101 | G54: 60021 | H54: ខ្មៅដៃ | I54: Regular | J54: ប្រអប់ | K54: 3 | L54: KHR | M54: 3200 | N54: =IF(AND(F54<>"",G54<>""),K54*M54,"") -> 9600 | O54: 1 | P54: =IF(AND(F54<>"",G54<>""),N54*O54,"") -> 9600 | T54: =IF(AND(F54<>"",G54<>""),"ok","-") -> ok | U54: =MOD(K54,1) -> 0 | V54: =MOD(M54,1) -> 0 | W54: =MOD(O54,1) -> 0
A55: =IF(AND(F55<>"",G55<>""),LEFT(E55,5),"") -> 10101 | B55: =IF(AND(F55<>"",G55<>""),LEFT(G55,2),"") -> 60 | C55: =IF(AND(F55<>"",G55<>""),COUNT($C$32:C54)+1,"") -> 19 | D55: =IF(C55<>"","LN"&TEXT(C55,"0000"),"") -> LN0019 | E55: =IF(AND(F55<>"",G55<>""),LEFT(F55,7),"") -> 1010101 | F55: 101010101 | G55: 60021 | H55: ប៊ិច highlight | I55: Regular | J55: ប្រអប់ | K55: 3 | L55: KHR | M55: 40000 | N55: =IF(AND(F55<>"",G55<>""),K55*M55,"") -> 120000 | O55: 1 | P55: =IF(AND(F55<>"",G55<>""),N55*O55,"") -> 120000 | T55: =IF(AND(F55<>"",G55<>""),"ok","-") -> ok | U55: =MOD(K55,1) -> 0 | V55: =MOD(M55,1) -> 0 | W55: =MOD(O55,1) -> 0
A56: =IF(AND(F56<>"",G56<>""),LEFT(E56,5),"") -> 10101 | B56: =IF(AND(F56<>"",G56<>""),LEFT(G56,2),"") -> 60 | C56: =IF(AND(F56<>"",G56<>""),COUNT($C$32:C55)+1,"") -> 20 | D56: =IF(C56<>"","LN"&TEXT(C56,"0000"),"") -> LN0020 | E56: =IF(AND(F56<>"",G56<>""),LEFT(F56,7),"") -> 1010101 | F56: 101010101 | G56: 60021 | H56: ឃ្នាប Paper clip | I56: Regular | J56: ប្រអប់ | K56: 15 | L56: KHR | M56: 9600 | N56: =IF(AND(F56<>"",G56<>""),K56*M56,"") -> 144000 | O56: 1 | P56: =IF(AND(F56<>"",G56<>""),N56*O56,"") -> 144000 | T56: =IF(AND(F56<>"",G56<>""),"ok","-") -> ok | U56: =MOD(K56,1) -> 0 | V56: =MOD(M56,1) -> 0 | W56: =MOD(O56,1) -> 0
A57: =IF(AND(F57<>"",G57<>""),LEFT(E57,5),"") -> 10101 | B57: =IF(AND(F57<>"",G57<>""),LEFT(G57,2),"") -> 60 | C57: =IF(AND(F57<>"",G57<>""),COUNT($C$32:C56)+1,"") -> 21 | D57: =IF(C57<>"","LN"&TEXT(C57,"0000"),"") -> LN0021 | E57: =IF(AND(F57<>"",G57<>""),LEFT(F57,7),"") -> 1010101 | F57: 101010101 | G57: 60021 | H57: ប្រដាប់កឹបតូច | I57: Regular | J57: គ្រៀង | K57: 10 | L57: KHR | M57: 3400 | N57: =IF(AND(F57<>"",G57<>""),K57*M57,"") -> 34000 | O57: 1 | P57: =IF(AND(F57<>"",G57<>""),N57*O57,"") -> 34000 | T57: =IF(AND(F57<>"",G57<>""),"ok","-") -> ok | U57: =MOD(K57,1) -> 0 | V57: =MOD(M57,1) -> 0 | W57: =MOD(O57,1) -> 0
A58: =IF(AND(F58<>"",G58<>""),LEFT(E58,5),"") -> 10101 | B58: =IF(AND(F58<>"",G58<>""),LEFT(G58,2),"") -> 60 | C58: =IF(AND(F58<>"",G58<>""),COUNT($C$32:C57)+1,"") -> 22 | D58: =IF(C58<>"","LN"&TEXT(C58,"0000"),"") -> LN0022 | E58: =IF(AND(F58<>"",G58<>""),LEFT(F58,7),"") -> 1010101 | F58: 101010101 | G58: 60021 | H58: គ្រាប់កឹមតូច | I58: Regular | J58: ប្រអប់ | K58: 6 | L58: KHR | M58: 12000 | N58: =IF(AND(F58<>"",G58<>""),K58*M58,"") -> 72000 | O58: 1 | P58: =IF(AND(F58<>"",G58<>""),N58*O58,"") -> 72000 | T58: =IF(AND(F58<>"",G58<>""),"ok","-") -> ok | U58: =MOD(K58,1) -> 0 | V58: =MOD(M58,1) -> 0 | W58: =MOD(O58,1) -> 0
A59: =IF(AND(F59<>"",G59<>""),LEFT(E59,5),"") -> 10101 | B59: =IF(AND(F59<>"",G59<>""),LEFT(G59,2),"") -> 60 | C59: =IF(AND(F59<>"",G59<>""),COUNT($C$32:C58)+1,"") -> 23 | D59: =IF(C59<>"","LN"&TEXT(C59,"0000"),"") -> LN0023 | E59: =IF(AND(F59<>"",G59<>""),LEFT(F59,7),"") -> 1010101 | F59: 101010101 | G59: 60021 | H59: Sticker note 3x3 | I59: Regular | J59: ប្រអប់ | K59: 1 | L59: KHR | M59: 150000 | N59: =IF(AND(F59<>"",G59<>""),K59*M59,"") -> 150000 | O59: 12 | P59: =IF(AND(F59<>"",G59<>""),N59*O59,"") -> 1800000 | T59: =IF(AND(F59<>"",G59<>""),"ok","-") -> ok | U59: =MOD(K59,1) -> 0 | V59: =MOD(M59,1) -> 0 | W59: =MOD(O59,1) -> 0
A60: =IF(AND(F60<>"",G60<>""),LEFT(E60,5),"") -> 10101 | B60: =IF(AND(F60<>"",G60<>""),LEFT(G60,2),"") -> 60 | C60: =IF(AND(F60<>"",G60<>""),COUNT($C$32:C59)+1,"") -> 24 | D60: =IF(C60<>"","LN"&TEXT(C60,"0000"),"") -> LN0024 | E60: =IF(AND(F60<>"",G60<>""),LEFT(F60,7),"") -> 1010101 | F60: 101010101 | G60: 60021 | H60: សឺមី UD ថ្លា | I60: Regular | J60: ប្រអប់ | K60: 1 | L60: KHR | M60: 160000 | N60: =IF(AND(F60<>"",G60<>""),K60*M60,"") -> 160000 | O60: 2 | P60: =IF(AND(F60<>"",G60<>""),N60*O60,"") -> 320000 | T60: =IF(AND(F60<>"",G60<>""),"ok","-") -> ok | U60: =MOD(K60,1) -> 0 | V60: =MOD(M60,1) -> 0 | W60: =MOD(O60,1) -> 0
A61: =IF(AND(F61<>"",G61<>""),LEFT(E61,5),"") -> 10101 | B61: =IF(AND(F61<>"",G61<>""),LEFT(G61,2),"") -> 60 | C61: =IF(AND(F61<>"",G61<>""),COUNT($C$32:C60)+1,"") -> 25 | D61: =IF(C61<>"","LN"&TEXT(C61,"0000"),"") -> LN0025 | E61: =IF(AND(F61<>"",G61<>""),LEFT(F61,7),"") -> 1010101 | F61: 101010101 | G61: 60021 | H61: បង្គ្រប់សីមីUDថ្លា | I61: Regular | J61: ប្រអប់ | K61: 1 | L61: KHR | M61: 100000 | N61: =IF(AND(F61<>"",G61<>""),K61*M61,"") -> 100000 | O61: 1 | P61: =IF(AND(F61<>"",G61<>""),N61*O61,"") -> 100000 | T61: =IF(AND(F61<>"",G61<>""),"ok","-") -> ok | U61: =MOD(K61,1) -> 0 | V61: =MOD(M61,1) -> 0 | W61: =MOD(O61,1) -> 0
... A74: =IF(AND(F74<>"",G74<>""),LEFT(E74,5),"") -> 10101 | B74: =IF(AND(F74<>"",G74<>""),LEFT(G74,2),"") -> 60 | C74: =IF(AND(F74<>"",G74<>""),COUNT($C$32:C73)+1,"") -> 38 | D74: =IF(C74<>"","LN"&TEXT(C74,"0000"),"") -> LN0038 | E74: =IF(AND(F74<>"",G74<>""),LEFT(F74,7),"") -> 1010101 | F74: 101010101 | G74: 60037 | H74: ស្បៀងសម្រាប់រដ្ឋបាល | I74: Regular | J74: ដង | K74: 1 | L74: KHR | M74: 455000 | N74: =IF(AND(F74<>"",G74<>""),K74*M74,"") -> 455000 | O74: 12 | P74: =IF(AND(F74<>"",G74<>""),N74*O74,"") -> 5460000 | T74: =IF(AND(F74<>"",G74<>""),"ok","-") -> ok | U74: =MOD(K74,1) -> 0 | V74: =MOD(M74,1) -> 0 | W74: =MOD(O74,1) -> 0
A75: =IF(AND(F75<>"",G75<>""),LEFT(E75,5),"") -> 10101 | B75: =IF(AND(F75<>"",G75<>""),LEFT(G75,2),"") -> 60 | C75: =IF(AND(F75<>"",G75<>""),COUNT($C$32:C74)+1,"") -> 39 | D75: =IF(C75<>"","LN"&TEXT(C75,"0000"),"") -> LN0039 | E75: =IF(AND(F75<>"",G75<>""),LEFT(F75,7),"") -> 1010101 | F75: 101010101 | G75: 60037 | H75: បង្គ្រប់ស្បៀងសម្រាប់រដ្ឋបាល | I75: Regular | J75: គ្រឿង | K75: 1 | L75: KHR | N75: =IF(AND(F75<>"",G75<>""),K75*M75,"") -> 0 | O75: 1 | P75: =IF(AND(F75<>"",G75<>""),N75*O75,"") -> 0 | T75: =IF(AND(F75<>"",G75<>""),"ok","-") -> ok | U75: =MOD(K75,1) -> 0 | V75: =MOD(M75,1) -> 0 | W75: =MOD(O75,1) -> 0
A76: =IF(AND(F76<>"",G76<>""),LEFT(E76,5),"") -> 10101 | B76: =IF(AND(F76<>"",G76<>""),LEFT(G76,2),"") -> 60 | C76: =IF(AND(F76<>"",G76<>""),COUNT($C$32:C75)+1,"") -> 40 | D76: =IF(C76<>"","LN"&TEXT(C76,"0000"),"") -> LN0040 | E76: =IF(AND(F76<>"",G76<>""),LEFT(F76,7),"") -> 1010101 | F76: 101010101 | G76: 60052 | H76: ទូដាក់ឯកសារនិងសៀវភៅ | I76: Regular | J76: គ្រឿង | K76: 0 | L76: KHR | M76: 1200000 | N76: =IF(AND(F76<>"",G76<>""),K76*M76,"") -> 0 | O76: 1 | P76: =IF(AND(F76<>"",G76<>""),N76*O76,"") -> 0 | T76: =IF(AND(F76<>"",G76<>""),"ok","-") -> ok | U76: =MOD(K76,1) -> 0 | V76: =MOD(M76,1) -> 0 | W76: =MOD(O76,1) -> 0
A77: =IF(AND(F77<>"",G77<>""),LEFT(E77,5),"") -> 10101 | B77: =IF(AND(F77<>"",G77<>""),LEFT(G77,2),"") -> 60 | C77: =IF(AND(F77<>"",G77<>""),COUNT($C$32:C76)+1,"") -> 41 | D77: =IF(C77<>"","LN"&TEXT(C77,"0000"),"") -> LN0041 | E77: =IF(AND(F77<>"",G77<>""),LEFT(F77,7),"") -> 1010101 | F77: 101010101 | G77: 60052 | H77: សាទ្បុង | I77: Regular | J77: គ្រឿង | K77: 0 | L77: KHR | M77: 1000000 | N77: =IF(AND(F77<>"",G77<>""),K77*M77,"") -> 0 | O77: 1 | P77: =IF(AND(F77<>"",G77<>""),N77*O77,"") -> 0 | T77: =IF(AND(F77<>"",G77<>""),"ok","-") -> ok | U77: =MOD(K77,1) -> 0 | V77: =MOD(M77,1) -> 0 | W77: =MOD(O77,1) -> 0
A78: =IF(AND(F78<>"",G78<>""),LEFT(E78,5),"") -> 10101 | B78: =IF(AND(F78<>"",G78<>""),LEFT(G78,2),"") -> 60 | C78: =IF(AND(F78<>"",G78<>""),COUNT($C$32:C77)+1,"") -> 42 | D78: =IF(C78<>"","LN"&TEXT(C78,"0000"),"") -> LN0042 | E78: =IF(AND(F78<>"",G78<>""),LEFT(F78,7),"") -> 1010101 | F78: 101010101 | G78: 60055 | H78: កុំព្យូទ័រយួរដៃ | I78: Regular | J78: គ្រឿង | K78: 0 | L78: KHR | M78: 7800000 | N78: =IF(AND(F78<>"",G78<>""),K78*M78,"") -> 0 | O78: 1 | P78: =IF(AND(F78<>"",G78<>""),N78*O78,"") -> 0 | T78: =IF(AND(F78<>"",G78<>""),"ok","-") -> ok | U78: =MOD(K78,1) -> 0 | V78: =MOD(M78,1) -> 0 | W78: =MOD(O78,1) -> 0
A79: =IF(AND(F79<>"",G79<>""),LEFT(E79,5),"") -> 10101 | B79: =IF(AND(F79<>"",G79<>""),LEFT(G79,2),"") -> 61 | C79: =IF(AND(F79<>"",G79<>""),COUNT($C$32:C78)+1,"") -> 43 | D79: =IF(C79<>"","LN"&TEXT(C79,"0000"),"") -> LN0043 | E79: =IF(AND(F79<>"",G79<>""),LEFT(F79,7),"") -> 1010101 | F79: 101010101 | G79: 61056 | H79: ជួសជុលឡាន | I79: Regular | J79: គ្រឿង | K79: 3 | L79: KHR | M79: 2766666 | N79: =IF(AND(F79<>"",G79<>""),K79*M79,"") -> 8299998 | O79: 2 | P79: =IF(AND(F79<>"",G79<>""),N79*O79,"") -> 16599996 | T79: =IF(AND(F79<>"",G79<>""),"ok","-") -> ok | U79: =MOD(K79,1) -> 0 | V79: =MOD(M79,1) -> 0 | W79: =MOD(O79,1) -> 0
A80: =IF(AND(F80<>"",G80<>""),LEFT(E80,5),"") -> 10101 | B80: =IF(AND(F80<>"",G80<>""),LEFT(G80,2),"") -> 61 | C80: =IF(AND(F80<>"",G80<>""),COUNT($C$32:C79)+1,"") -> 44 | D80: =IF(C80<>"","LN"&TEXT(C80,"0000"),"") -> LN0044 | E80: =IF(AND(F80<>"",G80<>""),LEFT(F80,7),"") -> 1010101 | F80: 101010101 | G80: 61056 | H80: បង្គ្រប់ជួសជុលឡាន | I80: Regular | J80: គ្រឿង | K80: 1 | L80: KHR | M80: 100004 | N80: =IF(AND(F80<>"",G80<>""),K80*M80,"") -> 100004 | O80: 1 | P80: =IF(AND(F80<>"",G80<>""),N80*O80,"") -> 100004 | T80: =IF(AND(F80<>"",G80<>""),"ok","-") -> ok | U80: =MOD(K80,1) -> 0 | V80: =MOD(M80,1) -> 0 | W80: =MOD(O80,1) -> 0
A81: =IF(AND(F81<>"",G81<>""),LEFT(E81,5),"") -> 10101 | B81: =IF(AND(F81<>"",G81<>""),LEFT(G81,2),"") -> 60 | C81: =IF(AND(F81<>"",G81<>""),COUNT($C$32:C80)+1,"") -> 45 | D81: =IF(C81<>"","LN"&TEXT(C81,"0000"),"") -> LN0045 | E81: =IF(AND(F81<>"",G81<>""),LEFT(F81,7),"") -> 1010101 | F81: 101010101 | G81: 60015 | H81: បង្គ្រប់ប្រេងឥន្ធនៈ និងប្រេងរំអិល | I81: Regular | J81: លីត្រ | K81: 1 | L81: KHR | M81: 24000 | N81: =IF(AND(F81<>"",G81<>""),K81*M81,"") -> 24000 | O81: 1 | P81: =IF(AND(F81<>"",G81<>""),N81*O81,"") -> 24000 | T81: =IF(AND(F81<>"",G81<>""),"ok","-") -> ok | U81: =MOD(K81,1) -> 0 | V81: =MOD(M81,1) -> 0 | W81: =MOD(O81,1) -> 0
A82: =IF(AND(F82<>"",G82<>""),LEFT(E82,5),"") -> 10101 | B82: =IF(AND(F82<>"",G82<>""),LEFT(G82,2),"") -> 61 | C82: =IF(AND(F82<>"",G82<>""),COUNT($C$32:C81)+1,"") -> 46 | D82: =IF(C82<>"","LN"&TEXT(C82,"0000"),"") -> LN0046 | E82: =IF(AND(F82<>"",G82<>""),LEFT(F82,7),"") -> 1010101 | F82: 101010101 | G82: 61057 | H82: សេវាថែទំា និងជួសជុល ម៉ាស៊ីនហ្វូតូកូពី ព្រីនធើ | I82: Regular | J82: គ្រឿង | K82: 1 | L82: KHR | M82: 126404 | N82: =IF(AND(F82<>"",G82<>""),K82*M82,"") -> 126404 | O82: 1 | P82: =IF(AND(F82<>"",G82<>""),N82*O82,"") -> 126404 | T82: =IF(AND(F82<>"",G82<>""),"ok","-") -> ok | U82: =MOD(K82,1) -> 0 | V82: =MOD(M82,1) -> 0 | W82: =MOD(O82,1) -> 0
A83: =IF(AND(F83<>"",G83<>""),LEFT(E83,5),"") | B83: =IF(AND(F83<>"",G83<>""),LEFT(G83,2),"") | C83: =IF(AND(F83<>"",G83<>""),COUNT($C$32:C82)+1,"") | D83: =IF(C83<>"","LN"&TEXT(C83,"0000"),"") | E83: =IF(AND(F83<>"",G83<>""),LEFT(F83,7),"") | H83: ៣.កិច្ចប្រជុំ​លេខាធិការដ្ឋានគណៈកម្មាធិការត្រួតពិនិត្យ និងវាយតម្លៃចំណូលសារពើពន្ធ | P83: =SUM(P84:P87) -> 337500 | T83: =IF(AND(F83<>"",G83<>""),"ok","-") -> - | U83: =MOD(K83,1) -> 0 | V83: =MOD(M83,1) -> 0 | W83: =MOD(O83,1) -> 0
A84: =IF(AND(F84<>"",G84<>""),LEFT(E84,5),"") -> 10101 | B84: =IF(AND(F84<>"",G84<>""),LEFT(G84,2),"") -> 61 | C84: =IF(AND(F84<>"",G84<>""),COUNT($C$32:C83)+1,"") -> 47 | D84: =IF(C84<>"","LN"&TEXT(C84,"0000"),"") -> LN0047 | E84: =IF(AND(F84<>"",G84<>""),LEFT(F84,7),"") -> 1010101 | F84: 101010101 | G84: 61103 | H84: ក្រណូដាក់ឯកសារ | I84: Regular | J84: រាយ | K84: 15 | L84: KHR | M84: 15000 | N84: =IF(AND(F84<>"",G84<>""),K84*M84,"") -> 225000 | O84: 1 | P84: =IF(AND(F84<>"",G84<>""),N84*O84,"") -> 225000 | T84: =IF(AND(F84<>"",G84<>""),"ok","-") -> ok | U84: =MOD(K84,1) -> 0 | V84: =MOD(M84,1) -> 0 | W84: =MOD(O84,1) -> 0
A85: =IF(AND(F85<>"",G85<>""),LEFT(E85,5),"") -> 10101 | B85: =IF(AND(F85<>"",G85<>""),LEFT(G85,2),"") -> 61 | C85: =IF(AND(F85<>"",G85<>""),COUNT($C$32:C84)+1,"") -> 48 | D85: =IF(C85<>"","LN"&TEXT(C85,"0000"),"") -> LN0048 | E85: =IF(AND(F85<>"",G85<>""),LEFT(F85,7),"") -> 1010101 | F85: 101010101 | G85: 61103 | H85: សៀវភៅកត់ត្រា | I85: Regular | J85: ក្បាល | K85: 15 | L85: KHR | M85: 2800 | N85: =IF(AND(F85<>"",G85<>""),K85*M85,"") -> 42000 | O85: 1 | P85: =IF(AND(F85<>"",G85<>""),N85*O85,"") -> 42000 | T85: =IF(AND(F85<>"",G85<>""),"ok","-") -> ok | U85: =MOD(K85,1) -> 0 | V85: =MOD(M85,1) -> 0 | W85: =MOD(O85,1) -> 0
A86: =IF(AND(F86<>"",G86<>""),LEFT(E86,5),"") -> 10101 | B86: =IF(AND(F86<>"",G86<>""),LEFT(G86,2),"") -> 61 | C86: =IF(AND(F86<>"",G86<>""),COUNT($C$32:C85)+1,"") -> 49 | D86: =IF(C86<>"","LN"&TEXT(C86,"0000"),"") -> LN0049 | E86: =IF(AND(F86<>"",G86<>""),LEFT(F86,7),"") -> 1010101 | F86: 101010101 | G86: 61103 | H86: ប៊ិចសរសេរ | I86: Regular | J86: ដើម | K86: 15 | L86: KHR | M86: 700 | N86: =IF(AND(F86<>"",G86<>""),K86*M86,"") -> 10500 | O86: 1 | P86: =IF(AND(F86<>"",G86<>""),N86*O86,"") -> 10500 | T86: =IF(AND(F86<>"",G86<>""),"ok","-") -> ok | U86: =MOD(K86,1) -> 0 | V86: =MOD(M86,1) -> 0 | W86: =MOD(O86,1) -> 0
A87: =IF(AND(F87<>"",G87<>""),LEFT(E87,5),"") -> 10101 | B87: =IF(AND(F87<>"",G87<>""),LEFT(G87,2),"") -> 61 | C87: =IF(AND(F87<>"",G87<>""),COUNT($C$32:C86)+1,"") -> 50 | D87: =IF(C87<>"","LN"&TEXT(C87,"0000"),"") -> LN0050 | E87: =IF(AND(F87<>"",G87<>""),LEFT(F87,7),"") -> 1010101 | F87: 101010101 | G87: 61103 | H87: ថតចម្លងឯកសារ | I87: Regular | J87: ច្បាប់ | K87: 15 | L87: KHR | M87: 4000 | N87: =IF(AND(F87<>"",G87<>""),K87*M87,"") -> 60000 | O87: 1 | P87: =IF(AND(F87<>"",G87<>""),N87*O87,"") -> 60000 | T87: =IF(AND(F87<>"",G87<>""),"ok","-") -> ok | U87: =MOD(K87,1) -> 0 | V87: =MOD(M87,1) -> 0 | W87: =MOD(O87,1) -> 0
A88: =IF(AND(F88<>"",G88<>""),LEFT(E88,5),"") | B88: =IF(AND(F88<>"",G88<>""),LEFT(G88,2),"") | C88: =IF(AND(F88<>"",G88<>""),COUNT($C$32:C87)+1,"") | D88: =IF(C88<>"","LN"&TEXT(C88,"0000"),"") | E88: =IF(AND(F88<>"",G88<>""),LEFT(F88,7),"") | H88: ៤.កិច្ចប្រជុំលេខាធិការដ្ឋានគណៈកម្មាធិការត្រួតពិនិត្យ និងវាយតម្លៃចំណូលមិនមែនសារពើពន្ធ | P88: =SUM(P89:P92) -> 337500 | T88: =IF(AND(F88<>"",G88<>""),"ok","-") -> - | U88: =MOD(K88,1) -> 0 | V88: =MOD(M88,1) -> 0 | W88: =MOD(O88,1) -> 0
A89: =IF(AND(F89<>"",G89<>""),LEFT(E89,5),"") -> 10101 | B89: =IF(AND(F89<>"",G89<>""),LEFT(G89,2),"") -> 61 | C89: =IF(AND(F89<>"",G89<>""),COUNT($C$32:C88)+1,"") -> 51 | D89: =IF(C89<>"","LN"&TEXT(C89,"0000"),"") -> LN0051 | E89: =IF(AND(F89<>"",G89<>""),LEFT(F89,7),"") -> 1010101 | F89: 101010101 | G89: 61103 | H89: ក្រណូដាក់ឯកសារ | I89: Regular | J89: រាយ | K89: 15 | L89: KHR | M89: 15000 | N89: =IF(AND(F89<>"",G89<>""),K89*M89,"") -> 225000 | O89: 1 | P89: =IF(AND(F89<>"",G89<>""),N89*O89,"") -> 225000 | T89: =IF(AND(F89<>"",G89<>""),"ok","-") -> ok | U89: =MOD(K89,1) -> 0 | V89: =MOD(M89,1) -> 0 | W89: =MOD(O89,1) -> 0
A90: =IF(AND(F90<>"",G90<>""),LEFT(E90,5),"") -> 10101 | B90: =IF(AND(F90<>"",G90<>""),LEFT(G90,2),"") -> 61 | C90: =IF(AND(F90<>"",G90<>""),COUNT($C$32:C89)+1,"") -> 52 | D90: =IF(C90<>"","LN"&TEXT(C90,"0000"),"") -> LN0052 | E90: =IF(AND(F90<>"",G90<>""),LEFT(F90,7),"") -> 1010101 | F90: 101010101 | G90: 61103 | H90: សៀវភៅកត់ត្រា | I90: Regular | J90: ក្បាល | K90: 15 | L90: KHR | M90: 2800 | N90: =IF(AND(F90<>"",G90<>""),K90*M90,"") -> 42000 | O90: 1 | P90: =IF(AND(F90<>"",G90<>""),N90*O90,"") -> 42000 | T90: =IF(AND(F90<>"",G90<>""),"ok","-") -> ok | U90: =MOD(K90,1) -> 0 | V90: =MOD(M90,1) -> 0 | W90: =MOD(O90,1) -> 0
A91: =IF(AND(F91<>"",G91<>""),LEFT(E91,5),"") -> 10101 | B91: =IF(AND(F91<>"",G91<>""),LEFT(G91,2),"") -> 61 | C91: =IF(AND(F91<>"",G91<>""),COUNT($C$32:C90)+1,"") -> 53 | D91: =IF(C91<>"","LN"&TEXT(C91,"0000"),"") -> LN0053 | E91: =IF(AND(F91<>"",G91<>""),LEFT(F91,7),"") -> 1010101 | F91: 101010101 | G91: 61103 | H91: ប៊ិចសរសេរ | I91: Regular | J91: ដើម | K91: 15 | L91: KHR | M91: 700 | N91: =IF(AND(F91<>"",G91<>""),K91*M91,"") -> 10500 | O91: 1 | P91: =IF(AND(F91<>"",G91<>""),N91*O91,"") -> 10500 | T91: =IF(AND(F91<>"",G91<>""),"ok","-") -> ok | U91: =MOD(K91,1) -> 0 | V91: =MOD(M91,1) -> 0 | W91: =MOD(O91,1) -> 0
A92: =IF(AND(F92<>"",G92<>""),LEFT(E92,5),"") -> 10101 | B92: =IF(AND(F92<>"",G92<>""),LEFT(G92,2),"") -> 61 | C92: =IF(AND(F92<>"",G92<>""),COUNT($C$32:C91)+1,"") -> 54 | D92: =IF(C92<>"","LN"&TEXT(C92,"0000"),"") -> LN0054 | E92: =IF(AND(F92<>"",G92<>""),LEFT(F92,7),"") -> 1010101 | F92: 101010101 | G92: 61103 | H92: ថតចម្លងឯកសារ | I92: Regular | J92: ច្បាប់ | K92: 15 | L92: KHR | M92: 4000 | N92: =IF(AND(F92<>"",G92<>""),K92*M92,"") -> 60000 | O92: 1 | P92: =IF(AND(F92<>"",G92<>""),N92*O92,"") -> 60000 | T92: =IF(AND(F92<>"",G92<>""),"ok","-") -> ok | U92: =MOD(K92,1) -> 0 | V92: =MOD(M92,1) -> 0 | W92: =MOD(O92,1) -> 0
A93: =IF(AND(F93<>"",G93<>""),LEFT(E93,5),"") | B93: =IF(AND(F93<>"",G93<>""),LEFT(G93,2),"") | C93: =IF(AND(F93<>"",G93<>""),COUNT($C$32:C92)+1,"") | D93: =IF(C93<>"","LN"&TEXT(C93,"0000"),"") | E93: =IF(AND(F93<>"",G93<>""),LEFT(F93,7),"") | H93: ៥.កិច្ចប្រជុំលេខាធិការដ្ឋានគណៈកម្មាធិការគោលនយោបាយសារពើពន្ធ | P93: =SUM(P94:P98) -> 325000 | T93: =IF(AND(F93<>"",G93<>""),"ok","-") -> - | U93: =MOD(K93,1) -> 0 | V93: =MOD(M93,1) -> 0 | W93: =MOD(O93,1) -> 0
A94: =IF(AND(F94<>"",G94<>""),LEFT(E94,5),"") -> 10101 | B94: =IF(AND(F94<>"",G94<>""),LEFT(G94,2),"") -> 61 | C94: =IF(AND(F94<>"",G94<>""),COUNT($C$32:C93)+1,"") -> 55 | D94: =IF(C94<>"","LN"&TEXT(C94,"0000"),"") -> LN0055 | E94: =IF(AND(F94<>"",G94<>""),LEFT(F94,7),"") -> 1010101 | F94: 101010101 | G94: 61103 | H94: ក្រណូដាក់ឯកសារ | I94: Regular | J94: រាយ | K94: 15 | L94: KHR | M94: 15000 | N94: =IF(AND(F94<>"",G94<>""),K94*M94,"") -> 225000 | O94: 1 | P94: =IF(AND(F94<>"",G94<>""),N94*O94,"") -> 225000 | T94: =IF(AND(F94<>"",G94<>""),"ok","-") -> ok | U94: =MOD(K94,1) -> 0 | V94: =MOD(M94,1) -> 0 | W94: =MOD(O94,1) -> 0
A95: =IF(AND(F95<>"",G95<>""),LEFT(E95,5),"") -> 10101 | B95: =IF(AND(F95<>"",G95<>""),LEFT(G95,2),"") -> 61 | C95: =IF(AND(F95<>"",G95<>""),COUNT($C$32:C94)+1,"") -> 56 | D95: =IF(C95<>"","LN"&TEXT(C95,"0000"),"") -> LN0056 | E95: =IF(AND(F95<>"",G95<>""),LEFT(F95,7),"") -> 1010101 | F95: 101010101 | G95: 61103 | H95: សៀវភៅកត់ត្រា | I95: Regular | J95: ក្បាល | K95: 15 | L95: KHR | M95: 2800 | N95: =IF(AND(F95<>"",G95<>""),K95*M95,"") -> 42000 | O95: 1 | P95: =IF(AND(F95<>"",G95<>""),N95*O95,"") -> 42000 | T95: =IF(AND(F95<>"",G95<>""),"ok","-") -> ok | U95: =MOD(K95,1) -> 0 | V95: =MOD(M95,1) -> 0 | W95: =MOD(O95,1) -> 0
A96: =IF(AND(F96<>"",G96<>""),LEFT(E96,5),"") -> 10101 | B96: =IF(AND(F96<>"",G96<>""),LEFT(G96,2),"") -> 61 | C96: =IF(AND(F96<>"",G96<>""),COUNT($C$32:C95)+1,"") -> 57 | D96: =IF(C96<>"","LN"&TEXT(C96,"0000"),"") -> LN0057 | E96: =IF(AND(F96<>"",G96<>""),LEFT(F96,7),"") -> 1010101 | F96: 101010101 | G96: 61103 | H96: ប៊ិចសរសេរ | I96: Regular | J96: ដើម | K96: 15 | L96: KHR | M96: 700 | N96: =IF(AND(F96<>"",G96<>""),K96*M96,"") -> 10500 | O96: 1 | P96: =IF(AND(F96<>"",G96<>""),N96*O96,"") -> 10500 | T96: =IF(AND(F96<>"",G96<>""),"ok","-") -> ok | U96: =MOD(K96,1) -> 0 | V96: =MOD(M96,1) -> 0 | W96: =MOD(O96,1) -> 0
A97: =IF(AND(F97<>"",G97<>""),LEFT(E97,5),"") -> 10101 | B97: =IF(AND(F97<>"",G97<>""),LEFT(G97,2),"") -> 61 | C97: =IF(AND(F97<>"",G97<>""),COUNT($C$32:C96)+1,"") -> 58 | D97: =IF(C97<>"","LN"&TEXT(C97,"0000"),"") -> LN0058 | E97: =IF(AND(F97<>"",G97<>""),LEFT(F97,7),"") -> 1010101 | F97: 101010101 | G97: 61103 | H97: ថតចម្លងឯកសារ | I97: Regular | J97: ច្បាប់ | K97: 11 | L97: KHR | M97: 4000 | N97: =IF(AND(F97<>"",G97<>""),K97*M97,"") -> 44000 | O97: 1 | P97: =IF(AND(F97<>"",G97<>""),N97*O97,"") -> 44000 | T97: =IF(AND(F97<>"",G97<>""),"ok","-") -> ok | U97: =MOD(K97,1) -> 0 | V97: =MOD(M97,1) -> 0 | W97: =MOD(O97,1) -> 0
A98: =IF(AND(F98<>"",G98<>""),LEFT(E98,5),"") -> 10101 | B98: =IF(AND(F98<>"",G98<>""),LEFT(G98,2),"") -> 61 | C98: =IF(AND(F98<>"",G98<>""),COUNT($C$32:C97)+1,"") -> 59 | D98: =IF(C98<>"","LN"&TEXT(C98,"0000"),"") -> LN0059 | E98: =IF(AND(F98<>"",G98<>""),LEFT(F98,7),"") -> 1010101 | F98: 101010101 | G98: 61103 | H98: បង្គ្រប់ថតចម្លងឯកសារ | I98: Regular | J98: ច្បាប់ | K98: 1 | L98: KHR | M98: 3500 | N98: =IF(AND(F98<>"",G98<>""),K98*M98,"") -> 3500 | O98: 1 | P98: =IF(AND(F98<>"",G98<>""),N98*O98,"") -> 3500 | T98: =IF(AND(F98<>"",G98<>""),"ok","-") -> ok | U98: =MOD(K98,1) -> 0 | V98: =MOD(M98,1) -> 0 | W98: =MOD(O98,1) -> 0
A99: =IF(AND(F99<>"",G99<>""),LEFT(E99,5),"") | B99: =IF(AND(F99<>"",G99<>""),LEFT(G99,2),"") | C99: =IF(AND(F99<>"",G99<>""),COUNT($C$32:C98)+1,"") | D99: =IF(C99<>"","LN"&TEXT(C99,"0000"),"") | E99: =IF(AND(F99<>"",G99<>""),LEFT(F99,7),"") | F99: 101010102 | H99: សកម្មភាពទី២ នៃចង្កោមសកម្មភាពទី១៖ ចូលរួមកិច្ចប្រជុំផ្សេងៗ ក្នុង និងក្រៅប្រទេសរបស់ឯកឧត្តមអគ្គនាយក និងអគ្គនាយករង២រូប | P99: =SUMIF($F100:$F$1454,F99,$P100:$P$1454) -> 26000000 | T99: =IF(AND(F99<>"",G99<>""),"ok","-") -> - | U99: =MOD(K99,1) -> 0 | V99: =MOD(M99,1) -> 0 | W99: =MOD(O99,1) -> 0
A100: =IF(AND(F100<>"",G100<>""),LEFT(E100,5),"") | B100: =IF(AND(F100<>"",G100<>""),LEFT(G100,2),"") | C100: =IF(AND(F100<>"",G100<>""),COUNT($C$32:C99)+1,"") | D100: =IF(C100<>"","LN"&TEXT(C100,"0000"),"") | E100: =IF(AND(F100<>"",G100<>""),LEFT(F100,7),"") | H100: ១.បេសកកម្មក្នុងប្រទេសរបស់ឯកឧត្តមអគ្គនាយក និង​​អគ្គនាយករង២រូប and DG team | N100: =IF(AND(F100<>"",G100<>""),K100*M100,"") | P100: =SUM(P101:P107) -> 26000000 | T100: =IF(AND(F100<>"",G100<>""),"ok","-") -> - | U100: =MOD(K100,1) -> 0 | V100: =MOD(M100,1) -> 0 | W100: =MOD(O100,1) -> 0
A101: =IF(AND(F101<>"",G101<>""),LEFT(E101,5),"") -> 10101 | B101: =IF(AND(F101<>"",G101<>""),LEFT(G101,2),"") -> 61 | C101: =IF(AND(F101<>"",G101<>""),COUNT($C$32:C100)+1,"") -> 60 | D101: =IF(C101<>"","LN"&TEXT(C101,"0000"),"") -> LN0060 | E101: =IF(AND(F101<>"",G101<>""),LEFT(F101,7),"") -> 1010101 | F101: 101010102 | G101: 61122 | H101: ប្រាក់ហោប៉ៅ | I101: Regular | J101: នាក់ | K101: 6 | L101: KHR | M101: 300000 | N101: =IF(AND(F101<>"",G101<>""),K101*M101,"") -> 1800000 | O101: 2 | P101: =IF(AND(F101<>"",G101<>""),N101*O101,"") -> 3600000 | T101: =IF(AND(F101<>"",G101<>""),"ok","-") -> ok | U101: =MOD(K101,1) -> 0 | V101: =MOD(M101,1) -> 0 | W101: =MOD(O101,1) -> 0
A102: =IF(AND(F102<>"",G102<>""),LEFT(E102,5),"") -> 10101 | B102: =IF(AND(F102<>"",G102<>""),LEFT(G102,2),"") -> 61 | C102: =IF(AND(F102<>"",G102<>""),COUNT($C$32:C101)+1,"") -> 61 | D102: =IF(C102<>"","LN"&TEXT(C102,"0000"),"") -> LN0061 | E102: =IF(AND(F102<>"",G102<>""),LEFT(F102,7),"") -> 1010101 | F102: 101010102 | G102: 61122 | H102: បង្គ្រប់ប្រាក់ហោប៉ៅ | I102: Regular | J102: នាក់ | K102: 1 | L102: KHR | M102: =300000+100000 -> 400000 | N102: =IF(AND(F102<>"",G102<>""),K102*M102,"") -> 400000 | O102: 1 | P102: =IF(AND(F102<>"",G102<>""),N102*O102,"") -> 400000 | T102: =IF(AND(F102<>"",G102<>""),"ok","-") -> ok | U102: =MOD(K102,1) -> 0 | V102: =MOD(M102,1) -> 0 | W102: =MOD(O102,1) -> 0
A103: =IF(AND(F103<>"",G103<>""),LEFT(E103,5),"") -> 10101 | B103: =IF(AND(F103<>"",G103<>""),LEFT(G103,2),"") -> 61 | C103: =IF(AND(F103<>"",G103<>""),COUNT($C$32:C102)+1,"") -> 62 | D103: =IF(C103<>"","LN"&TEXT(C103,"0000"),"") -> LN0062 | E103: =IF(AND(F103<>"",G103<>""),LEFT(F103,7),"") -> 1010101 | F103: 101010102 | G103: 61121 | H103: សោហ៊ុយធ្វើដំណើរ (ទៅមក) | I103: Regular | J103: នាក់ | K103: 6 | L103: KHR | M103: 200000 | N103: =IF(AND(F103<>"",G103<>""),K103*M103,"") -> 1200000 | O103: 2 | P103: =IF(AND(F103<>"",G103<>""),N103*O103,"") -> 2400000 | T103: =IF(AND(F103<>"",G103<>""),"ok","-") -> ok | U103: =MOD(K103,1) -> 0 | V103: =MOD(M103,1) -> 0 | W103: =MOD(O103,1) -> 0
A104: =IF(AND(F104<>"",G104<>""),LEFT(E104,5),"") -> 10101 | B104: =IF(AND(F104<>"",G104<>""),LEFT(G104,2),"") -> 61 | C104: =IF(AND(F104<>"",G104<>""),COUNT($C$32:C103)+1,"") -> 63 | D104: =IF(C104<>"","LN"&TEXT(C104,"0000"),"") -> LN0063 | E104: =IF(AND(F104<>"",G104<>""),LEFT(F104,7),"") -> 1010101 | F104: 101010102 | G104: 61121 | H104: បង្គ្រប់សោហ៊ុយធ្វើដំណើរ (ទៅមក) | I104: Regular | J104: នាក់ | K104: 1 | L104: KHR | M104: =300000+300000 -> 600000 | N104: =IF(AND(F104<>"",G104<>""),K104*M104,"") -> 600000 | O104: 1 | P104: =IF(AND(F104<>"",G104<>""),N104*O104,"") -> 600000 | T104: =IF(AND(F104<>"",G104<>""),"ok","-") -> ok | U104: =MOD(K104,1) -> 0 | V104: =MOD(M104,1) -> 0 | W104: =MOD(O104,1) -> 0
A105: =IF(AND(F105<>"",G105<>""),LEFT(E105,5),"") -> 10101 | B105: =IF(AND(F105<>"",G105<>""),LEFT(G105,2),"") -> 61 | C105: =IF(AND(F105<>"",G105<>""),COUNT($C$32:C104)+1,"") -> 64 | D105: =IF(C105<>"","LN"&TEXT(C105,"0000"),"") -> LN0064 | E105: =IF(AND(F105<>"",G105<>""),LEFT(F105,7),"") -> 1010101 | F105: 101010102 | G105: 61123 | H105: ប្រាក់ស្នាក់នៅ | I105: Regular | J105: នាក់ | K105: 6 | L105: KHR | M105: 1500000 | N105: =IF(AND(F105<>"",G105<>""),K105*M105,"") -> 9000000 | O105: 2 | P105: =IF(AND(F105<>"",G105<>""),N105*O105,"") -> 18000000 | T105: =IF(AND(F105<>"",G105<>""),"ok","-") -> ok | U105: =MOD(K105,1) -> 0 | V105: =MOD(M105,1) -> 0 | W105: =MOD(O105,1) -> 0
A106: =IF(AND(F106<>"",G106<>""),LEFT(E106,5),"") -> 10101 | B106: =IF(AND(F106<>"",G106<>""),LEFT(G106,2),"") -> 61 | C106: =IF(AND(F106<>"",G106<>""),COUNT($C$32:C105)+1,"") -> 65 | D106: =IF(C106<>"","LN"&TEXT(C106,"0000"),"") -> LN0065 | E106: =IF(AND(F106<>"",G106<>""),LEFT(F106,7),"") -> 1010101 | F106: 101010102 | G106: 61123 | H106: បង្គ្រប់ប្រាក់ស្នាក់នៅ | I106: Regular | J106: នាក់ | K106: 1 | L106: KHR | M106: =400000+600000 -> 1000000 | N106: =IF(AND(F106<>"",G106<>""),K106*M106,"") -> 1000000 | O106: 1 | P106: =IF(AND(F106<>"",G106<>""),N106*O106,"") -> 1000000 | T106: =IF(AND(F106<>"",G106<>""),"ok","-") -> ok | U106: =MOD(K106,1) -> 0 | V106: =MOD(M106,1) -> 0 | W106: =MOD(O106,1) -> 0
A107: =IF(AND(F107<>"",G107<>""),LEFT(E107,5),"") -> 10101 | B107: =IF(AND(F107<>"",G107<>""),LEFT(G107,2),"") -> 61 | C107: =IF(AND(F107<>"",G107<>""),COUNT($C$32:C106)+1,"") -> 66 | D107: =IF(C107<>"","LN"&TEXT(C107,"0000"),"") -> LN0066 | E107: =IF(AND(F107<>"",G107<>""),LEFT(F107,7),"") -> 1010101 | F107: 101010102 | G107: 61128 | H107: ចំណាយទូទាត់សោហ៊ុយក្នុងប្រទេសផ្សេងៗ | I107: Regular | J107: នាក់ | K107: 0 | L107: KHR | M107: 200000 | N107: =IF(AND(F107<>"",G107<>""),K107*M107,"") -> 0 | O107: 0 | P107: =IF(AND(F107<>"",G107<>""),N107*O107,"") -> 0 | T107: =IF(AND(F107<>"",G107<>""),"ok","-") -> ok | U107: =MOD(K107,1) -> 0 | V107: =MOD(M107,1) -> 0 | W107: =MOD(O107,1) -> 0
A108: =IF(AND(F108<>"",G108<>""),LEFT(E108,5),"") | B108: =IF(AND(F108<>"",G108<>""),LEFT(G108,2),"") | C108: =IF(AND(F108<>"",G108<>""),COUNT($C$32:C107)+1,"") | D108: =IF(C108<>"","LN"&TEXT(C108,"0000"),"") | E108: =IF(AND(F108<>"",G108<>""),LEFT(F108,7),"") | H108: ២.ធ្វើបេសកកម្មក្រៅស្រុករបស់ឯកឧត្តមអគ្គនាយក និង​​អគ្គនាយករង១រូប | P108: =SUM(P109:P112) -> 0 | T108: =IF(AND(F108<>"",G108<>""),"ok","-") -> - | U108: =MOD(K108,1) -> 0 | V108: =MOD(M108,1) -> 0 | W108: =MOD(O108,1) -> 0
A109: =IF(AND(F109<>"",G109<>""),LEFT(E109,5),"") -> 10101 | B109: =IF(AND(F109<>"",G109<>""),LEFT(G109,2),"") -> 61 | C109: =IF(AND(F109<>"",G109<>""),COUNT($C$32:C108)+1,"") -> 67 | D109: =IF(C109<>"","LN"&TEXT(C109,"0000"),"") -> LN0067 | E109: =IF(AND(F109<>"",G109<>""),LEFT(F109,7),"") -> 1010101 | F109: 101010102 | G109: 61131 | H109: សោហ៊ុយដឹកជញ្ជូន | I109: Regular | J109: នាក់ | L109: KHR | M109: 5000000 | N109: =IF(AND(F109<>"",G109<>""),K109*M109,"") -> 0 | O109: 2 | P109: =IF(AND(F109<>"",G109<>""),N109*O109,"") -> 0 | T109: =IF(AND(F109<>"",G109<>""),"ok","-") -> ok | U109: =MOD(K109,1) -> 0 | V109: =MOD(M109,1) -> 0 | W109: =MOD(O109,1) -> 0
A110: =IF(AND(F110<>"",G110<>""),LEFT(E110,5),"") -> 10101 | B110: =IF(AND(F110<>"",G110<>""),LEFT(G110,2),"") -> 61 | C110: =IF(AND(F110<>"",G110<>""),COUNT($C$32:C109)+1,"") -> 68 | D110: =IF(C110<>"","LN"&TEXT(C110,"0000"),"") -> LN0068 | E110: =IF(AND(F110<>"",G110<>""),LEFT(F110,7),"") -> 1010101 | F110: 101010102 | G110: 61132 | H110: សោហ៊ុយបេសកកម្ម | I110: Regular | J110: នាក់ | L110: KHR | M110: 1000000 | N110: =IF(AND(F110<>"",G110<>""),K110*M110,"") -> 0 | O110: 2 | P110: =IF(AND(F110<>"",G110<>""),N110*O110,"") -> 0 | T110: =IF(AND(F110<>"",G110<>""),"ok","-") -> ok | U110: =MOD(K110,1) -> 0 | V110: =MOD(M110,1) -> 0 | W110: =MOD(O110,1) -> 0
A111: =IF(AND(F111<>"",G111<>""),LEFT(E111,5),"") -> 10101 | B111: =IF(AND(F111<>"",G111<>""),LEFT(G111,2),"") -> 61 | C111: =IF(AND(F111<>"",G111<>""),COUNT($C$32:C110)+1,"") -> 69 | D111: =IF(C111<>"","LN"&TEXT(C111,"0000"),"") -> LN0069 | E111: =IF(AND(F111<>"",G111<>""),LEFT(F111,7),"") -> 1010101 | F111: 101010102 | G111: 61133 | H111: សោហ៊ុយស្នាក់នៅ | I111: Regular | J111: នាក់ | L111: KHR | M111: 7800000 | N111: =IF(AND(F111<>"",G111<>""),K111*M111,"") -> 0 | O111: 2 | P111: =IF(AND(F111<>"",G111<>""),N111*O111,"") -> 0 | T111: =IF(AND(F111<>"",G111<>""),"ok","-") -> ok | U111: =MOD(K111,1) -> 0 | V111: =MOD(M111,1) -> 0 | W111: =MOD(O111,1) -> 0
A112: =IF(AND(F112<>"",G112<>""),LEFT(E112,5),"") -> 10101 | B112: =IF(AND(F112<>"",G112<>""),LEFT(G112,2),"") -> 61 | C112: =IF(AND(F112<>"",G112<>""),COUNT($C$32:C111)+1,"") -> 70 | D112: =IF(C112<>"","LN"&TEXT(C112,"0000"),"") -> LN0070 | E112: =IF(AND(F112<>"",G112<>""),LEFT(F112,7),"") -> 1010101 | F112: 101010102 | G112: 61138 | H112: ចំណាយទូទាត់សោហ៊ុយក្នុងប្រទេសផ្សេងៗ | I112: Regular | J112: នាក់ | K112: 0 | L112: KHR | M112: 200000 | N112: =IF(AND(F112<>"",G112<>""),K112*M112,"") -> 0 | O112: 0 | P112: =IF(AND(F112<>"",G112<>""),N112*O112,"") -> 0 | T112: =IF(AND(F112<>"",G112<>""),"ok","-") -> ok | U112: =MOD(K112,1) -> 0 | V112: =MOD(M112,1) -> 0 | W112: =MOD(O112,1) -> 0
A113: =IF(AND(F113<>"",G113<>""),LEFT(E113,5),"") | B113: =IF(AND(F113<>"",G113<>""),LEFT(G113,2),"") | C113: =IF(AND(F113<>"",G113<>""),COUNT($C$32:C112)+1,"") | D113: =IF(C113<>"","LN"&TEXT(C113,"0000"),"") | E113: =IF(AND(F113<>"",G113<>""),LEFT(F113,7),"") | F113: 1010102 | H113: ចង្កោមសកម្មភាពទី២៖ រៀបចំ កែលម្អ ត្រួតពិនិត្យ និងវាយតម្លៃគោលនយោបាយម៉ាក្រូសេដ្ឋកិច្ច និងសារពើពន្ធ | P113: =SUMIF($E114:$E$1454,F113,$P114:$P$1454) -> 347200000 | T113: =IF(AND(F113<>"",G113<>""),"ok","-") -> - | U113: =MOD(K113,1) -> 0 | V113: =MOD(M113,1) -> 0 | W113: =MOD(O113,1) -> 0
A114: =IF(AND(F114<>"",G114<>""),LEFT(E114,5),"") | B114: =IF(AND(F114<>"",G114<>""),LEFT(G114,2),"") | C114: =IF(AND(F114<>"",G114<>""),COUNT($C$32:C113)+1,"") | D114: =IF(C114<>"","LN"&TEXT(C114,"0000"),"") | E114: =IF(AND(F114<>"",G114<>""),LEFT(F114,7),"") | F114: 101010201 | H114: សកម្មភាពទី១នៃចង្កោមសកម្មភាពទី២៖ ធ្វើការស្រាវជ្រាវលើវឌ្ឍនភាព និងបញ្ហា អភិវឌ្ឍន៍សេដ្ឋកិច្ច ហិរញ្ញវត្ថុ និងវិស័យសំខាន់ៗ | P114: =SUMIF($F115:$F$1454,F114,$P115:$P$1454) -> 19900000 | T114: =IF(AND(F114<>"",G114<>""),"ok","-") -> - | U114: =MOD(K114,1) -> 0 | V114: =MOD(M114,1) -> 0 | W114: =MOD(O114,1) -> 0
A115: =IF(AND(F115<>"",G115<>""),LEFT(E115,5),"") | B115: =IF(AND(F115<>"",G115<>""),LEFT(G115,2),"") | C115: =IF(AND(F115<>"",G115<>""),COUNT($C$32:C114)+1,"") | D115: =IF(C115<>"","LN"&TEXT(C115,"0000"),"") | E115: =IF(AND(F115<>"",G115<>""),LEFT(F115,7),"") | H115: ១.បេសកកម្មក្នុងស្រុកលើកទី១ | N115: =IF(AND(F115<>"",G115<>""),K115*M115,"") | P115: =SUM(P116:P120) -> 6669000 | T115: =IF(AND(F115<>"",G115<>""),"ok","-") -> - | U115: =MOD(K115,1) -> 0 | V115: =MOD(M115,1) -> 0 | W115: =MOD(O115,1) -> 0
A116: =IF(AND(F116<>"",G116<>""),LEFT(E116,5),"") -> 10101 | B116: =IF(AND(F116<>"",G116<>""),LEFT(G116,2),"") -> 61 | C116: =IF(AND(F116<>"",G116<>""),COUNT($C$32:C115)+1,"") -> 71 | D116: =IF(C116<>"","LN"&TEXT(C116,"0000"),"") -> LN0071 | E116: =IF(AND(F116<>"",G116<>""),LEFT(F116,7),"") -> 1010102 | F116: 101010201 | G116: 61122 | H116: ប្រាក់បេសកកម្ម-ប្រាក់ហោប៉ៅ (5 days X 16,000) = 80,000 | I116: Regular | J116: នាក់ | K116: 10 | L116: KHR | M116: 80000 | N116: =IF(AND(F116<>"",G116<>""),K116*M116,"") -> 800000 | O116: 1 | P116: =IF(AND(F116<>"",G116<>""),N116*O116,"") -> 800000 | T116: =IF(AND(F116<>"",G116<>""),"ok","-") -> ok | U116: =MOD(K116,1) -> 0 | V116: =MOD(M116,1) -> 0 | W116: =MOD(O116,1) -> 0
A117: =IF(AND(F117<>"",G117<>""),LEFT(E117,5),"") -> 10101 | B117: =IF(AND(F117<>"",G117<>""),LEFT(G117,2),"") -> 61 | C117: =IF(AND(F117<>"",G117<>""),COUNT($C$32:C116)+1,"") -> 72 | D117: =IF(C117<>"","LN"&TEXT(C117,"0000"),"") -> LN0072 | E117: =IF(AND(F117<>"",G117<>""),LEFT(F117,7),"") -> 1010102 | F117: 101010201 | G117: 61121 | H117: សោហ៊ុយធ្វើដំណើរទៅមក | I117: Regular | J117: នាក់ | K117: 10 | L117: KHR | M117: 70000 | N117: =IF(AND(F117<>"",G117<>""),K117*M117,"") -> 700000 | O117: 1 | P117: =IF(AND(F117<>"",G117<>""),N117*O117,"") -> 700000 | T117: =IF(AND(F117<>"",G117<>""),"ok","-") -> ok | U117: =MOD(K117,1) -> 0 | V117: =MOD(M117,1) -> 0 | W117: =MOD(O117,1) -> 0
A118: =IF(AND(F118<>"",G118<>""),LEFT(E118,5),"") -> 10101 | B118: =IF(AND(F118<>"",G118<>""),LEFT(G118,2),"") -> 61 | C118: =IF(AND(F118<>"",G118<>""),COUNT($C$32:C117)+1,"") -> 73 | D118: =IF(C118<>"","LN"&TEXT(C118,"0000"),"") -> LN0073 | E118: =IF(AND(F118<>"",G118<>""),LEFT(F118,7),"") -> 1010102 | F118: 101010201 | G118: 61123 | H118: ប្រាក់បេសកកម្ម ប្រាក់ហូបចុក (5 days X 40,000) = 200,000 | I118: Regular | J118: នាក់ | K118: 10 | L118: KHR | M118: 200000 | N118: =IF(AND(F118<>"",G118<>""),K118*M118,"") -> 2000000 | O118: 1 | P118: =IF(AND(F118<>"",G118<>""),N118*O118,"") -> 2000000 | T118: =IF(AND(F118<>"",G118<>""),"ok","-") -> ok | U118: =MOD(K118,1) -> 0 | V118: =MOD(M118,1) -> 0 | W118: =MOD(O118,1) -> 0
A119: =IF(AND(F119<>"",G119<>""),LEFT(E119,5),"") -> 10101 | B119: =IF(AND(F119<>"",G119<>""),LEFT(G119,2),"") -> 61 | C119: =IF(AND(F119<>"",G119<>""),COUNT($C$32:C118)+1,"") -> 74 | D119: =IF(C119<>"","LN"&TEXT(C119,"0000"),"") -> LN0074 | E119: =IF(AND(F119<>"",G119<>""),LEFT(F119,7),"") -> 1010102 | F119: 101010201 | G119: 61123 | H119: ប្រាក់បេសកកម្ម ប្រាក់ស្នាក់នៅ (4 night X 80,000) = 320,000 | I119: Regular | J119: នាក់ | K119: 9 | L119: KHR | M119: 320000 | N119: =IF(AND(F119<>"",G119<>""),K119*M119,"") -> 2880000 | O119: 1 | P119: =IF(AND(F119<>"",G119<>""),N119*O119,"") -> 2880000 | T119: =IF(AND(F119<>"",G119<>""),"ok","-") -> ok | U119: =MOD(K119,1) -> 0 | V119: =MOD(M119,1) -> 0 | W119: =MOD(O119,1) -> 0
...

Sheet Table11A-Full
D8: កូដអង្គភាព | J8: 101 | K8: =J8&"01" -> 10101 | L8: =J8&"02" -> 10102 | M8: =J8&"03" -> 10103 | N8: =J8&"04" -> 10104 | O8: =J8&"05" -> 10105 | P8: =J8&"06" -> 10106 | Q8: =J8&"07" -> 10107 | R8: =J8&"08" -> 10108 | S8: =J8&"09" -> 10109 | T8: =J8&"10" -> 10110 | U8: =J8&"11" -> 10111 | V8: =J8&"12" -> 10112 | W8: =J8&"13" -> 10113 | X8: =J8&"14" -> 10114 | Y8: =J8&"15" -> 10115 | Z8: 102 | AA8: =Z8&"01" -> 10201 | AB8: =Z8&"02" -> 10202 | AC8: =Z8&"03" -> 10203 | AD8: =Z8&"04" -> 10204 | AE8: =Z8&"05" -> 10205 | AF8: =Z8&"06" -> 10206 | AG8: =Z8&"07" -> 10207 | AH8: =Z8&"08" -> 10208 | AI8: =Z8&"09" -> 10209 | AJ8: =Z8&"10" -> 10210 | AK8: =Z8&"11" -> 10211 | AL8: =Z8&"12" -> 10212 | AM8: =Z8&"13" -> 10213 | AN8: =Z8&"14" -> 10214 | AO8: =Z8&"15" -> 10215 | AP8: 103 | AQ8: =AP8&"01" -> 10301 | AR8: =AP8&"02" -> 10302 | AS8: =AP8&"03" -> 10303 | AT8: =AP8&"04" -> 10304 | AU8: =AP8&"05" -> 10305 | AV8: =AP8&"06" -> 10306 | AW8: =AP8&"07" -> 10307 | AX8: =AP8&"08" -> 10308 | AY8: =AP8&"09" -> 10309 | AZ8: =AP8&"10" -> 10310 | BA8: =AP8&"11" -> 10311 | BB8: =AP8&"12" -> 10312 | BC8: =AP8&"13" -> 10313 | BD8: =AP8&"14" -> 10314 | BE8: =AP8&"15" -> 10315 | BF8: 104 | BG8: =BF8&"01" -> 10401 | BH8: =BF8&"02" -> 10402 | BI8: =BF8&"03" -> 10403 | BJ8: =BF8&"04" -> 10404 | BK8: =BF8&"05" -> 10405 | BL8: =BF8&"06" -> 10406 | BM8: =BF8&"07" -> 10407 | BN8: =BF8&"08" -> 10408 | BO8: =BF8&"09" -> 10409 | BP8: =BF8&"10" -> 10410 | BQ8: =BF8&"11" -> 10411 | BR8: =BF8&"12" -> 10412 | BS8: =BF8&"13" -> 10413 | BT8: =BF8&"14" -> 10414 | BU8: =BF8&"15" -> 10415 | BV8: 105 | BW8: =BV8&"01" -> 10501 | BX8: =BV8&"02" -> 10502 | BY8: =BV8&"03" -> 10503 | BZ8: =BV8&"04" -> 10504 | CA8: =BV8&"05" -> 10505 | CB8: =BV8&"06" -> 10506 | CC8: =BV8&"07" -> 10507 | CD8: =BV8&"08" -> 10508 | CE8: =BV8&"09" -> 10509 | CF8: =BV8&"10" -> 10510 | CG8: =BV8&"11" -> 10511 | CH8: =BV8&"12" -> 10512 | CI8: =BV8&"13" -> 10513 | CJ8: =BV8&"14" -> 10514 | CK8: =BV8&"15" -> 10515 | CL8: =BV8&"16" -> 10516 | CM8: =BV8&"17" -> 10517 | CN8: =BV8&"18" -> 10518 | CO8: =BV8&"19" -> 10519 | CP8: =BV8&"20" -> 10520 | CQ8: =BV8&"21" -> 10521 | CR8: =BV8&"22" -> 10522 | CS8: =BV8&"23" -> 10523 | CT8: =BV8&"24" -> 10524 | CU8: =BV8&"25" -> 10525 | CW8: 201 | CX8: =CW8&"01" -> 20101 | CY8: =CW8&"02" -> 20102 | CZ8: =CW8&"03" -> 20103 | DA8: =CW8&"04" -> 20104 | DB8: =CW8&"05" -> 20105 | DC8: =CW8&"06" -> 20106 | DD8: =CW8&"07" -> 20107 | DE8: =CW8&"08" -> 20108 | DF8: =CW8&"09" -> 20109 | DG8: =CW8&"10" -> 20110 | DH8: =CW8&"11" -> 20111 | DI8: =CW8&"12" -> 20112 | DJ8: =CW8&"13" -> 20113 | DK8: =CW8&"14" -> 20114 | DL8: =CW8&"15" -> 20115 | DM8: 202 | DN8: =DM8&"01" -> 20201 | DO8: =DM8&"02" -> 20202 | DP8: =DM8&"03" -> 20203 | DQ8: =DM8&"04" -> 20204 | DR8: =DM8&"05" -> 20205 | DS8: =DM8&"06" -> 20206 | DT8: =DM8&"07" -> 20207 | DU8: =DM8&"08" -> 20208 | DV8: =DM8&"09" -> 20209 | DW8: =DM8&"10" -> 20210 | DX8: =DM8&"11" -> 20211 | DY8: =DM8&"12" -> 20212 | DZ8: =DM8&"13" -> 20213 | EA8: =DM8&"14" -> 20214 | EB8: =DM8&"15" -> 20215 | EC8: 203 | ED8: =EC8&"01" -> 20301 | EE8: =EC8&"02" -> 20302 | EF8: =EC8&"03" -> 20303 | EG8: =EC8&"04" -> 20304 | EH8: =EC8&"05" -> 20305 | EI8: =EC8&"06" -> 20306 | EJ8: =EC8&"07" -> 20307 | EK8: =EC8&"08" -> 20308 | EL8: =EC8&"09" -> 20309 | EM8: =EC8&"10" -> 20310 | EN8: =EC8&"11" -> 20311 | EO8: =EC8&"12" -> 20312 | EP8: =EC8&"13" -> 20313 | EQ8: =EC8&"14" -> 20314 | ER8: =EC8&"15" -> 20315 | ES8: 204 | ET8: =ES8&"01" -> 20401 | EU8: =ES8&"02" -> 20402 | EV8: =ES8&"03" -> 20403 | EW8: =ES8&"04" -> 20404 | EX8: =ES8&"05" -> 20405 | EY8: =ES8&"06" -> 20406 | EZ8: =ES8&"07" -> 20407 | FA8: =ES8&"08" -> 20408 | FB8: =ES8&"09" -> 20409 | FC8: =ES8&"10" -> 20410 | FD8: =ES8&"11" -> 20411 | FE8: =ES8&"12" -> 20412 | FF8: =ES8&"13" -> 20413 | FG8: =ES8&"14" -> 20414 | FH8: =ES8&"15" -> 20415 | FI8: 205 | FJ8: =FI8&"01" -> 20501 | FK8: =FI8&"02" -> 20502 | FL8: =FI8&"03" -> 20503 | FM8: =FI8&"04" -> 20504 | FN8: =FI8&"05" -> 20505 | FO8: =FI8&"06" -> 20506 | FP8: =FI8&"07" -> 20507 | FQ8: =FI8&"08" -> 20508 | FR8: =FI8&"09" -> 20509 | FS8: =FI8&"10" -> 20510 | FT8: =FI8&"11" -> 20511 | FU8: =FI8&"12" -> 20512 | FV8: =FI8&"13" -> 20513 | FW8: =FI8&"14" -> 20514 | FX8: =FI8&"15" -> 20515 | FY8: 206 | FZ8: =FY8&"01" -> 20601 | GA8: =FY8&"02" -> 20602 | GB8: =FY8&"03" -> 20603 | GC8: =FY8&"04" -> 20604 | GD8: =FY8&"05" -> 20605 | GE8: =FY8&"06" -> 20606 | GF8: =FY8&"07" -> 20607 | GG8: =FY8&"08" -> 20608 | GH8: =FY8&"09" -> 20609 | GI8: =FY8&"10" -> 20610 | GJ8: =FY8&"11" -> 20611 | GK8: =FY8&"12" -> 20612 | GL8: =FY8&"13" -> 20613 | GM8: =FY8&"14" -> 20614 | GN8: =FY8&"15" -> 20615 | GO8: 207 | GP8: =GO8&"01" -> 20701 | GQ8: =GO8&"02" -> 20702 | GR8: =GO8&"03" -> 20703 | GS8: =GO8&"04" -> 20704 | GT8: =GO8&"05" -> 20705 | GU8: =GO8&"06" -> 20706 | GV8: =GO8&"07" -> 20707 | GW8: =GO8&"08" -> 20708 | GX8: =GO8&"09" -> 20709 | GY8: =GO8&"10" -> 20710 | GZ8: =GO8&"11" -> 20711 | HA8: =GO8&"12" -> 20712 | HB8: =GO8&"13" -> 20713 | HC8: =GO8&"14" -> 20714 | HD8: =GO8&"15" -> 20715 | HE8: =GO8&"16" -> 20716 | HF8: =GO8&"17" -> 20717 | HG8: =GO8&"18" -> 20718 | HH8: =GO8&"19" -> 20719 | HI8: =GO8&"20" -> 20720 | HJ8: =GO8&"21" -> 20721 | HK8: =GO8&"22" -> 20722 | HL8: =GO8&"23" -> 20723 | HM8: =GO8&"24" -> 20724 | HN8: =GO8&"25" -> 20725 | HQ8: 301 | HR8: =HQ8&"01" -> 30101 | HS8: =HQ8&"02" -> 30102 | HT8: =HQ8&"03" -> 30103 | HU8: =HQ8&"04" -> 30104 | HV8: =HQ8&"05" -> 30105 | HW8: =HQ8&"06" -> 30106 | HX8: =HQ8&"07" -> 30107 | HY8: =HQ8&"08" -> 30108 | HZ8: =HQ8&"09" -> 30109 | IA8: =HQ8&"10" -> 30110 | IB8: =HQ8&"11" -> 30111 | IC8: =HQ8&"12" -> 30112 | ID8: =HQ8&"13" -> 30113 | IE8: =HQ8&"14" -> 30114 | IF8: =HQ8&"15" -> 30115 | IG8: 302 | IH8: =IG8&"01" -> 30201 | II8: =IG8&"02" -> 30202 | IJ8: =IG8&"03" -> 30203 | IK8: =IG8&"04" -> 30204 | IL8: =IG8&"05" -> 30205 | IM8: =IG8&"06" -> 30206 | IN8: =IG8&"07" -> 30207 | IO8: =IG8&"08" -> 30208 | IP8: =IG8&"09" -> 30209 | IQ8: =IG8&"10" -> 30210 | IR8: =IG8&"11" -> 30211 | IS8: =IG8&"12" -> 30212 | IT8: =IG8&"13" -> 30213 | IU8: =IG8&"14" -> 30214 | IV8: =IG8&"15" -> 30215 | IW8: 303 | IX8: =IW8&"01" -> 30301 | IY8: =IW8&"02" -> 30302 | IZ8: =IW8&"03" -> 30303 | JA8: =IW8&"04" -> 30304 | JB8: =IW8&"05" -> 30305 | JC8: =IW8&"06" -> 30306 | JD8: =IW8&"07" -> 30307 | JE8: =IW8&"08" -> 30308 | JF8: =IW8&"09" -> 30309 | JG8: =IW8&"10" -> 30310 | JH8: =IW8&"11" -> 30311 | JI8: =IW8&"12" -> 30312 | JJ8: =IW8&"13" -> 30313 | JK8: =IW8&"14" -> 30314 | JL8: =IW8&"15" -> 30315 | JM8: 304 | JN8: =JM8&"01" -> 30401 | JO8: =JM8&"02" -> 30402 | JP8: =JM8&"03" -> 30403 | JQ8: =JM8&"04" -> 30404 | JR8: =JM8&"05" -> 30405 | JS8: =JM8&"06" -> 30406 | JT8: =JM8&"07" -> 30407 | JU8: =JM8&"08" -> 30408 | JV8: =JM8&"09" -> 30409 | JW8: =JM8&"10" -> 30410 | JX8: =JM8&"11" -> 30411 | JY8: =JM8&"12" -> 30412 | JZ8: =JM8&"13" -> 30413 | KA8: =JM8&"14" -> 30414 | KB8: =JM8&"15" -> 30415 | KC8: 305 | KD8: =KC8&"01" -> 30501 | KE8: =KC8&"02" -> 30502 | KF8: =KC8&"03" -> 30503 | KG8: =KC8&"04" -> 30504 | KH8: =KC8&"05" -> 30505 | KI8: =KC8&"06" -> 30506 | KJ8: =KC8&"07" -> 30507 | KK8: =KC8&"08" -> 30508 | KL8: =KC8&"09" -> 30509 | KM8: =KC8&"10" -> 30510 | KN8: =KC8&"11" -> 30511 | KO8: =KC8&"12" -> 30512 | KP8: =KC8&"13" -> 30513 | KQ8: =KC8&"14" -> 30514 | KR8: =KC8&"15" -> 30515 | KS8: =KC8&"16" -> 30516 | KT8: =KC8&"17" -> 30517 | KU8: =KC8&"18" -> 30518 | KV8: =KC8&"19" -> 30519 | KW8: =KC8&"20" -> 30520 | KX8: =KC8&"21" -> 30521 | KY8: =KC8&"22" -> 30522 | KZ8: =KC8&"23" -> 30523 | LA8: =KC8&"24" -> 30524 | LB8: =KC8&"25" -> 30525 | LD8: 401 | LE8: =LD8&"01" -> 40101 | LF8: =LD8&"02" -> 40102 | LG8: =LD8&"03" -> 40103 | LH8: =LD8&"04" -> 40104 | LI8: =LD8&"05" -> 40105 | LJ8: =LD8&"06" -> 40106 | LK8: =LD8&"07" -> 40107 | LL8: =LD8&"08" -> 40108 | LM8: =LD8&"09" -> 40109 | LN8: =LD8&"10" -> 40110 | LO8: =LD8&"11" -> 40111 | LP8: =LD8&"12" -> 40112 | LQ8: =LD8&"13" -> 40113 | LR8: =LD8&"14" -> 40114 | LS8: =LD8&"15" -> 40115 | LT8: 402 | LU8: =LT8&"01" -> 40201 | LV8: =LT8&"02" -> 40202 | LW8: =LT8&"03" -> 40203 | LX8: =LT8&"04" -> 40204 | LY8: =LT8&"05" -> 40205 | LZ8: =LT8&"06" -> 40206 | MA8: =LT8&"07" -> 40207 | MB8: =LT8&"08" -> 40208 | MC8: =LT8&"09" -> 40209 | MD8: =LT8&"10" -> 40210 | ME8: =LT8&"11" -> 40211 | MF8: =LT8&"12" -> 40212 | MG8: =LT8&"13" -> 40213 | MH8: =LT8&"14" -> 40214 | MI8: =LT8&"15" -> 40215 | MJ8: 403 | MK8: =MJ8&"01" -> 40301 | ML8: =MJ8&"02" -> 40302 | MM8: =MJ8&"03" -> 40303 | MN8: =MJ8&"04" -> 40304 | MO8: =MJ8&"05" -> 40305 | MP8: =MJ8&"06" -> 40306 | MQ8: =MJ8&"07" -> 40307 | MR8: =MJ8&"08" -> 40308 | MS8: =MJ8&"09" -> 40309 | MT8: =MJ8&"10" -> 40310 | MU8: =MJ8&"11" -> 40311 | MV8: =MJ8&"12" -> 40312 | MW8: =MJ8&"13" -> 40313 | MX8: =MJ8&"14" -> 40314 | MY8: =MJ8&"15" -> 40315 | MZ8: 404 | NA8: =MZ8&"01" -> 40401 | NB8: =MZ8&"02" -> 40402 | NC8: =MZ8&"03" -> 40403 | ND8: =MZ8&"04" -> 40404 | NE8: =MZ8&"05" -> 40405 | NF8: =MZ8&"06" -> 40406 | NG8: =MZ8&"07" -> 40407 | NH8: =MZ8&"08" -> 40408 | NI8: =MZ8&"09" -> 40409 | NJ8: =MZ8&"10" -> 40410 | NK8: =MZ8&"11" -> 40411 | NL8: =MZ8&"12" -> 40412 | NM8: =MZ8&"13" -> 40413 | NN8: =MZ8&"14" -> 40414 | NO8: =MZ8&"15" -> 40415 | NP8: 405 | NQ8: =NP8&"01" -> 40501 | NR8: =NP8&"02" -> 40502 | NS8: =NP8&"03" -> 40503 | NT8: =NP8&"04" -> 40504 | NU8: =NP8&"05" -> 40505 | NV8: =NP8&"06" -> 40506 | NW8: =NP8&"07" -> 40507 | NX8: =NP8&"08" -> 40508 | NY8: =NP8&"09" -> 40509 | NZ8: =NP8&"10" -> 40510 | OA8: =NP8&"11" -> 40511 | OB8: =NP8&"12" -> 40512 | OC8: =NP8&"13" -> 40513 | OD8: =NP8&"14" -> 40514 | OE8: =NP8&"15" -> 40515 | OF8: 406 | OG8: =OF8&"01" -> 40601 | OH8: =OF8&"02" -> 40602 | OI8: =OF8&"03" -> 40603 | OJ8: =OF8&"04" -> 40604 | OK8: =OF8&"05" -> 40605 | OL8: =OF8&"06" -> 40606 | OM8: =OF8&"07" -> 40607 | ON8: =OF8&"08" -> 40608 | OO8: =OF8&"09" -> 40609 | OP8: =OF8&"10" -> 40610 | OQ8: =OF8&"11" -> 40611 | OR8: =OF8&"12" -> 40612 | OS8: =OF8&"13" -> 40613 | OT8: =OF8&"14" -> 40614 | OU8: =OF8&"15" -> 40615 | OV8: 407 | OW8: =OV8&"01" -> 40701 | OX8: =OV8&"02" -> 40702 | OY8: =OV8&"03" -> 40703 | OZ8: =OV8&"04" -> 40704 | PA8: =OV8&"05" -> 40705 | PB8: =OV8&"06" -> 40706 | PC8: =OV8&"07" -> 40707 | PD8: =OV8&"08" -> 40708 | PE8: =OV8&"09" -> 40709 | PF8: =OV8&"10" -> 40710 | PG8: =OV8&"11" -> 40711 | PH8: =OV8&"12" -> 40712 | PI8: =OV8&"13" -> 40713 | PJ8: =OV8&"14" -> 40714 | PK8: =OV8&"15" -> 40715 | PL8: 408 | PM8: =PL8&"01" -> 40801 | PN8: =PL8&"02" -> 40802 | PO8: =PL8&"03" -> 40803 | PP8: =PL8&"04" -> 40804 | PQ8: =PL8&"05" -> 40805 | PR8: =PL8&"06" -> 40806 | PS8: =PL8&"07" -> 40807 | PT8: =PL8&"08" -> 40808 | PU8: =PL8&"09" -> 40809 | PV8: =PL8&"10" -> 40810 | PW8: =PL8&"11" -> 40811 | PX8: =PL8&"12" -> 40812 | PY8: =PL8&"13" -> 40813 | PZ8: =PL8&"14" -> 40814 | QA8: =PL8&"15" -> 40815 | QB8: 409 | QC8: =QB8&"01" -> 40901 | QD8: =QB8&"02" -> 40902 | QE8: =QB8&"03" -> 40903 | QF8: =QB8&"04" -> 40904 | QG8: =QB8&"05" -> 40905 | QH8: =QB8&"06" -> 40906 | QI8: =QB8&"07" -> 40907 | QJ8: =QB8&"08" -> 40908 | QK8: =QB8&"09" -> 40909 | QL8: =QB8&"10" -> 40910 | QM8: =QB8&"11" -> 40911 | QN8: =QB8&"12" -> 40912 | QO8: =QB8&"13" -> 40913 | QP8: =QB8&"14" -> 40914 | QQ8: =QB8&"15" -> 40915 | QR8: 410 | QS8: =QR8&"01" -> 41001 | QT8: =QR8&"02" -> 41002 | QU8: =QR8&"03" -> 41003 | QV8: =QR8&"04" -> 41004 | QW8: =QR8&"05" -> 41005 | QX8: =QR8&"06" -> 41006 | QY8: =QR8&"07" -> 41007 | QZ8: =QR8&"08" -> 41008 | RA8: =QR8&"09" -> 41009 | RB8: =QR8&"10" -> 41010 | RC8: =QR8&"11" -> 41011 | RD8: =QR8&"12" -> 41012 | RE8: =QR8&"13" -> 41013 | RF8: =QR8&"14" -> 41014 | RG8: =QR8&"15" -> 41015 | RH8: =QR8&"16" -> 41016 | RI8: =QR8&"17" -> 41017 | RJ8: =QR8&"18" -> 41018 | RK8: =QR8&"19" -> 41019 | RL8: =QR8&"20" -> 41020 | RM8: =QR8&"21" -> 41021 | RN8: =QR8&"22" -> 41022 | RO8: =QR8&"23" -> 41023 | RP8: =QR8&"24" -> 41024 | RQ8: =QR8&"25" -> 41025 | RS8: 501 | RT8: =RS8&"01" -> 50101 | RU8: =RS8&"02" -> 50102 | RV8: =RS8&"03" -> 50103 | RW8: =RS8&"04" -> 50104 | RX8: =RS8&"05" -> 50105 | RY8: =RS8&"06" -> 50106 | RZ8: =RS8&"07" -> 50107 | SA8: =RS8&"08" -> 50108 | SB8: =RS8&"09" -> 50109 | SC8: =RS8&"10" -> 50110 | SD8: =RS8&"11" -> 50111 | SE8: =RS8&"12" -> 50112 | SF8: =RS8&"13" -> 50113 | SG8: =RS8&"14" -> 50114 | SH8: =RS8&"15" -> 50115 | SI8: 502 | SJ8: =SI8&"01" -> 50201 | SK8: =SI8&"02" -> 50202 | SL8: =SI8&"03" -> 50203 | SM8: =SI8&"04" -> 50204 | SN8: =SI8&"05" -> 50205 | SO8: =SI8&"06" -> 50206 | SP8: =SI8&"07" -> 50207 | SQ8: =SI8&"08" -> 50208 | SR8: =SI8&"09" -> 50209 | SS8: =SI8&"10" -> 50210 | ST8: =SI8&"11" -> 50211 | SU8: =SI8&"12" -> 50212 | SV8: =SI8&"13" -> 50213 | SW8: =SI8&"14" -> 50214 | SX8: =SI8&"15" -> 50215 | SY8: 503 | SZ8: =SY8&"01" -> 50301 | TA8: =SY8&"02" -> 50302 | TB8: =SY8&"03" -> 50303 | TC8: =SY8&"04" -> 50304 | TD8: =SY8&"05" -> 50305 | TE8: =SY8&"06" -> 50306 | TF8: =SY8&"07" -> 50307 | TG8: =SY8&"08" -> 50308 | TH8: =SY8&"09" -> 50309 | TI8: =SY8&"10" -> 50310 | TJ8: =SY8&"11" -> 50311 | TK8: =SY8&"12" -> 50312 | TL8: =SY8&"13" -> 50313 | TM8: =SY8&"14" -> 50314 | TN8: =SY8&"15" -> 50315 | TO8: 504 | TP8: =TO8&"01" -> 50401 | TQ8: =TO8&"02" -> 50402 | TR8: =TO8&"03" -> 50403 | TS8: =TO8&"04" -> 50404 | TT8: =TO8&"05" -> 50405 | TU8: =TO8&"06" -> 50406 | TV8: =TO8&"07" -> 50407 | TW8: =TO8&"08" -> 50408 | TX8: =TO8&"09" -> 50409 | TY8: =TO8&"10" -> 50410 | TZ8: =TO8&"11" -> 50411 | UA8: =TO8&"12" -> 50412 | UB8: =TO8&"13" -> 50413 | UC8: =TO8&"14" -> 50414 | UD8: =TO8&"15" -> 50415 | UE8: 505 | UF8: =UE8&"01" -> 50501 | UG8: =UE8&"02" -> 50502 | UH8: =UE8&"03" -> 50503 | UI8: =UE8&"04" -> 50504 | UJ8: =UE8&"05" -> 50505 | UK8: =UE8&"06" -> 50506 | UL8: =UE8&"07" -> 50507 | UM8: =UE8&"08" -> 50508 | UN8: =UE8&"09" -> 50509 | UO8: =UE8&"10" -> 50510 | UP8: =UE8&"11" -> 50511 | UQ8: =UE8&"12" -> 50512 | UR8: =UE8&"13" -> 50513 | US8: =UE8&"14" -> 50514 | UT8: =UE8&"15" -> 50515 | UU8: =UE8&"16" -> 50516 | UV8: =UE8&"17" -> 50517 | UW8: =UE8&"18" -> 50518 | UX8: =UE8&"19" -> 50519 | UY8: =UE8&"20" -> 50520 | UZ8: =UE8&"21" -> 50521 | VA8: =UE8&"22" -> 50522 | VB8: =UE8&"23" -> 50523 | VC8: =UE8&"24" -> 50524 | VD8: =UE8&"25" -> 50525
A10: ជំពូក | B10: គណនី | C10: អនុគណនី | D10: ចំណាត់ថ្នាក់ចំណាយ (តាមតារាងមាតិកាថវិកា ) | E10: សរុបរួម ក្រសួង | F10: រដ្ឋបាល កណ្ដាល | G10: មន្ទីរ សហវ. | H10: គោលប. គនប.ទី១ | I10: កម្មវិធីទី១ | J10: =VLOOKUP(J8,#REF!,8,FALSE) -> #REF! | Z10: =VLOOKUP(Z8,#REF!,8,FALSE) -> #REF! | AP10: =VLOOKUP(AP8,#REF!,8,FALSE) -> #REF! | BF10: =VLOOKUP(BF8,#REF!,8,FALSE) -> #REF! | BV10: =VLOOKUP(BV8,#REF!,8,FALSE) -> #REF! | CV10: កម្មវិធីទី២ | CW10: =VLOOKUP(CW8,#REF!,8,FALSE) -> #REF! | DM10: =VLOOKUP(DM8,#REF!,8,FALSE) -> #REF! | EC10: =VLOOKUP(EC8,#REF!,8,FALSE) -> #REF! | ES10: =VLOOKUP(ES8,#REF!,8,FALSE) -> #REF! | FI10: =VLOOKUP(FI8,#REF!,8,FALSE) -> #REF! | FY10: =VLOOKUP(FY8,#REF!,8,FALSE) -> #REF! | GO10: =VLOOKUP(GO8,#REF!,8,FALSE) -> #REF! | HO10: គោលប. គនប.ទី២ | HP10: កម្មវិធីទី៣ | HQ10: =VLOOKUP(HQ8,#REF!,8,FALSE) -> #REF! | IG10: =VLOOKUP(IG8,#REF!,8,FALSE) -> #REF! | IW10: =VLOOKUP(IW8,#REF!,8,FALSE) -> #REF! | JM10: =VLOOKUP(JM8,#REF!,8,FALSE) -> #REF! | KC10: =VLOOKUP(KC8,#REF!,8,FALSE) -> #REF! | LC10: កម្មវិធីទី៤ | LD10: =VLOOKUP(LD8,#REF!,8,FALSE) -> #REF! | LT10: =VLOOKUP(LT8,#REF!,8,FALSE) -> #REF! | MJ10: =VLOOKUP(MJ8,#REF!,8,FALSE) -> #REF! | MZ10: =VLOOKUP(MZ8,#REF!,8,FALSE) -> #REF! | NP10: =VLOOKUP(NP8,#REF!,8,FALSE) -> #REF! | OF10: =VLOOKUP(OF8,#REF!,8,FALSE) -> #REF! | OV10: =VLOOKUP(OV8,#REF!,8,FALSE) -> #REF! | PL10: =VLOOKUP(PL8,#REF!,8,FALSE) -> #REF! | QB10: =VLOOKUP(QB8,#REF!,8,FALSE) -> #REF! | QR10: =VLOOKUP(QR8,#REF!,8,FALSE) -> #REF! | RR10: កម្មវិធីទី៥ | RS10: =VLOOKUP(RS8,#REF!,8,FALSE) -> #REF! | SI10: =VLOOKUP(SI8,#REF!,8,FALSE) -> #REF! | SY10: =VLOOKUP(SY8,#REF!,8,FALSE) -> #REF! | TO10: =VLOOKUP(TO8,#REF!,8,FALSE) -> #REF! | UE10: =VLOOKUP(UE8,#REF!,8,FALSE) -> #REF!
J11: សរុប | K11: ច.ស.ទី១ | L11: ច.ស.ទី២ | M11: ច.ស.ទី៣ | N11: ច.ស.ទី៤ | O11: ច.ស.ទី៥ | P11: ច.ស.ទី៦ | Q11: ច.ស.ទី៧ | R11: ច.ស.ទី៨ | S11: ច.ស.ទី៩ | T11: ច.ស.ទី១០ | U11: ច.ស.ទី១១ | V11: ច.ស.ទី១២ | W11: ច.ស.ទី១៣ | X11: ច.ស.ទី១៤ | Y11: ច.ស.ទី១៥ | Z11: សរុប | AA11: ច.ស.ទី១ | AB11: ច.ស.ទី២ | AC11: ច.ស.ទី៣ | AD11: ច.ស.ទី៤ | AE11: ច.ស.ទី៥ | AF11: ច.ស.ទី៦ | AG11: ច.ស.ទី៧ | AH11: ច.ស.ទី៨ | AI11: ច.ស.ទី៩ | AJ11: ច.ស.ទី១០ | AK11: ច.ស.ទី១១ | AL11: ច.ស.ទី១២ | AM11: ច.ស.ទី១៣ | AN11: ច.ស.ទី១៤ | AO11: ច.ស.ទី១៥ | AP11: សរុប | AQ11: ច.ស.ទី១ | AR11: ច.ស.ទី២ | AS11: ច.ស.ទី៣ | AT11: ច.ស.ទី៤ | AU11: ច.ស.ទី៥ | AV11: ច.ស.ទី៦ | AW11: ច.ស.ទី៧ | AX11: ច.ស.ទី៨ | AY11: ច.ស.ទី៩ | AZ11: ច.ស.ទី១០ | BA11: ច.ស.ទី១១ | BB11: ច.ស.ទី១២ | BC11: ច.ស.ទី១៣ | BD11: ច.ស.ទី១៤ | BE11: ច.ស.ទី១៥ | BF11: សរុប | BG11: ច.ស.ទី១ | BH11: ច.ស.ទី២ | BI11: ច.ស.ទី៣ | BJ11: ច.ស.ទី៤ | BK11: ច.ស.ទី៥ | BL11: ច.ស.ទី៦ | BM11: ច.ស.ទី៧ | BN11: ច.ស.ទី៨ | BO11: ច.ស.ទី៩ | BP11: ច.ស.ទី១០ | BQ11: ច.ស.ទី១១ | BR11: ច.ស.ទី១២ | BS11: ច.ស.ទី១៣ | BT11: ច.ស.ទី១៤ | BU11: ច.ស.ទី១៥ | BV11: សរុប | BW11: ច.ស.ទី១ | BX11: ច.ស.ទី២ | BY11: ច.ស.ទី៣ | BZ11: ច.ស.ទី៤ | CA11: ច.ស.ទី៥ | CB11: ច.ស.ទី៦ | CC11: ច.ស.ទី៧ | CD11: ច.ស.ទី៨ | CE11: ច.ស.ទី៩ | CF11: ច.ស.ទី១០ | CG11: ច.ស.ទី១១ | CH11: ច.ស.ទី១២ | CI11: ច.ស.ទី១៣ | CJ11: ច.ស.ទី១៤ | CK11: ច.ស.ទី១៥ | CL11: ច.ស.ទី១៦ | CM11: ច.ស.ទី១៧ | CN11: ច.ស.ទី១៨ | CO11: ច.ស.ទី១៩ | CP11: ច.ស.ទី២០ | CQ11: ច.ស.ទី២១ | CR11: ច.ស.ទី២២ | CS11: ច.ស.ទី២៣ | CT11: ច.ស.ទី២៤ | CU11: ច.ស.ទី២៥ | CW11: សរុប | CX11: ច.ស.ទី១ | CY11: ច.ស.ទី២ | CZ11: ច.ស.ទី៣ | DA11: ច.ស.ទី៤ | DB11: ច.ស.ទី៥ | DC11: ច.ស.ទី៦ | DD11: ច.ស.ទី៧ | DE11: ច.ស.ទី៨ | DF11: ច.ស.ទី៩ | DG11: ច.ស.ទី១០ | DH11: ច.ស.ទី១១ | DI11: ច.ស.ទី១២ | DJ11: ច.ស.ទី១៣ | DK11: ច.ស.ទី១៤ | DL11: ច.ស.ទី១៥ | DM11: សរុប | DN11: ច.ស.ទី១ | DO11: ច.ស.ទី២ | DP11: ច.ស.ទី៣ | DQ11: ច.ស.ទី៤ | DR11: ច.ស.ទី៥ | DS11: ច.ស.ទី៦ | DT11: ច.ស.ទី៧ | DU11: ច.ស.ទី៨ | DV11: ច.ស.ទី៩ | DW11: ច.ស.ទី១០ | DX11: ច.ស.ទី១១ | DY11: ច.ស.ទី១២ | DZ11: ច.ស.ទី១៣ | EA11: ច.ស.ទី១៤ | EB11: ច.ស.ទី១៥ | EC11: សរុប | ED11: ច.ស.ទី១ | EE11: ច.ស.ទី២ | EF11: ច.ស.ទី៣ | EG11: ច.ស.ទី៤ | EH11: ច.ស.ទី៥ | EI11: ច.ស.ទី៦ | EJ11: ច.ស.ទី៧ | EK11: ច.ស.ទី៨ | EL11: ច.ស.ទី៩ | EM11: ច.ស.ទី១០ | EN11: ច.ស.ទី១១ | EO11: ច.ស.ទី១២ | EP11: ច.ស.ទី១៣ | EQ11: ច.ស.ទី១៤ | ER11: ច.ស.ទី១៥ | ES11: សរុប | ET11: ច.ស.ទី១ | EU11: ច.ស.ទី២ | EV11: ច.ស.ទី៣ | EW11: ច.ស.ទី៤ | EX11: ច.ស.ទី៥ | EY11: ច.ស.ទី៦ | EZ11: ច.ស.ទី៧ | FA11: ច.ស.ទី៨ | FB11: ច.ស.ទី៩ | FC11: ច.ស.ទី១០ | FD11: ច.ស.ទី១១ | FE11: ច.ស.ទី១២ | FF11: ច.ស.ទី១៣ | FG11: ច.ស.ទី១៤ | FH11: ច.ស.ទី១៥ | FI11: សរុប | FJ11: ច.ស.ទី១ | FK11: ច.ស.ទី២ | FL11: ច.ស.ទី៣ | FM11: ច.ស.ទី៤ | FN11: ច.ស.ទី៥ | FO11: ច.ស.ទី៦ | FP11: ច.ស.ទី៧ | FQ11: ច.ស.ទី៨ | FR11: ច.ស.ទី៩ | FS11: ច.ស.ទី១០ | FT11: ច.ស.ទី១១ | FU11: ច.ស.ទី១២ | FV11: ច.ស.ទី១៣ | FW11: ច.ស.ទី១៤ | FX11: ច.ស.ទី១៥ | FY11: សរុប | FZ11: ច.ស.ទី១ | GA11: ច.ស.ទី២ | GB11: ច.ស.ទី៣ | GC11: ច.ស.ទី៤ | GD11: ច.ស.ទី៥ | GE11: ច.ស.ទី៦ | GF11: ច.ស.ទី៧ | GG11: ច.ស.ទី៨ | GH11: ច.ស.ទី៩ | GI11: ច.ស.ទី១០ | GJ11: ច.ស.ទី១១ | GK11: ច.ស.ទី១២ | GL11: ច.ស.ទី១៣ | GM11: ច.ស.ទី១៤ | GN11: ច.ស.ទី១៥ | GO11: សរុប | GP11: ច.ស.ទី១ | GQ11: ច.ស.ទី២ | GR11: ច.ស.ទី៣ | GS11: ច.ស.ទី៤ | GT11: ច.ស.ទី៥ | GU11: ច.ស.ទី៦ | GV11: ច.ស.ទី៧ | GW11: ច.ស.ទី៨ | GX11: ច.ស.ទី៩ | GY11: ច.ស.ទី១០ | GZ11: ច.ស.ទី១១ | HA11: ច.ស.ទី១២ | HB11: ច.ស.ទី១៣ | HC11: ច.ស.ទី១៤ | HD11: ច.ស.ទី១៥ | HE11: ច.ស.ទី១៦ | HF11: ច.ស.ទី១៧ | HG11: ច.ស.ទី១៨ | HH11: ច.ស.ទី១៩ | HI11: ច.ស.ទី២០ | HJ11: ច.ស.ទី២១ | HK11: ច.ស.ទី២២ | HL11: ច.ស.ទី២៣ | HM11: ច.ស.ទី២៤ | HN11: ច.ស.ទី២៥ | HQ11: សរុប | HR11: ច.ស.ទី១ | HS11: ច.ស.ទី២ | HT11: ច.ស.ទី៣ | HU11: ច.ស.ទី៤ | HV11: ច.ស.ទី៥ | HW11: ច.ស.ទី៦ | HX11: ច.ស.ទី៧ | HY11: ច.ស.ទី៨ | HZ11: ច.ស.ទី៩ | IA11: ច.ស.ទី១០ | IB11: ច.ស.ទី១១ | IC11: ច.ស.ទី១២ | ID11: ច.ស.ទី១៣ | IE11: ច.ស.ទី១៤ | IF11: ច.ស.ទី១៥ | IG11: សរុប | IH11: ច.ស.ទី១ | II11: ច.ស.ទី២ | IJ11: ច.ស.ទី៣ | IK11: ច.ស.ទី៤ | IL11: ច.ស.ទី៥ | IM11: ច.ស.ទី៦ | IN11: ច.ស.ទី៧ | IO11: ច.ស.ទី៨ | IP11: ច.ស.ទី៩ | IQ11: ច.ស.ទី១០ | IR11: ច.ស.ទី១១ | IS11: ច.ស.ទី១២ | IT11: ច.ស.ទី១៣ | IU11: ច.ស.ទី១៤ | IV11: ច.ស.ទី១៥ | IW11: សរុប | IX11: ច.ស.ទី១ | IY11: ច.ស.ទី២ | IZ11: ច.ស.ទី៣ | JA11: ច.ស.ទី៤ | JB11: ច.ស.ទី៥ | JC11: ច.ស.ទី៦ | JD11: ច.ស.ទី៧ | JE11: ច.ស.ទី៨ | JF11: ច.ស.ទី៩ | JG11: ច.ស.ទី១០ | JH11: ច.ស.ទី១១ | JI11: ច.ស.ទី១២ | JJ11: ច.ស.ទី១៣ | JK11: ច.ស.ទី១៤ | JL11: ច.ស.ទី១៥ | JM11: សរុប | JN11: ច.ស.ទី១ | JO11: ច.ស.ទី២ | JP11: ច.ស.ទី៣ | JQ11: ច.ស.ទី៤ | JR11: ច.ស.ទី៥ | JS11: ច.ស.ទី៦ | JT11: ច.ស.ទី៧ | JU11: ច.ស.ទី៨ | JV11: ច.ស.ទី៩ | JW11: ច.ស.ទី១០ | JX11: ច.ស.ទី១១ | JY11: ច.ស.ទី១២ | JZ11: ច.ស.ទី១៣ | KA11: ច.ស.ទី១៤ | KB11: ច.ស.ទី១៥ | KC11: សរុប | KD11: ច.ស.ទី១ | KE11: ច.ស.ទី២ | KF11: ច.ស.ទី៣ | KG11: ច.ស.ទី៤ | KH11: ច.ស.ទី៥ | KI11: ច.ស.ទី៦ | KJ11: ច.ស.ទី៧ | KK11: ច.ស.ទី៨ | KL11: ច.ស.ទី៩ | KM11: ច.ស.ទី១០ | KN11: ច.ស.ទី១១ | KO11: ច.ស.ទី១២ | KP11: ច.ស.ទី១៣ | KQ11: ច.ស.ទី១៤ | KR11: ច.ស.ទី១៥ | KS11: ច.ស.ទី១៦ | KT11: ច.ស.ទី១៧ | KU11: ច.ស.ទី១៨ | KV11: ច.ស.ទី១៩ | KW11: ច.ស.ទី២០ | KX11: ច.ស.ទី២១ | KY11: ច.ស.ទី២២ | KZ11: ច.ស.ទី២៣ | LA11: ច.ស.ទី២៤ | LB11: ច.ស.ទី២៥ | LD11: សរុប | LE11: ច.ស.ទី១ | LF11: ច.ស.ទី២ | LG11: ច.ស.ទី៣ | LH11: ច.ស.ទី៤ | LI11: ច.ស.ទី៥ | LJ11: ច.ស.ទី៦ | LK11: ច.ស.ទី៧ | LL11: ច.ស.ទី៨ | LM11: ច.ស.ទី៩ | LN11: ច.ស.ទី១០ | LO11: ច.ស.ទី១១ | LP11: ច.ស.ទី១២ | LQ11: ច.ស.ទី១៣ | LR11: ច.ស.ទី១៤ | LS11: ច.ស.ទី១៥ | LT11: សរុប | LU11: ច.ស.ទី១ | LV11: ច.ស.ទី២ | LW11: ច.ស.ទី៣ | LX11: ច.ស.ទី៤ | LY11: ច.ស.ទី៥ | LZ11: ច.ស.ទី៦ | MA11: ច.ស.ទី៧ | MB11: ច.ស.ទី៨ | MC11: ច.ស.ទី៩ | MD11: ច.ស.ទី១០ | ME11: ច.ស.ទី១១ | MF11: ច.ស.ទី១២ | MG11: ច.ស.ទី១៣ | MH11: ច.ស.ទី១៤ | MI11: ច.ស.ទី១៥ | MJ11: សរុប | MK11: ច.ស.ទី១ | ML11: ច.ស.ទី២ | MM11: ច.ស.ទី៣ | MN11: ច.ស.ទី៤ | MO11: ច.ស.ទី៥ | MP11: ច.ស.ទី៦ | MQ11: ច.ស.ទី៧ | MR11: ច.ស.ទី៨ | MS11: ច.ស.ទី៩ | MT11: ច.ស.ទី១០ | MU11: ច.ស.ទី១១ | MV11: ច.ស.ទី១២ | MW11: ច.ស.ទី១៣ | MX11: ច.ស.ទី១៤ | MY11: ច.ស.ទី១៥ | MZ11: សរុប | NA11: ច.ស.ទី១ | NB11: ច.ស.ទី២ | NC11: ច.ស.ទី៣ | ND11: ច.ស.ទី៤ | NE11: ច.ស.ទី៥ | NF11: ច.ស.ទី៦ | NG11: ច.ស.ទី៧ | NH11: ច.ស.ទី៨ | NI11: ច.ស.ទី៩ | NJ11: ច.ស.ទី១០ | NK11: ច.ស.ទី១១ | NL11: ច.ស.ទី១២ | NM11: ច.ស.ទី១៣ | NN11: ច.ស.ទី១៤ | NO11: ច.ស.ទី១៥ | NP11: សរុប | NQ11: ច.ស.ទី១ | NR11: ច.ស.ទី២ | NS11: ច.ស.ទី៣ | NT11: ច.ស.ទី៤ | NU11: ច.ស.ទី៥ | NV11: ច.ស.ទី៦ | NW11: ច.ស.ទី៧ | NX11: ច.ស.ទី៨ | NY11: ច.ស.ទី៩ | NZ11: ច.ស.ទី១០ | OA11: ច.ស.ទី១១ | OB11: ច.ស.ទី១២ | OC11: ច.ស.ទី១៣ | OD11: ច.ស.ទី១៤ | OE11: ច.ស.ទី១៥ | OF11: សរុប | OG11: ច.ស.ទី១ | OH11: ច.ស.ទី២ | OI11: ច.ស.ទី៣ | OJ11: ច.ស.ទី៤ | OK11: ច.ស.ទី៥ | OL11: ច.ស.ទី៦ | OM11: ច.ស.ទី៧ | ON11: ច.ស.ទី៨ | OO11: ច.ស.ទី៩ | OP11: ច.ស.ទី១០ | OQ11: ច.ស.ទី១១ | OR11: ច.ស.ទី១២ | OS11: ច.ស.ទី១៣ | OT11: ច.ស.ទី១៤ | OU11: ច.ស.ទី១៥ | OV11: សរុប | OW11: ច.ស.ទី១ | OX11: ច.ស.ទី២ | OY11: ច.ស.ទី៣ | OZ11: ច.ស.ទី៤ | PA11: ច.ស.ទី៥ | PB11: ច.ស.ទី៦ | PC11: ច.ស.ទី៧ | PD11: ច.ស.ទី៨ | PE11: ច.ស.ទី៩ | PF11: ច.ស.ទី១០ | PG11: ច.ស.ទី១១ | PH11: ច.ស.ទី១២ | PI11: ច.ស.ទី១៣ | PJ11: ច.ស.ទី១៤ | PK11: ច.ស.ទី១៥ | PL11: សរុប | PM11: ច.ស.ទី១ | PN11: ច.ស.ទី២ | PO11: ច.ស.ទី៣ | PP11: ច.ស.ទី៤ | PQ11: ច.ស.ទី៥ | PR11: ច.ស.ទី៦ | PS11: ច.ស.ទី៧ | PT11: ច.ស.ទី៨ | PU11: ច.ស.ទី៩ | PV11: ច.ស.ទី១០ | PW11: ច.ស.ទី១១ | PX11: ច.ស.ទី១២ | PY11: ច.ស.ទី១៣ | PZ11: ច.ស.ទី១៤ | QA11: ច.ស.ទី១៥ | QB11: សរុប | QC11: ច.ស.ទី១ | QD11: ច.ស.ទី២ | QE11: ច.ស.ទី៣ | QF11: ច.ស.ទី៤ | QG11: ច.ស.ទី៥ | QH11: ច.ស.ទី៦ | QI11: ច.ស.ទី៧ | QJ11: ច.ស.ទី៨ | QK11: ច.ស.ទី៩ | QL11: ច.ស.ទី១០ | QM11: ច.ស.ទី១១ | QN11: ច.ស.ទី១២ | QO11: ច.ស.ទី១៣ | QP11: ច.ស.ទី១៤ | QQ11: ច.ស.ទី១៥ | QR11: សរុប | QS11: ច.ស.ទី១ | QT11: ច.ស.ទី២ | QU11: ច.ស.ទី៣ | QV11: ច.ស.ទី៤ | QW11: ច.ស.ទី៥ | QX11: ច.ស.ទី៦ | QY11: ច.ស.ទី៧ | QZ11: ច.ស.ទី៨ | RA11: ច.ស.ទី៩ | RB11: ច.ស.ទី១០ | RC11: ច.ស.ទី១១ | RD11: ច.ស.ទី១២ | RE11: ច.ស.ទី១៣ | RF11: ច.ស.ទី១៤ | RG11: ច.ស.ទី១៥ | RH11: ច.ស.ទី១៦ | RI11: ច.ស.ទី១៧ | RJ11: ច.ស.ទី១៨ | RK11: ច.ស.ទី១៩ | RL11: ច.ស.ទី២០ | RM11: ច.ស.ទី២១ | RN11: ច.ស.ទី២២ | RO11: ច.ស.ទី២៣ | RP11: ច.ស.ទី២៤ | RQ11: ច.ស.ទី២៥ | RS11: សរុប | RT11: ច.ស.ទី១ | RU11: ច.ស.ទី២ | RV11: ច.ស.ទី៣ | RW11: ច.ស.ទី៤ | RX11: ច.ស.ទី៥ | RY11: ច.ស.ទី៦ | RZ11: ច.ស.ទី៧ | SA11: ច.ស.ទី៨ | SB11: ច.ស.ទី៩ | SC11: ច.ស.ទី១០ | SD11: ច.ស.ទី១១ | SE11: ច.ស.ទី១២ | SF11: ច.ស.ទី១៣ | SG11: ច.ស.ទី១៤ | SH11: ច.ស.ទី១៥ | SI11: សរុប | SJ11: ច.ស.ទី១ | SK11: ច.ស.ទី២ | SL11: ច.ស.ទី៣ | SM11: ច.ស.ទី៤ | SN11: ច.ស.ទី៥ | SO11: ច.ស.ទី៦ | SP11: ច.ស.ទី៧ | SQ11: ច.ស.ទី៨ | SR11: ច.ស.ទី៩ | SS11: ច.ស.ទី១០ | ST11: ច.ស.ទី១១ | SU11: ច.ស.ទី១២ | SV11: ច.ស.ទី១៣ | SW11: ច.ស.ទី១៤ | SX11: ច.ស.ទី១៥ | SY11: សរុប | SZ11: ច.ស.ទី១ | TA11: ច.ស.ទី២ | TB11: ច.ស.ទី៣ | TC11: ច.ស.ទី៤ | TD11: ច.ស.ទី៥ | TE11: ច.ស.ទី៦ | TF11: ច.ស.ទី៧ | TG11: ច.ស.ទី៨ | TH11: ច.ស.ទី៩ | TI11: ច.ស.ទី១០ | TJ11: ច.ស.ទី១១ | TK11: ច.ស.ទី១២ | TL11: ច.ស.ទី១៣ | TM11: ច.ស.ទី១៤ | TN11: ច.ស.ទី១៥ | TO11: សរុប | TP11: ច.ស.ទី១ | TQ11: ច.ស.ទី២ | TR11: ច.ស.ទី៣ | TS11: ច.ស.ទី៤ | TT11: ច.ស.ទី៥ | TU11: ច.ស.ទី៦ | TV11: ច.ស.ទី៧ | TW11: ច.ស.ទី៨ | TX11: ច.ស.ទី៩ | TY11: ច.ស.ទី១០ | TZ11: ច.ស.ទី១១ | UA11: ច.ស.ទី១២ | UB11: ច.ស.ទី១៣ | UC11: ច.ស.ទី១៤ | UD11: ច.ស.ទី១៥ | UE11: សរុប | UF11: ច.ស.ទី១ | UG11: ច.ស.ទី២ | UH11: ច.ស.ទី៣ | UI11: ច.ស.ទី៤ | UJ11: ច.ស.ទី៥ | UK11: ច.ស.ទី៦ | UL11: ច.ស.ទី៧ | UM11: ច.ស.ទី៨ | UN11: ច.ស.ទី៩ | UO11: ច.ស.ទី១០ | UP11: ច.ស.ទី១១ | UQ11: ច.ស.ទី១២ | UR11: ច.ស.ទី១៣ | US11: ច.ស.ទី១៤ | UT11: ច.ស.ទី១៥ | UU11: ច.ស.ទី១៦ | UV11: ច.ស.ទី១៧ | UW11: ច.ស.ទី១៨ | UX11: ច.ស.ទី១៩ | UY11: ច.ស.ទី២០ | UZ11: ច.ស.ទី២១ | VA11: ច.ស.ទី២២ | VB11: ច.ស.ទី២៣ | VC11: ច.ស.ទី២៤ | VD11: ច.ស.ទី២៥
A12: សរុបចំណាយថវិកាទូទៅរបស់រដ្ឋ (ក+ខ) | E12: =E13+E334 -> 0 | F12: =F13+F334 -> 0 | G12: =G13+G334 -> 0 | H12: =H13+H334 -> 0 | I12: =I13+I334 -> 0 | J12: =J13+J334 -> 0 | K12: =K13+K334 -> 0 | L12: =L13+L334 -> 0 | ... VD12: =VD13+VD334 -> 0 | VE12: =IF(SUM(E12:I12)<>0,"ok","-") -> -
A13: ក/.សរុបចំណាយចរន្ត (ក្រុមទី១+ក្រុមទី២) | E13: =E14+E315 -> 0 | F13: =F14+F315 -> 0 | G13: =G14+G315 -> 0 | H13: =H14+H315 -> 0 | I13: =I14+I315 -> 0 | J13: =J14+J315 -> 0 | K13: =K14+K315 -> 0 | L13: =L14+L315 -> 0 | ... VD13: =VD14+VD315 -> 0 | VE13: =IF(SUM(E13:I13)<>0,"ok","-") -> -
A14: ក្រុមទី១:ចំណាយពិត (ប្រភេទ១+២+៣+៤) | E14: =E15+E198+E212+E286 -> 0 | F14: =F15+F198+F212+F286 -> 0 | G14: =G15+G198+G212+G286 -> 0 | H14: =H15+H198+H212+H286 -> 0 | I14: =I15+I198+I212+I286 -> 0 | J14: =J15+J198+J212+J286 -> 0 | K14: =K15+K198+K212+K286 -> 0 | L14: =L15+L198+L212+L286 -> 0 | ... VD14: =VD15+VD198+VD212+VD286 -> 0 | VE14: =IF(SUM(E14:I14)<>0,"ok","-") -> -
A15: ប្រភេទទី១:មធ្យោបាយសេវា | E15: =E16+E60+E145 -> 0 | F15: =F16+F60+F145 -> 0 | G15: =G16+G60+G145 -> 0 | H15: =H16+H60+H145 -> 0 | I15: =I16+I60+I145 -> 0 | J15: =J16+J60+J145 -> 0 | K15: =K16+K60+K145 -> 0 | L15: =L16+L60+L145 -> 0 | ... VD15: =VD16+VD60+VD145 -> 0 | VE15: =IF(SUM(E15:I15)<>0,"ok","-") -> -
A16: 60 | D16: ការទិញ | E16: =E17+E24+E29+E38+E43+E50+E54+E58 -> 0 | F16: =F17+F24+F29+F38+F43+F50+F54+F58 -> 0 | G16: =G17+G24+G29+G38+G43+G50+G54+G58 -> 0 | H16: =H17+H24+H29+H38+H43+H50+H54+H58 -> 0 | I16: =I17+I24+I29+I38+I43+I50+I54+I58 -> 0 | J16: =J17+J24+J29+J38+J43+J50+J54+J58 -> 0 | K16: =K17+K24+K29+K38+K43+K50+K54+K58 -> 0 | L16: =L17+L24+L29+L38+L43+L50+L54+L58 -> 0 | ... VD16: =VD17+VD24+VD29+VD38+VD43+VD50+VD54+VD58 -> 0 | VE16: =IF(SUM(E16:I16)<>0,"ok","-") -> -
B17: 6001 | D17: សម្ភារផ្គត់ផ្គង់ថែទាំ | E17: =SUM(E18:E23) -> 0 | F17: =SUM(F18:F23) -> 0 | G17: =SUM(G18:G23) -> 0 | H17: =SUM(H18:H23) -> 0 | I17: =SUM(I18:I23) -> 0 | J17: =SUM(J18:J23) -> 0 | K17: =SUM(K18:K23) -> 0 | L17: =SUM(L18:L23) -> 0 | ... VD17: =SUM(VD18:VD23) -> 0 | VE17: =IF(SUM(E17:I17)<>0,"ok","-") -> -
C18: 60011 | D18: សម្ភារផ្គត់ផ្គង់សម្អាតនិងអនាម័យ | E18: =H18+HO18 -> 0 | H18: =I18+CV18 -> 0 | I18: =J18+Z18+AP18+BF18+BV18 -> 0 | J18: =SUM(K18:Y18) -> 0 | Z18: =SUM(AA18:AO18) -> 0 | AP18: =SUM(AQ18:BE18) -> 0 | BF18: =SUM(BG18:BU18) -> 0 | BV18: =SUM(BW18:CU18) -> 0 | CV18: =CW18+DM18+EC18+ES18+FI18+FY18+GO18 -> 0 | CW18: =SUM(CX18:DL18) -> 0 | DM18: =SUM(DN18:EB18) -> 0 | EC18: =SUM(ED18:ER18) -> 0 | ES18: =SUM(ET18:FH18) -> 0 | FI18: =SUM(FJ18:FX18) -> 0 | FY18: =SUM(FZ18:GN18) -> 0 | GO18: =SUM(GP18:HN18) -> 0 | HO18: =HP18+LC18+RR18 -> 0 | HP18: =HQ18+IG18+IW18+JM18+KC18 -> 0 | HQ18: =SUM(HR18:IF18) -> 0 | IG18: =SUM(IH18:IV18) -> 0 | IW18: =SUM(IX18:JL18) -> 0 | JM18: =SUM(JN18:KB18) -> 0 | KC18: =SUM(KD18:LB18) -> 0 | LC18: =LD18+LT18+MJ18+MZ18+NP18+OF18+OV18+PL18+QB18+QR18 -> 0 | LD18: =SUM(LE18:LS18) -> 0 | LT18: =SUM(LU18:MI18) -> 0 | MJ18: =SUM(MK18:MY18) -> 0 | MZ18: =SUM(NA18:NO18) -> 0 | NP18: =SUM(NQ18:OE18) -> 0 | OF18: =SUM(OG18:OU18) -> 0 | OV18: =SUM(OW18:PK18) -> 0 | PL18: =SUM(PM18:QA18) -> 0 | QB18: =SUM(QC18:QQ18) -> 0 | QR18: =SUM(QS18:RQ18) -> 0 | RR18: =RS18+SI18+SY18+TO18+UE18 -> 0 | RS18: =SUM(RT18:SH18) -> 0 | SI18: =SUM(SJ18:SX18) -> 0 | SY18: =SUM(SZ18:TN18) -> 0 | TO18: =SUM(TP18:UD18) -> 0 | UE18: =SUM(UF18:VD18) -> 0 | VE18: =IF(SUM(E18:I18)<>0,"ok","-") -> -
C19: 60012 | D19: សម្ភារផ្គត់ផ្គង់សម្រាប់ថែទាំអគារ ប្រាសាទ និងសំណង់ផ្សេងៗ | E19: =SUM(F19:I19) -> 0 | J19: =SUM(K19:Y19) -> 0 | Z19: =SUM(AA19:AO19) -> 0 | AP19: =SUM(AQ19:BE19) -> 0 | BF19: =SUM(BG19:BU19) -> 0 | BV19: =SUM(BW19:CU19) -> 0 | CW19: =SUM(CX19:DL19) -> 0 | DM19: =SUM(DN19:EB19) -> 0 | EC19: =SUM(ED19:ER19) -> 0 | ES19: =SUM(ET19:FH19) -> 0 | FI19: =SUM(FJ19:FX19) -> 0 | FY19: =SUM(FZ19:GN19) -> 0 | GO19: =SUM(GP19:HN19) -> 0 | HQ19: =SUM(HR19:IF19) -> 0 | IG19: =SUM(IH19:IV19) -> 0 | IW19: =SUM(IX19:JL19) -> 0 | JM19: =SUM(JN19:KB19) -> 0 | KC19: =SUM(KD19:LB19) -> 0 | LD19: =SUM(LE19:LS19) -> 0 | LT19: =SUM(LU19:MI19) -> 0 | MJ19: =SUM(MK19:MY19) -> 0 | MZ19: =SUM(NA19:NO19) -> 0 | NP19: =SUM(NQ19:OE19) -> 0 | OF19: =SUM(OG19:OU19) -> 0 | OV19: =SUM(OW19:PK19) -> 0 | PL19: =SUM(PM19:QA19) -> 0 | QB19: =SUM(QC19:QQ19) -> 0 | QR19: =SUM(QS19:RQ19) -> 0 | RS19: =SUM(RT19:SH19) -> 0 | SI19: =SUM(SJ19:SX19) -> 0 | SY19: =SUM(SZ19:TN19) -> 0 | TO19: =SUM(TP19:UD19) -> 0 | UE19: =SUM(UF19:VD19) -> 0 | VE19: =IF(SUM(E19:I19)<>0,"ok","-") -> -
